Workbook

Sheet README
A1: International Tax Competitiveness Index — Working Excel Calculator
A3: Replicates the Tax Foundation's ITCI scoring methodology (github.com/TaxFoundation/international-tax-competitiveness-index, R_code_files/08_index_calculations.R) as live, formula-driven Excel sheets — no VBA, no add-ins. Entirely closed-form (z-scores, averages, min/max rescale); no eigen-decomposition or iterative engine needed anywhere.
A5: Color legend
A6: Amber cells = GIVEN (2025 ITCI input data, from the Tax Foundation's own repo)
A7: Teal cells = LIVE (formulas; recalculate automatically)
A9: Validated
A10: Every stage (subcategories, categories, final score) matches the Tax Foundation's own real 2025 ground-truth output files to floating-point precision (<1e-13) for all 38 countries — see itci_core.py and scratch/validate.py in the companion Python project. Two real bugs were caught and fixed during validation: (1) corporate_other_rev/personal_other_rev need ABS() before z-scoring (Sweden has a negative personal_other_rev, off by 0.33/100 without the fix), and (2) categories must be computed from the RAW (pre-rescale) subcategory z-averages, not the rescaled 0-100 subcategory values — confirmed empirically against categories_score.csv since the R script reuses one variable name for both versions, making it ambiguous from the code alone.
A12: Pipeline
A13: 1. ZScores: z = (x-AVERAGE)/STDEV across the 38-country cross-section, per variable. corporate_other_rev/personal_other_rev use ABS(x) first. 30 "higher=worse" variables (rates, surtaxes, withholding taxes, restrictive rules) then multiplied by -1.
A14: 2. Subcategories: equal-weighted average of the relevant z-scores, one column per subcategory (15 total).
A15: 3. SubcategoriesScored: score2() rescale — shift so MIN becomes 1, scale so MAX becomes 100 — applied independently to each subcategory.
A16: 4. Categories: equal-weighted average of the RAW (pre-score2) subcategory scores, one column per category (5 total: corporate, consumption, property, income, cross_border).
... A21: Overwrite the amber GIVEN cells on RawData with updated variable values (same 38 countries, or add/remove rows). Everything downstream — z-scores, subcategories, categories, final score, ranks, chart — recalculates automatically. This is exactly how the Tax Foundation's own repo supports testing tax-reform scenarios (README: "modify tax variables ... re-run ... compare against baseline").

Sheet RawData
A1: Raw Data (GIVEN) — 38 countries x 42 variables, 2025 ITCI input data
A2: country | B2: corporate_rate | C2: loss_carryback | D2: loss_carryforward | E2: machines_cost_recovery | F2: buildings_cost_recovery | G2: intangibles_cost_recovery | H2: inventory | I2: allowance_corporate_equity | J2: patent_box | K2: r_and_d_credit | L2: digital_services_tax | M2: corporate_alt_minimum | N2: corporate_surtax | O2: corporate_other_rev | P2: top_income_rate | Q2: threshold_top_income_rate | R2: tax_wedge | S2: personal_surtax | T2: personal_other_rev | U2: capital_gains_rate | V2: dividends_rate | W2: vat_rate | X2: vat_threshold | Y2: vat_base | Z2: property_tax | AA2: property_tax_collections | AB2: net_wealth | AC2: estate_or_inheritance_tax | AD2: transfer_tax | AE2: asset_tax | AF2: capital_duties | AG2: financial_transaction_tax | AH2: dividends_exemption | AI2: capital_gains_exemption | AJ2: country_limitations | AK2: dividends_withholding_tax | AL2: interest_withholding_tax | AM2: royalties_withholding_tax | AN2: tax_treaties | AO2: cfc_rules | AP2: thin_capitalization_rules | AQ2: minimum_tax
A3: Austria | B3: 0.23 | C3: 0 | D3: 75 | E3: 0.88436503 | F3: 0.33847473 | G3: 0.7378887 | H3: 1 | I3: 0 | J3: 0 | K3: 0.17 | L3: 1 | M3: 3 | N3: 0 | O3: 0.278569 | P3: 0.55 | Q3: 17.80329 | R3: 1.1311761 | S3: 0 | T3: 0 | U3: 0.275 | V3: 0.275 | W3: 20 | X3: 75017.424 | Y3: 0.61997648 | Z3: 0 | AA3: 0.11045113 | AB3: 0 | AC3: 0 | AD3: 1 | AE3: 1 | AF3: 0 | AG3: 0 | AH3: 1 | AI3: 1 | AJ3: 0 | AK3: 0.275 | AL3: 0 | AM3: 0.2 | AN3: 89 | AO3: 0.66666667 | AP3: 1 | AQ3: 1
A4: Australia | B4: 0.3 | C4: 0 | D4: 100 | E4: 0.85148497 | F4: 0.47931867 | G4: 0.54795391 | H4: 0.5 | I4: 0 | J4: 0 | K4: 0.1525 | L4: 0 | M4: 3 | N4: 0 | O4: 0 | P4: 0.47 | Q4: 1.73421 | R4: 1.3329211 | S4: 0 | T4: 0 | U4: 0.235 | V4: 0.24285714 | W4: 10 | X4: 54350.307 | Y4: 0.45951336 | Z4: 1 | AA4: 0.036917013 | AB4: 0 | AC4: 0 | AD4: 1 | AE4: 1 | AF4: 0 | AG4: 0 | AH4: 1 | AI4: 1 | AJ4: 0 | AK4: 0.3 | AL4: 0.1 | AM4: 0.3 | AN4: 48 | AO4: 0.33333333 | AP4: 1 | AQ4: 1
A5: Belgium | B5: 0.25 | C5: 0 | D5: 70 | E5: 0.86986525 | F5: 0.54795391 | G5: 0.86986525 | H5: 1 | I5: 0 | J5: 1 | K5: 0.155 | L5: 0 | M5: 2 | N5: 0 | O5: 0.018283 | P5: 0.60172143 | Q5: 1.022341 | R5: 1.2813917 | S5: 0 | T5: 0 | U5: 0 | V5: 0.3 | W5: 21 | X5: 34879.957 | Y5: 0.43331369 | Z5: 0.5 | AA5: 0.76110655 | AB5: 0.5 | AC5: 1 | AD5: 1 | AE5: 1 | AF5: 0 | AG5: 1 | AH5: 1 | AI5: 1 | AJ5: 0 | AK5: 0.3 | AL5: 0.3 | AM5: 0.3 | AN5: 95 | AO5: 0.66666667 | AP5: 1 | AQ5: 1
A6: Canada | B6: 0.25981152 | C6: 3 | D6: 20 | E6: 0.9673913 | F6: 0.625 | G6: 0.51896552 | H6: 0.5 | I6: 0 | J6: 0 | K6: 0.2125 | L6: 0 | M6: 2 | N6: 0 | O6: 0.444411 | P6: 0.535296 | Q6: 2.802078 | R6: 1.2197173 | S6: 0 | T6: 0 | U6: 0.2675 | V6: 0.39343524 | W6: 12.3 | X6: 26420.405 | Y6: 0.52674595 | Z6: 0.5 | AA6: 1.2084102 | AB6: 0 | AC6: 0 | AD6: 1 | AE6: 1 | AF6: 1 | AG6: 0 | AH6: 1 | AI6: 0.5 | AJ6: 1 | AK6: 0.25 | AL6: 0.25 | AM6: 0.25 | AN6: 96 | AO6: 0.33333333 | AP6: 0.5 | AQ6: 1
A7: Switzerland | B7: 0.19607821 | C7: 0 | D7: 7 | E7: 0.86 | F7: 0.55483871 | G7: 0.90526316 | H7: 1 | I7: 0 | J7: 1 | K7: -0.01 | L7: 1 | M7: 1 | N7: 0 | O7: 1.077651 | P7: 0.4141 | Q7: 3.122135 | R7: 1.3383172 | S7: 0 | T7: 0 | U7: 0 | V7: 0.22155 | W7: 8.1 | X7: 102786.65 | Y7: 0.68135293 | Z7: 0.5 | AA7: 0.095367028 | AB7: 1 | AC7: 1 | AD7: 1 | AE7: 1 | AF7: 1 | AG7: 1 | AH7: 1 | AI7: 1 | AJ7: 0 | AK7: 0.35 | AL7: 0.35 | AM7: 0 | AN7: 110 | AO7: 0 | AP7: 0.5 | AQ7: 0.5
A8: Chile | B8: 0.27 | C8: 0 | D8: 100 | E8: 0.63261166 | F8: 0.33847473 | G8: 0 | H8: 0.5 | I8: 0 | J8: 0 | K8: 0.275 | L8: 0 | M8: 0 | N8: 0 | O8: 0.107049 | P8: 0.40000001 | Q8: 17.951571 | R8: 1.214444 | S8: 0 | T8: 0 | U8: 0.4 | V8: 0.2390411 | W8: 19 | X8: 0 | Y8: 0.67226555 | Z8: 0.5 | AA8: 0.00088103 | AB8: 0 | AC8: 1 | AD8: 0 | AE8: 1 | AF8: 0 | AG8: 0 | AH8: 0 | AI8: 0 | AJ8: 1 | AK8: 0.35 | AL8: 0.35 | AM8: 0.3 | AN8: 37 | AO8: 0.5 | AP8: 0.5 | AQ8: 0
A9: Colombia | B9: 0.35 | C9: 0 | D9: 12 | E9: 0.7378887 | F9: 0.30595653 | G9: 0.86986525 | H9: 0.5 | I9: 0 | J9: 0 | K9: 0.0725 | L9: 1 | M9: 3 | N9: 0 | O9: 0.086333 | P9: 0.38999999 | Q9: 50.77305 | R9: 0 | S9: 0 | T9: 1.613716 | U9: 0.15 | V9: 0.2 | W9: 19 | X9: 0 | Y9: 0.38530428 | Z9: 0.5 | AA9: 0.000142808 | AB9: 1 | AC9: 1 | AD9: 1 | AE9: 0 | AF9: 1 | AG9: 1 | AH9: 0 | AI9: 0 | AJ9: 0 | AK9: 0.2 | AL9: 0.2 | AM9: 0.2 | AN9: 14 | AO9: 0.66666667 | AP9: 0.5 | AQ9: 0
A10: Costa Rica | B10: 0.3 | C10: 0 | D10: 3 | E10: 0.82245669 | F10: 0.27895845 | G10: 0.7378887 | H10: 0.5 | I10: 0 | J10: 0 | K10: -0.02 | L10: 0 | M10: 5 | N10: 0 | O10: 1.212838 | P10: 0.33615205 | Q10: 6.865182 | R10: 1.0643568 | S10: 0 | T10: 7.993262 | U10: 0.15 | V10: 0.15 | W10: 13 | X10: 0 | Y10: 0.50135879 | Z10: 0.5 | AA10: 0.000505989 | AB10: 0 | AC10: 0 | AD10: 1 | AE10: 1 | AF10: 0 | AG10: 1 | AH10: 1 | AI10: 1 | AJ10: 0 | AK10: 0.15 | AL10: 0.15 | AM10: 0.25 | AN10: 4 | AO10: 0 | AP10: 1 | AQ10: 0
A11: Czech Republic | B11: 0.21 | C11: 2 | D11: 5 | E11: 0.87387911 | F11: 0.54322283 | G11: 0.84131885 | H11: 0.5 | I11: 0 | J11: 0 | K11: 0.205 | L11: 0 | M11: 1 | N11: 0 | O11: 0 | P11: 0.346 | Q11: 2.879198 | R11: 1.1058366 | S11: 0 | T11: 0 | U11: 0.23 | V11: 0.23 | W11: 21 | X11: 154336.46 | Y11: 0.5994904 | Z11: 0.5 | AA11: 0.004302784 | AB11: 0 | AC11: 1 | AD11: 0 | AE11: 0 | AF11: 0 | AG11: 0 | AH11: 1 | AI11: 1 | AJ11: 1 | AK11: 0.15 | AL11: 0.15 | AM11: 0.15 | AN11: 98 | AO11: 0.33333333 | AP11: 1 | AQ11: 1
A12: Germany | B12: 0.30058462 | C12: 2 | D12: 70 | E12: 0.87651404 | F12: 0.39140601 | G12: 0.86986525 | H12: 1 | I12: 0 | J12: 0 | K12: 0.2625 | L12: 0 | M12: 1 | N12: 1 | O12: 0 | P12: 0.47475 | Q12: 4.654217 | R12: 1.0615432 | S12: 1 | T12: 0 | U12: 0.26375 | V12: 0.26375 | W12: 19 | X12: 35060.901 | Y12: 0.53475626 | Z12: 0.5 | AA12: 0.23305556 | AB12: 0 | AC12: 1 | AD12: 1 | AE12: 0 | AF12: 0 | AG12: 0 | AH12: 0.95 | AI12: 0.95 | AJ12: 0 | AK12: 0.26375 | AL12: 0 | AM12: 0.15825 | AN12: 95 | AO12: 0.33333333 | AP12: 1 | AQ12: 1
A13: Denmark | B13: 0.22 | C13: 0 | D13: 60 | E13: 0.82692308 | F13: 0.39140601 | G13: 0.81340644 | H13: 0 | I13: 0 | J13: 0 | K13: 0.01 | L13: 1 | M13: 1 | N13: 0 | O13: 0.517328 | P13: 0.559044 | Q13: 1.257352 | R13: 1.2214928 | S13: 0 | T13: 0 | U13: 0.42 | V13: 0.42 | W13: 25 | X13: 8025.5753 | Y13: 0.62634992 | Z13: 0.5 | AA13: 0.10983206 | AB13: 0 | AC13: 1 | AD13: 1 | AE13: 0 | AF13: 0 | AG13: 0 | AH13: 1 | AI13: 1 | AJ13: 1 | AK13: 0.27 | AL13: 0.22 | AM13: 0.22 | AN13: 77 | AO13: 0.66666667 | AP13: 1 | AQ13: 1
A14: Estonia | B14: 0.22 | C14: 100 | D14: 100 | E14: 1 | F14: 1 | G14: 1 | H14: 1 | I14: 1 | J14: 0 | K14: 0.04 | L14: 0 | M14: 1 | N14: 0 | O14: 0 | P14: 0.2 | Q14: 0.333272 | R14: 1.2442788 | S14: 0 | T14: 0 | U14: 0.22 | V14: 0 | W14: 24 | X14: 68524.597 | Y14: 0.69983246 | Z14: 1 | AA14: 0.11156757 | AB14: 0 | AC14: 0 | AD14: 0 | AE14: 0 | AF14: 0 | AG14: 0 | AH14: 1 | AI14: 1 | AJ14: 1 | AK14: 0 | AL14: 0 | AM14: 0.1 | AN14: 63 | AO14: 0.33333333 | AP14: 1 | AQ14: 0
... A40: United States | B40: 0.25569714 | C40: 0 | D40: 80 | E40: 1 | F40: 1 | G40: 0.63275134 | H40: 1 | I40: 0 | J40: 1 | K40: 0.0275 | L40: 0 | M40: 2 | N40: 0 | O40: 0 | P40: 0.46 | Q40: 8.834464 | R40: 1.2495081 | S40: 0 | T40: 0 | U40: 0.2887 | V40: 0.28666715 | W40: 7.5 | X40: 0 | Y40: 0.35887465 | Z40: 0.5 | AA40: 1.8121467 | AB40: 0 | AC40: 1 | AD40: 1 | AE40: 1 | AF40: 0 | AG40: 0 | AH40: 1 | AI40: 0 | AJ40: 0 | AK40: 0.3 | AL40: 0.3 | AM40: 0.3 | AN40: 64 | AO40: 0.33333333 | AP40: 1 | AQ40: 1

Sheet AbsValues
A1: ABS() of corporate_other_rev / personal_other_rev (LIVE)
A2: country | B2: corporate_other_rev | C2: personal_other_rev
A3: =RawData!A3 -> Austria | B3: =ABS(RawData!O3) -> 0.278569 | C3: =ABS(RawData!T3) -> 0
A4: =RawData!A4 -> Australia | B4: =ABS(RawData!O4) -> 0 | C4: =ABS(RawData!T4) -> 0
A5: =RawData!A5 -> Belgium | B5: =ABS(RawData!O5) -> 0.018283 | C5: =ABS(RawData!T5) -> 0
A6: =RawData!A6 -> Canada | B6: =ABS(RawData!O6) -> 0.444411 | C6: =ABS(RawData!T6) -> 0
A7: =RawData!A7 -> Switzerland | B7: =ABS(RawData!O7) -> 1.077651 | C7: =ABS(RawData!T7) -> 0
A8: =RawData!A8 -> Chile | B8: =ABS(RawData!O8) -> 0.107049 | C8: =ABS(RawData!T8) -> 0
A9: =RawData!A9 -> Colombia | B9: =ABS(RawData!O9) -> 0.086333 | C9: =ABS(RawData!T9) -> 1.613716
A10: =RawData!A10 -> Costa Rica | B10: =ABS(RawData!O10) -> 1.212838 | C10: =ABS(RawData!T10) -> 7.993262
A11: =RawData!A11 -> Czech Republic | B11: =ABS(RawData!O11) -> 0 | C11: =ABS(RawData!T11) -> 0
A12: =RawData!A12 -> Germany | B12: =ABS(RawData!O12) -> 0 | C12: =ABS(RawData!T12) -> 0
A13: =RawData!A13 -> Denmark | B13: =ABS(RawData!O13) -> 0.517328 | C13: =ABS(RawData!T13) -> 0
A14: =RawData!A14 -> Estonia | B14: =ABS(RawData!O14) -> 0 | C14: =ABS(RawData!T14) -> 0
... A40: =RawData!A40 -> United States | B40: =ABS(RawData!O40) -> 0 | C40: =ABS(RawData!T40) -> 0

Sheet ZScores
A1: Z-Scores (LIVE)
A2: z = (x - AVERAGE) / STDEV, across the country cross-section. corporate_other_rev/personal_other_rev use ABS(x) first (can be recorded as a negative revenue-impact figure). 30 variables then sign-flipped (*-1) so a higher z-score always means more competitive.
A3: country | B3: corporate_rate | C3: loss_carryback | D3: loss_carryforward | E3: machines_cost_recovery | F3: buildings_cost_recovery | G3: intangibles_cost_recovery | H3: inventory | I3: allowance_corporate_equity | J3: patent_box | K3: r_and_d_credit | L3: digital_services_tax | M3: corporate_alt_minimum | N3: corporate_surtax | O3: corporate_other_rev | P3: top_income_rate | Q3: threshold_top_income_rate | R3: tax_wedge | S3: personal_surtax | T3: personal_other_rev | U3: capital_gains_rate | V3: dividends_rate | W3: vat_rate | X3: vat_threshold | Y3: vat_base | Z3: property_tax | AA3: property_tax_collections | AB3: net_wealth | AC3: estate_or_inheritance_tax | AD3: transfer_tax | AE3: asset_tax | AF3: capital_duties | AG3: financial_transaction_tax | AH3: dividends_exemption | AI3: capital_gains_exemption | AJ3: country_limitations | AK3: dividends_withholding_tax | AL3: interest_withholding_tax | AM3: royalties_withholding_tax | AN3: tax_treaties | AO3: cfc_rules | AP3: thin_capitalization_rules | AQ3: minimum_tax
A4: =RawData!A3 -> Austria | B4: =-1*((RawData!B3-AVERAGE(RawData!$B$3:$B$40))/STDEV(RawData!$B$3:$B$40)) -> 0.21976872 | C4: =((RawData!C3-AVERAGE(RawData!$C$3:$C$40))/STDEV(RawData!$C$3:$C$40)) -> -0.24662998 | D4: =((RawData!D3-AVERAGE(RawData!$D$3:$D$40))/STDEV(RawData!$D$3:$D$40)) -> 0.71668063 | E4: =((RawData!E3-AVERAGE(RawData!$E$3:$E$40))/STDEV(RawData!$E$3:$E$40)) -> 0.33941188 | F4: =((RawData!F3-AVERAGE(RawData!$F$3:$F$40))/STDEV(RawData!$F$3:$F$40)) -> -0.82888336 | G4: =((RawData!G3-AVERAGE(RawData!$G$3:$G$40))/STDEV(RawData!$G$3:$G$40)) -> -0.16428036 | H4: =((RawData!H3-AVERAGE(RawData!$H$3:$H$40))/STDEV(RawData!$H$3:$H$40)) -> 1.1791342 | I4: =((RawData!I3-AVERAGE(RawData!$I$3:$I$40))/STDEV(RawData!$I$3:$I$40)) -> -0.38409362 | J4: =-1*((RawData!J3-AVERAGE(RawData!$J$3:$J$40))/STDEV(RawData!$J$3:$J$40)) -> 0.9361174 | K4: =-1*((RawData!K3-AVERAGE(RawData!$K$3:$K$40))/STDEV(RawData!$K$3:$K$40)) -> -0.088694085 | L4: =-1*((RawData!L3-AVERAGE(RawData!$L$3:$L$40))/STDEV(RawData!$L$3:$L$40)) -> -1.4524631 | M4: =-1*((RawData!M3-AVERAGE(RawData!$M$3:$M$40))/STDEV(RawData!$M$3:$M$40)) -> -0.80926387 | N4: =-1*((RawData!N3-AVERAGE(RawData!$N$3:$N$40))/STDEV(RawData!$N$3:$N$40)) -> 0.33845396 | O4: =-1*((AbsValues!B3-AVERAGE(AbsValues!$B$3:$B$40))/STDEV(AbsValues!$B$3:$B$40)) -> 0.044741031 | P4: =-1*((RawData!P3-AVERAGE(RawData!$P$3:$P$40))/STDEV(RawData!$P$3:$P$40)) -> -0.95276284 | Q4: =-1*((RawData!Q3-AVERAGE(RawData!$Q$3:$Q$40))/STDEV(RawData!$Q$3:$Q$40)) -> -1.1429712 | R4: =-1*((RawData!R3-AVERAGE(RawData!$R$3:$R$40))/STDEV(RawData!$R$3:$R$40)) -> 0.40224409 | S4: =-1*((RawData!S3-AVERAGE(RawData!$S$3:$S$40))/STDEV(RawData!$S$3:$S$40)) -> 0.33845396 | T4: =-1*((AbsValues!C3-AVERAGE(AbsValues!$C$3:$C$40))/STDEV(AbsValues!$C$3:$C$40)) -> 0.32073762 | U4: =-1*((RawData!U3-AVERAGE(RawData!$U$3:$U$40))/STDEV(RawData!$U$3:$U$40)) -> -0.56879446 | V4: =-1*((RawData!V3-AVERAGE(RawData!$V$3:$V$40))/STDEV(RawData!$V$3:$V$40)) -> -0.24291245 | W4: =-1*((RawData!W3-AVERAGE(RawData!$W$3:$W$40))/STDEV(RawData!$W$3:$W$40)) -> -0.12455652 | X4: =-1*((RawData!X3-AVERAGE(RawData!$X$3:$X$40))/STDEV(RawData!$X$3:$X$40)) -> -0.39047243 | Y4: =((RawData!Y3-AVERAGE(RawData!$Y$3:$Y$40))/STDEV(RawData!$Y$3:$Y$40)) -> 0.52626463 | Z4: =((RawData!Z3-AVERAGE(RawData!$Z$3:$Z$40))/STDEV(RawData!$Z$3:$Z$40)) -> -2.1543217 | AA4: =-1*((RawData!AA3-AVERAGE(RawData!$AA$3:$AA$40))/STDEV(RawData!$AA$3:$AA$40)) -> 0.52679341 | AB4: =-1*((RawData!AB3-AVERAGE(RawData!$AB$3:$AB$40))/STDEV(RawData!$AB$3:$AB$40)) -> 0.44275606 | AC4: =-1*((RawData!AC3-AVERAGE(RawData!$AC$3:$AC$40))/STDEV(RawData!$AC$3:$AC$40)) -> 1.4524631 | AD4: =-1*((RawData!AD3-AVERAGE(RawData!$AD$3:$AD$40))/STDEV(RawData!$AD$3:$AD$40)) -> -0.42727718 | AE4: =-1*((RawData!AE3-AVERAGE(RawData!$AE$3:$AE$40))/STDEV(RawData!$AE$3:$AE$40)) -> -0.9361174 | AF4: =-1*((RawData!AF3-AVERAGE(RawData!$AF$3:$AF$40))/STDEV(RawData!$AF$3:$AF$40)) -> 0.58969853 | AG4: =-1*((RawData!AG3-AVERAGE(RawData!$AG$3:$AG$40))/STDEV(RawData!$AG$3:$AG$40)) -> 0.79687605 | AH4: =((RawData!AH3-AVERAGE(RawData!$AH$3:$AH$40))/STDEV(RawData!$AH$3:$AH$40)) -> 0.32819245 | AI4: =((RawData!AI3-AVERAGE(RawData!$AI$3:$AI$40))/STDEV(RawData!$AI$3:$AI$40)) -> 0.55436816 | AJ4: =-1*((RawData!AJ3-AVERAGE(RawData!$AJ$3:$AJ$40))/STDEV(RawData!$AJ$3:$AJ$40)) -> 0.98675438 | AK4: =-1*((RawData!AK3-AVERAGE(RawData!$AK$3:$AK$40))/STDEV(RawData!$AK$3:$AK$40)) -> -0.70469318 | AL4: =-1*((RawData!AL3-AVERAGE(RawData!$AL$3:$AL$40))/STDEV(RawData!$AL$3:$AL$40)) -> 1.2947279 | AM4: =-1*((RawData!AM3-AVERAGE(RawData!$AM$3:$AM$40))/STDEV(RawData!$AM$3:$AM$40)) -> -0.24215868 | AN4: =((RawData!AN3-AVERAGE(RawData!$AN$3:$AN$40))/STDEV(RawData!$AN$3:$AN$40)) -> 0.49219182 | AO4: =-1*((RawData!AO3-AVERAGE(RawData!$AO$3:$AO$40))/STDEV(RawData!$AO$3:$AO$40)) -> -1.3355779 | AP4: =-1*((RawData!AP3-AVERAGE(RawData!$AP$3:$AP$40))/STDEV(RawData!$AP$3:$AP$40)) -> -0.48376743 | AQ4: =-1*((RawData!AQ3-AVERAGE(RawData!$AQ$3:$AQ$40))/STDEV(RawData!$AQ$3:$AQ$40)) -> -0.68274065
A5: =RawData!A4 -> Australia | B5: =-1*((RawData!B4-AVERAGE(RawData!$B$3:$B$40))/STDEV(RawData!$B$3:$B$40)) -> -1.0631397 | C5: =((RawData!C4-AVERAGE(RawData!$C$3:$C$40))/STDEV(RawData!$C$3:$C$40)) -> -0.24662998 | D5: =((RawData!D4-AVERAGE(RawData!$D$3:$D$40))/STDEV(RawData!$D$3:$D$40)) -> 1.3509999 | E5: =((RawData!E4-AVERAGE(RawData!$E$3:$E$40))/STDEV(RawData!$E$3:$E$40)) -> -0.065238195 | F5: =((RawData!F4-AVERAGE(RawData!$F$3:$F$40))/STDEV(RawData!$F$3:$F$40)) -> -0.10047078 | G5: =((RawData!G4-AVERAGE(RawData!$G$3:$G$40))/STDEV(RawData!$G$3:$G$40)) -> -1.2377336 | H5: =((RawData!H4-AVERAGE(RawData!$H$3:$H$40))/STDEV(RawData!$H$3:$H$40)) -> -0.2662561 | I5: =((RawData!I4-AVERAGE(RawData!$I$3:$I$40))/STDEV(RawData!$I$3:$I$40)) -> -0.38409362 | J5: =-1*((RawData!J4-AVERAGE(RawData!$J$3:$J$40))/STDEV(RawData!$J$3:$J$40)) -> 0.9361174 | K5: =-1*((RawData!K4-AVERAGE(RawData!$K$3:$K$40))/STDEV(RawData!$K$3:$K$40)) -> 0.064504789 | L5: =-1*((RawData!L4-AVERAGE(RawData!$L$3:$L$40))/STDEV(RawData!$L$3:$L$40)) -> 0.6703676 | M5: =-1*((RawData!M4-AVERAGE(RawData!$M$3:$M$40))/STDEV(RawData!$M$3:$M$40)) -> -0.80926387 | N5: =-1*((RawData!N4-AVERAGE(RawData!$N$3:$N$40))/STDEV(RawData!$N$3:$N$40)) -> 0.33845396 | O5: =-1*((AbsValues!B4-AVERAGE(AbsValues!$B$3:$B$40))/STDEV(AbsValues!$B$3:$B$40)) -> 0.59391264 | P5: =-1*((RawData!P4-AVERAGE(RawData!$P$3:$P$40))/STDEV(RawData!$P$3:$P$40)) -> -0.09193706 | Q5: =-1*((RawData!Q4-AVERAGE(RawData!$Q$3:$Q$40))/STDEV(RawData!$Q$3:$Q$40)) -> 0.57078064 | R5: =-1*((RawData!R4-AVERAGE(RawData!$R$3:$R$40))/STDEV(RawData!$R$3:$R$40)) -> -0.38675428 | S5: =-1*((RawData!S4-AVERAGE(RawData!$S$3:$S$40))/STDEV(RawData!$S$3:$S$40)) -> 0.33845396 | T5: =-1*((AbsValues!C4-AVERAGE(AbsValues!$C$3:$C$40))/STDEV(AbsValues!$C$3:$C$40)) -> 0.32073762 | U5: =-1*((RawData!U4-AVERAGE(RawData!$U$3:$U$40))/STDEV(RawData!$U$3:$U$40)) -> -0.26627597 | V5: =-1*((RawData!V4-AVERAGE(RawData!$V$3:$V$40))/STDEV(RawData!$V$3:$V$40)) -> 0.038335188 | W5: =-1*((RawData!W4-AVERAGE(RawData!$W$3:$W$40))/STDEV(RawData!$W$3:$W$40)) -> 1.7994873 | X5: =-1*((RawData!X4-AVERAGE(RawData!$X$3:$X$40))/STDEV(RawData!$X$3:$X$40)) -> 0.034288031 | Y5: =((RawData!Y4-AVERAGE(RawData!$Y$3:$Y$40))/STDEV(RawData!$Y$3:$Y$40)) -> -0.769383 | Z5: =((RawData!Z4-AVERAGE(RawData!$Z$3:$Z$40))/STDEV(RawData!$Z$3:$Z$40)) -> 2.5236339 | AA5: =-1*((RawData!AA4-AVERAGE(RawData!$AA$3:$AA$40))/STDEV(RawData!$AA$3:$AA$40)) -> 0.65847877 | AB5: =-1*((RawData!AB4-AVERAGE(RawData!$AB$3:$AB$40))/STDEV(RawData!$AB$3:$AB$40)) -> 0.44275606 | AC5: =-1*((RawData!AC4-AVERAGE(RawData!$AC$3:$AC$40))/STDEV(RawData!$AC$3:$AC$40)) -> 1.4524631 | AD5: =-1*((RawData!AD4-AVERAGE(RawData!$AD$3:$AD$40))/STDEV(RawData!$AD$3:$AD$40)) -> -0.42727718 | AE5: =-1*((RawData!AE4-AVERAGE(RawData!$AE$3:$AE$40))/STDEV(RawData!$AE$3:$AE$40)) -> -0.9361174 | AF5: =-1*((RawData!AF4-AVERAGE(RawData!$AF$3:$AF$40))/STDEV(RawData!$AF$3:$AF$40)) -> 0.58969853 | AG5: =-1*((RawData!AG4-AVERAGE(RawData!$AG$3:$AG$40))/STDEV(RawData!$AG$3:$AG$40)) -> 0.79687605 | AH5: =((RawData!AH4-AVERAGE(RawData!$AH$3:$AH$40))/STDEV(RawData!$AH$3:$AH$40)) -> 0.32819245 | AI5: =((RawData!AI4-AVERAGE(RawData!$AI$3:$AI$40))/STDEV(RawData!$AI$3:$AI$40)) -> 0.55436816 | AJ5: =-1*((RawData!AJ4-AVERAGE(RawData!$AJ$3:$AJ$40))/STDEV(RawData!$AJ$3:$AJ$40)) -> 0.98675438 | AK5: =-1*((RawData!AK4-AVERAGE(RawData!$AK$3:$AK$40))/STDEV(RawData!$AK$3:$AK$40)) -> -0.95570405 | AL5: =-1*((RawData!AL4-AVERAGE(RawData!$AL$3:$AL$40))/STDEV(RawData!$AL$3:$AL$40)) -> 0.42149551 | AM5: =-1*((RawData!AM4-AVERAGE(RawData!$AM$3:$AM$40))/STDEV(RawData!$AM$3:$AM$40)) -> -1.250545 | AN5: =((RawData!AN4-AVERAGE(RawData!$AN$3:$AN$40))/STDEV(RawData!$AN$3:$AN$40)) -> -1.0476372 | AO5: =-1*((RawData!AO4-AVERAGE(RawData!$AO$3:$AO$40))/STDEV(RawData!$AO$3:$AO$40)) -> 0.61642058 | AP5: =-1*((RawData!AP4-AVERAGE(RawData!$AP$3:$AP$40))/STDEV(RawData!$AP$3:$AP$40)) -> -0.48376743 | AQ5: =-1*((RawData!AQ4-AVERAGE(RawData!$AQ$3:$AQ$40))/STDEV(RawData!$AQ$3:$AQ$40)) -> -0.68274065
A6: =RawData!A5 -> Belgium | B6: =-1*((RawData!B5-AVERAGE(RawData!$B$3:$B$40))/STDEV(RawData!$B$3:$B$40)) -> -0.14677654 | C6: =((RawData!C5-AVERAGE(RawData!$C$3:$C$40))/STDEV(RawData!$C$3:$C$40)) -> -0.24662998 | D6: =((RawData!D5-AVERAGE(RawData!$D$3:$D$40))/STDEV(RawData!$D$3:$D$40)) -> 0.58981677 | E6: =((RawData!E5-AVERAGE(RawData!$E$3:$E$40))/STDEV(RawData!$E$3:$E$40)) -> 0.16096528 | F6: =((RawData!F5-AVERAGE(RawData!$F$3:$F$40))/STDEV(RawData!$F$3:$F$40)) -> 0.25449495 | G6: =((RawData!G5-AVERAGE(RawData!$G$3:$G$40))/STDEV(RawData!$G$3:$G$40)) -> 0.58161067 | H6: =((RawData!H5-AVERAGE(RawData!$H$3:$H$40))/STDEV(RawData!$H$3:$H$40)) -> 1.1791342 | I6: =((RawData!I5-AVERAGE(RawData!$I$3:$I$40))/STDEV(RawData!$I$3:$I$40)) -> -0.38409362 | J6: =-1*((RawData!J5-AVERAGE(RawData!$J$3:$J$40))/STDEV(RawData!$J$3:$J$40)) -> -1.0401304 | K6: =-1*((RawData!K5-AVERAGE(RawData!$K$3:$K$40))/STDEV(RawData!$K$3:$K$40)) -> 0.042619236 | L6: =-1*((RawData!L5-AVERAGE(RawData!$L$3:$L$40))/STDEV(RawData!$L$3:$L$40)) -> 0.6703676 | M6: =-1*((RawData!M5-AVERAGE(RawData!$M$3:$M$40))/STDEV(RawData!$M$3:$M$40)) -> -0.09410045 | N6: =-1*((RawData!N5-AVERAGE(RawData!$N$3:$N$40))/STDEV(RawData!$N$3:$N$40)) -> 0.33845396 | O6: =-1*((AbsValues!B5-AVERAGE(AbsValues!$B$3:$B$40))/STDEV(AbsValues!$B$3:$B$40)) -> 0.55786949 | P6: =-1*((RawData!P5-AVERAGE(RawData!$P$3:$P$40))/STDEV(RawData!$P$3:$P$40)) -> -1.5093021 | Q6: =-1*((RawData!Q5-AVERAGE(RawData!$Q$3:$Q$40))/STDEV(RawData!$Q$3:$Q$40)) -> 0.64670078 | R6: =-1*((RawData!R5-AVERAGE(RawData!$R$3:$R$40))/STDEV(RawData!$R$3:$R$40)) -> -0.1852295 | S6: =-1*((RawData!S5-AVERAGE(RawData!$S$3:$S$40))/STDEV(RawData!$S$3:$S$40)) -> 0.33845396 | T6: =-1*((AbsValues!C5-AVERAGE(AbsValues!$C$3:$C$40))/STDEV(AbsValues!$C$3:$C$40)) -> 0.32073762 | U6: =-1*((RawData!U5-AVERAGE(RawData!$U$3:$U$40))/STDEV(RawData!$U$3:$U$40)) -> 1.5110201 | V6: =-1*((RawData!V5-AVERAGE(RawData!$V$3:$V$40))/STDEV(RawData!$V$3:$V$40)) -> -0.46166058 | W6: =-1*((RawData!W5-AVERAGE(RawData!$W$3:$W$40))/STDEV(RawData!$W$3:$W$40)) -> -0.3169609 | X6: =-1*((RawData!X5-AVERAGE(RawData!$X$3:$X$40))/STDEV(RawData!$X$3:$X$40)) -> 0.43445197 | Y6: =((RawData!Y5-AVERAGE(RawData!$Y$3:$Y$40))/STDEV(RawData!$Y$3:$Y$40)) -> -0.98093024 | Z6: =((RawData!Z5-AVERAGE(RawData!$Z$3:$Z$40))/STDEV(RawData!$Z$3:$Z$40)) -> 0.18465614 | AA6: =-1*((RawData!AA5-AVERAGE(RawData!$AA$3:$AA$40))/STDEV(RawData!$AA$3:$AA$40)) -> -0.63840445 | AB6: =-1*((RawData!AB5-AVERAGE(RawData!$AB$3:$AB$40))/STDEV(RawData!$AB$3:$AB$40)) -> -1.0867649 | AC6: =-1*((RawData!AC5-AVERAGE(RawData!$AC$3:$AC$40))/STDEV(RawData!$AC$3:$AC$40)) -> -0.6703676 | AD6: =-1*((RawData!AD5-AVERAGE(RawData!$AD$3:$AD$40))/STDEV(RawData!$AD$3:$AD$40)) -> -0.42727718 | AE6: =-1*((RawData!AE5-AVERAGE(RawData!$AE$3:$AE$40))/STDEV(RawData!$AE$3:$AE$40)) -> -0.9361174 | AF6: =-1*((RawData!AF5-AVERAGE(RawData!$AF$3:$AF$40))/STDEV(RawData!$AF$3:$AF$40)) -> 0.58969853 | AG6: =-1*((RawData!AG5-AVERAGE(RawData!$AG$3:$AG$40))/STDEV(RawData!$AG$3:$AG$40)) -> -1.2218766 | AH6: =((RawData!AH5-AVERAGE(RawData!$AH$3:$AH$40))/STDEV(RawData!$AH$3:$AH$40)) -> 0.32819245 | AI6: =((RawData!AI5-AVERAGE(RawData!$AI$3:$AI$40))/STDEV(RawData!$AI$3:$AI$40)) -> 0.55436816 | AJ6: =-1*((RawData!AJ5-AVERAGE(RawData!$AJ$3:$AJ$40))/STDEV(RawData!$AJ$3:$AJ$40)) -> 0.98675438 | AK6: =-1*((RawData!AK5-AVERAGE(RawData!$AK$3:$AK$40))/STDEV(RawData!$AK$3:$AK$40)) -> -0.95570405 | AL6: =-1*((RawData!AL5-AVERAGE(RawData!$AL$3:$AL$40))/STDEV(RawData!$AL$3:$AL$40)) -> -1.3249694 | AM6: =-1*((RawData!AM5-AVERAGE(RawData!$AM$3:$AM$40))/STDEV(RawData!$AM$3:$AM$40)) -> -1.250545 | AN6: =((RawData!AN5-AVERAGE(RawData!$AN$3:$AN$40))/STDEV(RawData!$AN$3:$AN$40)) -> 0.71753265 | AO6: =-1*((RawData!AO5-AVERAGE(RawData!$AO$3:$AO$40))/STDEV(RawData!$AO$3:$AO$40)) -> -1.3355779 | AP6: =-1*((RawData!AP5-AVERAGE(RawData!$AP$3:$AP$40))/STDEV(RawData!$AP$3:$AP$40)) -> -0.48376743 | AQ6: =-1*((RawData!AQ5-AVERAGE(RawData!$AQ$3:$AQ$40))/STDEV(RawData!$AQ$3:$AQ$40)) -> -0.68274065
A7: =RawData!A6 -> Canada | B7: =-1*((RawData!B6-AVERAGE(RawData!$B$3:$B$40))/STDEV(RawData!$B$3:$B$40)) -> -0.32659485 | C7: =((RawData!C6-AVERAGE(RawData!$C$3:$C$40))/STDEV(RawData!$C$3:$C$40)) -> -0.11369467 | D7: =((RawData!D6-AVERAGE(RawData!$D$3:$D$40))/STDEV(RawData!$D$3:$D$40)) -> -0.67882178 | E7: =((RawData!E6-AVERAGE(RawData!$E$3:$E$40))/STDEV(RawData!$E$3:$E$40)) -> 1.3612042 | F7: =((RawData!F6-AVERAGE(RawData!$F$3:$F$40))/STDEV(RawData!$F$3:$F$40)) -> 0.65295967 | G7: =((RawData!G6-AVERAGE(RawData!$G$3:$G$40))/STDEV(RawData!$G$3:$G$40)) -> -1.4015671 | H7: =((RawData!H6-AVERAGE(RawData!$H$3:$H$40))/STDEV(RawData!$H$3:$H$40)) -> -0.2662561 | I7: =((RawData!I6-AVERAGE(RawData!$I$3:$I$40))/STDEV(RawData!$I$3:$I$40)) -> -0.38409362 | J7: =-1*((RawData!J6-AVERAGE(RawData!$J$3:$J$40))/STDEV(RawData!$J$3:$J$40)) -> 0.9361174 | K7: =-1*((RawData!K6-AVERAGE(RawData!$K$3:$K$40))/STDEV(RawData!$K$3:$K$40)) -> -0.4607485 | L7: =-1*((RawData!L6-AVERAGE(RawData!$L$3:$L$40))/STDEV(RawData!$L$3:$L$40)) -> 0.6703676 | M7: =-1*((RawData!M6-AVERAGE(RawData!$M$3:$M$40))/STDEV(RawData!$M$3:$M$40)) -> -0.09410045 | N7: =-1*((RawData!N6-AVERAGE(RawData!$N$3:$N$40))/STDEV(RawData!$N$3:$N$40)) -> 0.33845396 | O7: =-1*((AbsValues!B6-AVERAGE(AbsValues!$B$3:$B$40))/STDEV(AbsValues!$B$3:$B$40)) -> -0.2822003 | P7: =-1*((RawData!P6-AVERAGE(RawData!$P$3:$P$40))/STDEV(RawData!$P$3:$P$40)) -> -0.79454306 | Q7: =-1*((RawData!Q6-AVERAGE(RawData!$Q$3:$Q$40))/STDEV(RawData!$Q$3:$Q$40)) -> 0.45689355 | R7: =-1*((RawData!R6-AVERAGE(RawData!$R$3:$R$40))/STDEV(RawData!$R$3:$R$40)) -> 0.055971157 | S7: =-1*((RawData!S6-AVERAGE(RawData!$S$3:$S$40))/STDEV(RawData!$S$3:$S$40)) -> 0.33845396 | T7: =-1*((AbsValues!C6-AVERAGE(AbsValues!$C$3:$C$40))/STDEV(AbsValues!$C$3:$C$40)) -> 0.32073762 | U7: =-1*((RawData!U6-AVERAGE(RawData!$U$3:$U$40))/STDEV(RawData!$U$3:$U$40)) -> -0.51207224 | V7: =-1*((RawData!V6-AVERAGE(RawData!$V$3:$V$40))/STDEV(RawData!$V$3:$V$40)) -> -1.279212 | W7: =-1*((RawData!W6-AVERAGE(RawData!$W$3:$W$40))/STDEV(RawData!$W$3:$W$40)) -> 1.3569572 | X7: =-1*((RawData!X6-AVERAGE(RawData!$X$3:$X$40))/STDEV(RawData!$X$3:$X$40)) -> 0.60831673 | Y7: =((RawData!Y6-AVERAGE(RawData!$Y$3:$Y$40))/STDEV(RawData!$Y$3:$Y$40)) -> -0.22651839 | Z7: =((RawData!Z6-AVERAGE(RawData!$Z$3:$Z$40))/STDEV(RawData!$Z$3:$Z$40)) -> 0.18465614 | AA7: =-1*((RawData!AA6-AVERAGE(RawData!$AA$3:$AA$40))/STDEV(RawData!$AA$3:$AA$40)) -> -1.4394387 | AB7: =-1*((RawData!AB6-AVERAGE(RawData!$AB$3:$AB$40))/STDEV(RawData!$AB$3:$AB$40)) -> 0.44275606 | AC7: =-1*((RawData!AC6-AVERAGE(RawData!$AC$3:$AC$40))/STDEV(RawData!$AC$3:$AC$40)) -> 1.4524631 | AD7: =-1*((RawData!AD6-AVERAGE(RawData!$AD$3:$AD$40))/STDEV(RawData!$AD$3:$AD$40)) -> -0.42727718 | AE7: =-1*((RawData!AE6-AVERAGE(RawData!$AE$3:$AE$40))/STDEV(RawData!$AE$3:$AE$40)) -> -0.9361174 | AF7: =-1*((RawData!AF6-AVERAGE(RawData!$AF$3:$AF$40))/STDEV(RawData!$AF$3:$AF$40)) -> -1.6511559 | AG7: =-1*((RawData!AG6-AVERAGE(RawData!$AG$3:$AG$40))/STDEV(RawData!$AG$3:$AG$40)) -> 0.79687605 | AH7: =((RawData!AH6-AVERAGE(RawData!$AH$3:$AH$40))/STDEV(RawData!$AH$3:$AH$40)) -> 0.32819245 | AI7: =((RawData!AI6-AVERAGE(RawData!$AI$3:$AI$40))/STDEV(RawData!$AI$3:$AI$40)) -> -0.71543233 | AJ7: =-1*((RawData!AJ6-AVERAGE(RawData!$AJ$3:$AJ$40))/STDEV(RawData!$AJ$3:$AJ$40)) -> -0.98675438 | AK7: =-1*((RawData!AK6-AVERAGE(RawData!$AK$3:$AK$40))/STDEV(RawData!$AK$3:$AK$40)) -> -0.45368232 | AL7: =-1*((RawData!AL6-AVERAGE(RawData!$AL$3:$AL$40))/STDEV(RawData!$AL$3:$AL$40)) -> -0.88835314 | AM7: =-1*((RawData!AM6-AVERAGE(RawData!$AM$3:$AM$40))/STDEV(RawData!$AM$3:$AM$40)) -> -0.74635186 | AN7: =((RawData!AN6-AVERAGE(RawData!$AN$3:$AN$40))/STDEV(RawData!$AN$3:$AN$40)) -> 0.75508946 | AO7: =-1*((RawData!AO6-AVERAGE(RawData!$AO$3:$AO$40))/STDEV(RawData!$AO$3:$AO$40)) -> 0.61642058 | AP7: =-1*((RawData!AP6-AVERAGE(RawData!$AP$3:$AP$40))/STDEV(RawData!$AP$3:$AP$40)) -> 1.5588062 | AQ7: =-1*((RawData!AQ6-AVERAGE(RawData!$AQ$3:$AQ$40))/STDEV(RawData!$AQ$3:$AQ$40)) -> -0.68274065
A8: =RawData!A7 -> Switzerland | B8: =-1*((RawData!B7-AVERAGE(RawData!$B$3:$B$40))/STDEV(RawData!$B$3:$B$40)) -> 0.84146229 | C8: =((RawData!C7-AVERAGE(RawData!$C$3:$C$40))/STDEV(RawData!$C$3:$C$40)) -> -0.24662998 | D8: =((RawData!D7-AVERAGE(RawData!$D$3:$D$40))/STDEV(RawData!$D$3:$D$40)) -> -1.0086678 | E8: =((RawData!E7-AVERAGE(RawData!$E$3:$E$40))/STDEV(RawData!$E$3:$E$40)) -> 0.03955503 | F8: =((RawData!F7-AVERAGE(RawData!$F$3:$F$40))/STDEV(RawData!$F$3:$F$40)) -> 0.29010155 | G8: =((RawData!G7-AVERAGE(RawData!$G$3:$G$40))/STDEV(RawData!$G$3:$G$40)) -> 0.78166878 | H8: =((RawData!H7-AVERAGE(RawData!$H$3:$H$40))/STDEV(RawData!$H$3:$H$40)) -> 1.1791342 | I8: =((RawData!I7-AVERAGE(RawData!$I$3:$I$40))/STDEV(RawData!$I$3:$I$40)) -> -0.38409362 | J8: =-1*((RawData!J7-AVERAGE(RawData!$J$3:$J$40))/STDEV(RawData!$J$3:$J$40)) -> -1.0401304 | K8: =-1*((RawData!K7-AVERAGE(RawData!$K$3:$K$40))/STDEV(RawData!$K$3:$K$40)) -> 1.4870658 | L8: =-1*((RawData!L7-AVERAGE(RawData!$L$3:$L$40))/STDEV(RawData!$L$3:$L$40)) -> -1.4524631 | M8: =-1*((RawData!M7-AVERAGE(RawData!$M$3:$M$40))/STDEV(RawData!$M$3:$M$40)) -> 0.62106297 | N8: =-1*((RawData!N7-AVERAGE(RawData!$N$3:$N$40))/STDEV(RawData!$N$3:$N$40)) -> 0.33845396 | O8: =-1*((AbsValues!B7-AVERAGE(AbsValues!$B$3:$B$40))/STDEV(AbsValues!$B$3:$B$40)) -> -1.5305712 | P8: =-1*((RawData!P7-AVERAGE(RawData!$P$3:$P$40))/STDEV(RawData!$P$3:$P$40)) -> 0.50956495 | Q8: =-1*((RawData!Q7-AVERAGE(RawData!$Q$3:$Q$40))/STDEV(RawData!$Q$3:$Q$40)) -> 0.42275978 | R8: =-1*((RawData!R7-AVERAGE(RawData!$R$3:$R$40))/STDEV(RawData!$R$3:$R$40)) -> -0.40785752 | S8: =-1*((RawData!S7-AVERAGE(RawData!$S$3:$S$40))/STDEV(RawData!$S$3:$S$40)) -> 0.33845396 | T8: =-1*((AbsValues!C7-AVERAGE(AbsValues!$C$3:$C$40))/STDEV(AbsValues!$C$3:$C$40)) -> 0.32073762 | U8: =-1*((RawData!U7-AVERAGE(RawData!$U$3:$U$40))/STDEV(RawData!$U$3:$U$40)) -> 1.5110201 | V8: =-1*((RawData!V7-AVERAGE(RawData!$V$3:$V$40))/STDEV(RawData!$V$3:$V$40)) -> 0.22477108 | W8: =-1*((RawData!W7-AVERAGE(RawData!$W$3:$W$40))/STDEV(RawData!$W$3:$W$40)) -> 2.1650556 | X8: =-1*((RawData!X7-AVERAGE(RawData!$X$3:$X$40))/STDEV(RawData!$X$3:$X$40)) -> -0.9611988 | Y8: =((RawData!Y7-AVERAGE(RawData!$Y$3:$Y$40))/STDEV(RawData!$Y$3:$Y$40)) -> 1.0218442 | Z8: =((RawData!Z7-AVERAGE(RawData!$Z$3:$Z$40))/STDEV(RawData!$Z$3:$Z$40)) -> 0.18465614 | AA8: =-1*((RawData!AA7-AVERAGE(RawData!$AA$3:$AA$40))/STDEV(RawData!$AA$3:$AA$40)) -> 0.55380611 | AB8: =-1*((RawData!AB7-AVERAGE(RawData!$AB$3:$AB$40))/STDEV(RawData!$AB$3:$AB$40)) -> -2.6162858 | AC8: =-1*((RawData!AC7-AVERAGE(RawData!$AC$3:$AC$40))/STDEV(RawData!$AC$3:$AC$40)) -> -0.6703676 | AD8: =-1*((RawData!AD7-AVERAGE(RawData!$AD$3:$AD$40))/STDEV(RawData!$AD$3:$AD$40)) -> -0.42727718 | AE8: =-1*((RawData!AE7-AVERAGE(RawData!$AE$3:$AE$40))/STDEV(RawData!$AE$3:$AE$40)) -> -0.9361174 | AF8: =-1*((RawData!AF7-AVERAGE(RawData!$AF$3:$AF$40))/STDEV(RawData!$AF$3:$AF$40)) -> -1.6511559 | AG8: =-1*((RawData!AG7-AVERAGE(RawData!$AG$3:$AG$40))/STDEV(RawData!$AG$3:$AG$40)) -> -1.2218766 | AH8: =((RawData!AH7-AVERAGE(RawData!$AH$3:$AH$40))/STDEV(RawData!$AH$3:$AH$40)) -> 0.32819245 | AI8: =((RawData!AI7-AVERAGE(RawData!$AI$3:$AI$40))/STDEV(RawData!$AI$3:$AI$40)) -> 0.55436816 | AJ8: =-1*((RawData!AJ7-AVERAGE(RawData!$AJ$3:$AJ$40))/STDEV(RawData!$AJ$3:$AJ$40)) -> 0.98675438 | AK8: =-1*((RawData!AK7-AVERAGE(RawData!$AK$3:$AK$40))/STDEV(RawData!$AK$3:$AK$40)) -> -1.4577258 | AL8: =-1*((RawData!AL7-AVERAGE(RawData!$AL$3:$AL$40))/STDEV(RawData!$AL$3:$AL$40)) -> -1.7615856 | AM8: =-1*((RawData!AM7-AVERAGE(RawData!$AM$3:$AM$40))/STDEV(RawData!$AM$3:$AM$40)) -> 1.774614 | AN8: =((RawData!AN7-AVERAGE(RawData!$AN$3:$AN$40))/STDEV(RawData!$AN$3:$AN$40)) -> 1.2808847 | AO8: =-1*((RawData!AO7-AVERAGE(RawData!$AO$3:$AO$40))/STDEV(RawData!$AO$3:$AO$40)) -> 2.5684191 | AP8: =-1*((RawData!AP7-AVERAGE(RawData!$AP$3:$AP$40))/STDEV(RawData!$AP$3:$AP$40)) -> 1.5588062 | AQ8: =-1*((RawData!AQ7-AVERAGE(RawData!$AQ$3:$AQ$40))/STDEV(RawData!$AQ$3:$AQ$40)) -> 0.44526564
A9: =RawData!A8 -> Chile | B9: =-1*((RawData!B8-AVERAGE(RawData!$B$3:$B$40))/STDEV(RawData!$B$3:$B$40)) -> -0.51332181 | C9: =((RawData!C8-AVERAGE(RawData!$C$3:$C$40))/STDEV(RawData!$C$3:$C$40)) -> -0.24662998 | D9: =((RawData!D8-AVERAGE(RawData!$D$3:$D$40))/STDEV(RawData!$D$3:$D$40)) -> 1.3509999 | E9: =((RawData!E8-AVERAGE(RawData!$E$3:$E$40))/STDEV(RawData!$E$3:$E$40)) -> -2.7588802 | F9: =((RawData!F8-AVERAGE(RawData!$F$3:$F$40))/STDEV(RawData!$F$3:$F$40)) -> -0.82888336 | G9: =((RawData!G8-AVERAGE(RawData!$G$3:$G$40))/STDEV(RawData!$G$3:$G$40)) -> -4.3346012 | H9: =((RawData!H8-AVERAGE(RawData!$H$3:$H$40))/STDEV(RawData!$H$3:$H$40)) -> -0.2662561 | I9: =((RawData!I8-AVERAGE(RawData!$I$3:$I$40))/STDEV(RawData!$I$3:$I$40)) -> -0.38409362 | J9: =-1*((RawData!J8-AVERAGE(RawData!$J$3:$J$40))/STDEV(RawData!$J$3:$J$40)) -> 0.9361174 | K9: =-1*((RawData!K8-AVERAGE(RawData!$K$3:$K$40))/STDEV(RawData!$K$3:$K$40)) -> -1.0078873 | L9: =-1*((RawData!L8-AVERAGE(RawData!$L$3:$L$40))/STDEV(RawData!$L$3:$L$40)) -> 0.6703676 | M9: =-1*((RawData!M8-AVERAGE(RawData!$M$3:$M$40))/STDEV(RawData!$M$3:$M$40)) -> 1.3362264 | N9: =-1*((RawData!N8-AVERAGE(RawData!$N$3:$N$40))/STDEV(RawData!$N$3:$N$40)) -> 0.33845396 | O9: =-1*((AbsValues!B8-AVERAGE(AbsValues!$B$3:$B$40))/STDEV(AbsValues!$B$3:$B$40)) -> 0.38287598 | P9: =-1*((RawData!P8-AVERAGE(RawData!$P$3:$P$40))/STDEV(RawData!$P$3:$P$40)) -> 0.66128539 | Q9: =-1*((RawData!Q8-AVERAGE(RawData!$Q$3:$Q$40))/STDEV(RawData!$Q$3:$Q$40)) -> -1.1587852 | R9: =-1*((RawData!R8-AVERAGE(RawData!$R$3:$R$40))/STDEV(RawData!$R$3:$R$40)) -> 0.076594324 | S9: =-1*((RawData!S8-AVERAGE(RawData!$S$3:$S$40))/STDEV(RawData!$S$3:$S$40)) -> 0.33845396 | T9: =-1*((AbsValues!C8-AVERAGE(AbsValues!$C$3:$C$40))/STDEV(AbsValues!$C$3:$C$40)) -> 0.32073762 | U9: =-1*((RawData!U8-AVERAGE(RawData!$U$3:$U$40))/STDEV(RawData!$U$3:$U$40)) -> -1.5141647 | V9: =-1*((RawData!V8-AVERAGE(RawData!$V$3:$V$40))/STDEV(RawData!$V$3:$V$40)) -> 0.071725254 | W9: =-1*((RawData!W8-AVERAGE(RawData!$W$3:$W$40))/STDEV(RawData!$W$3:$W$40)) -> 0.06784786 | X9: =-1*((RawData!X8-AVERAGE(RawData!$X$3:$X$40))/STDEV(RawData!$X$3:$X$40)) -> 1.1513215 | Y9: =((RawData!Y8-AVERAGE(RawData!$Y$3:$Y$40))/STDEV(RawData!$Y$3:$Y$40)) -> 0.94846881 | Z9: =((RawData!Z8-AVERAGE(RawData!$Z$3:$Z$40))/STDEV(RawData!$Z$3:$Z$40)) -> 0.18465614 | AA9: =-1*((RawData!AA8-AVERAGE(RawData!$AA$3:$AA$40))/STDEV(RawData!$AA$3:$AA$40)) -> 0.72301223 | AB9: =-1*((RawData!AB8-AVERAGE(RawData!$AB$3:$AB$40))/STDEV(RawData!$AB$3:$AB$40)) -> 0.44275606 | AC9: =-1*((RawData!AC8-AVERAGE(RawData!$AC$3:$AC$40))/STDEV(RawData!$AC$3:$AC$40)) -> -0.6703676 | AD9: =-1*((RawData!AD8-AVERAGE(RawData!$AD$3:$AD$40))/STDEV(RawData!$AD$3:$AD$40)) -> 2.2788116 | AE9: =-1*((RawData!AE8-AVERAGE(RawData!$AE$3:$AE$40))/STDEV(RawData!$AE$3:$AE$40)) -> -0.9361174 | AF9: =-1*((RawData!AF8-AVERAGE(RawData!$AF$3:$AF$40))/STDEV(RawData!$AF$3:$AF$40)) -> 0.58969853 | AG9: =-1*((RawData!AG8-AVERAGE(RawData!$AG$3:$AG$40))/STDEV(RawData!$AG$3:$AG$40)) -> 0.79687605 | AH9: =((RawData!AH8-AVERAGE(RawData!$AH$3:$AH$40))/STDEV(RawData!$AH$3:$AH$40)) -> -3.3615451 | AI9: =((RawData!AI8-AVERAGE(RawData!$AI$3:$AI$40))/STDEV(RawData!$AI$3:$AI$40)) -> -1.9852328 | AJ9: =-1*((RawData!AJ8-AVERAGE(RawData!$AJ$3:$AJ$40))/STDEV(RawData!$AJ$3:$AJ$40)) -> -0.98675438 | AK9: =-1*((RawData!AK8-AVERAGE(RawData!$AK$3:$AK$40))/STDEV(RawData!$AK$3:$AK$40)) -> -1.4577258 | AL9: =-1*((RawData!AL8-AVERAGE(RawData!$AL$3:$AL$40))/STDEV(RawData!$AL$3:$AL$40)) -> -1.7615856 | AM9: =-1*((RawData!AM8-AVERAGE(RawData!$AM$3:$AM$40))/STDEV(RawData!$AM$3:$AM$40)) -> -1.250545 | AN9: =((RawData!AN8-AVERAGE(RawData!$AN$3:$AN$40))/STDEV(RawData!$AN$3:$AN$40)) -> -1.4607621 | AO9: =-1*((RawData!AO8-AVERAGE(RawData!$AO$3:$AO$40))/STDEV(RawData!$AO$3:$AO$40)) -> -0.35957867 | AP9: =-1*((RawData!AP8-AVERAGE(RawData!$AP$3:$AP$40))/STDEV(RawData!$AP$3:$AP$40)) -> 1.5588062 | AQ9: =-1*((RawData!AQ8-AVERAGE(RawData!$AQ$3:$AQ$40))/STDEV(RawData!$AQ$3:$AQ$40)) -> 1.5732719
A10: =RawData!A9 -> Colombia | B10: =-1*((RawData!B9-AVERAGE(RawData!$B$3:$B$40))/STDEV(RawData!$B$3:$B$40)) -> -1.9795029 | C10: =((RawData!C9-AVERAGE(RawData!$C$3:$C$40))/STDEV(RawData!$C$3:$C$40)) -> -0.24662998 | D10: =((RawData!D9-AVERAGE(RawData!$D$3:$D$40))/STDEV(RawData!$D$3:$D$40)) -> -0.88180395 | E10: =((RawData!E9-AVERAGE(RawData!$E$3:$E$40))/STDEV(RawData!$E$3:$E$40)) -> -1.463251 | F10: =((RawData!F9-AVERAGE(RawData!$F$3:$F$40))/STDEV(RawData!$F$3:$F$40)) -> -0.99706005 | G10: =((RawData!G9-AVERAGE(RawData!$G$3:$G$40))/STDEV(RawData!$G$3:$G$40)) -> 0.58161067 | H10: =((RawData!H9-AVERAGE(RawData!$H$3:$H$40))/STDEV(RawData!$H$3:$H$40)) -> -0.2662561 | I10: =((RawData!I9-AVERAGE(RawData!$I$3:$I$40))/STDEV(RawData!$I$3:$I$40)) -> -0.38409362 | J10: =-1*((RawData!J9-AVERAGE(RawData!$J$3:$J$40))/STDEV(RawData!$J$3:$J$40)) -> 0.9361174 | K10: =-1*((RawData!K9-AVERAGE(RawData!$K$3:$K$40))/STDEV(RawData!$K$3:$K$40)) -> 0.7648425 | L10: =-1*((RawData!L9-AVERAGE(RawData!$L$3:$L$40))/STDEV(RawData!$L$3:$L$40)) -> -1.4524631 | M10: =-1*((RawData!M9-AVERAGE(RawData!$M$3:$M$40))/STDEV(RawData!$M$3:$M$40)) -> -0.80926387 | N10: =-1*((RawData!N9-AVERAGE(RawData!$N$3:$N$40))/STDEV(RawData!$N$3:$N$40)) -> 0.33845396 | O10: =-1*((AbsValues!B9-AVERAGE(AbsValues!$B$3:$B$40))/STDEV(AbsValues!$B$3:$B$40)) -> 0.42371556 | P10: =-1*((RawData!P9-AVERAGE(RawData!$P$3:$P$40))/STDEV(RawData!$P$3:$P$40)) -> 0.76888883 | Q10: =-1*((RawData!Q9-AVERAGE(RawData!$Q$3:$Q$40))/STDEV(RawData!$Q$3:$Q$40)) -> -4.6591642 | R10: =-1*((RawData!R9-AVERAGE(RawData!$R$3:$R$40))/STDEV(RawData!$R$3:$R$40)) -> 4.8261269 | S10: =-1*((RawData!S9-AVERAGE(RawData!$S$3:$S$40))/STDEV(RawData!$S$3:$S$40)) -> 0.33845396 | T10: =-1*((AbsValues!C9-AVERAGE(AbsValues!$C$3:$C$40))/STDEV(AbsValues!$C$3:$C$40)) -> -0.52339323 | U10: =-1*((RawData!U9-AVERAGE(RawData!$U$3:$U$40))/STDEV(RawData!$U$3:$U$40)) -> 0.37657581 | V10: =-1*((RawData!V9-AVERAGE(RawData!$V$3:$V$40))/STDEV(RawData!$V$3:$V$40)) -> 0.41333197 | W10: =-1*((RawData!W9-AVERAGE(RawData!$W$3:$W$40))/STDEV(RawData!$W$3:$W$40)) -> 0.06784786 | X10: =-1*((RawData!X9-AVERAGE(RawData!$X$3:$X$40))/STDEV(RawData!$X$3:$X$40)) -> 1.1513215 | Y10: =((RawData!Y9-AVERAGE(RawData!$Y$3:$Y$40))/STDEV(RawData!$Y$3:$Y$40)) -> -1.3685787 | Z10: =((RawData!Z9-AVERAGE(RawData!$Z$3:$Z$40))/STDEV(RawData!$Z$3:$Z$40)) -> 0.18465614 | AA10: =-1*((RawData!AA9-AVERAGE(RawData!$AA$3:$AA$40))/STDEV(RawData!$AA$3:$AA$40)) -> 0.72433424 | AB10: =-1*((RawData!AB9-AVERAGE(RawData!$AB$3:$AB$40))/STDEV(RawData!$AB$3:$AB$40)) -> -2.6162858 | AC10: =-1*((RawData!AC9-AVERAGE(RawData!$AC$3:$AC$40))/STDEV(RawData!$AC$3:$AC$40)) -> -0.6703676 | AD10: =-1*((RawData!AD9-AVERAGE(RawData!$AD$3:$AD$40))/STDEV(RawData!$AD$3:$AD$40)) -> -0.42727718 | AE10: =-1*((RawData!AE9-AVERAGE(RawData!$AE$3:$AE$40))/STDEV(RawData!$AE$3:$AE$40)) -> 1.0401304 | AF10: =-1*((RawData!AF9-AVERAGE(RawData!$AF$3:$AF$40))/STDEV(RawData!$AF$3:$AF$40)) -> -1.6511559 | AG10: =-1*((RawData!AG9-AVERAGE(RawData!$AG$3:$AG$40))/STDEV(RawData!$AG$3:$AG$40)) -> -1.2218766 | AH10: =((RawData!AH9-AVERAGE(RawData!$AH$3:$AH$40))/STDEV(RawData!$AH$3:$AH$40)) -> -3.3615451 | AI10: =((RawData!AI9-AVERAGE(RawData!$AI$3:$AI$40))/STDEV(RawData!$AI$3:$AI$40)) -> -1.9852328 | AJ10: =-1*((RawData!AJ9-AVERAGE(RawData!$AJ$3:$AJ$40))/STDEV(RawData!$AJ$3:$AJ$40)) -> 0.98675438 | AK10: =-1*((RawData!AK9-AVERAGE(RawData!$AK$3:$AK$40))/STDEV(RawData!$AK$3:$AK$40)) -> 0.048339408 | AL10: =-1*((RawData!AL9-AVERAGE(RawData!$AL$3:$AL$40))/STDEV(RawData!$AL$3:$AL$40)) -> -0.45173693 | AM10: =-1*((RawData!AM9-AVERAGE(RawData!$AM$3:$AM$40))/STDEV(RawData!$AM$3:$AM$40)) -> -0.24215868 | AN10: =((RawData!AN9-AVERAGE(RawData!$AN$3:$AN$40))/STDEV(RawData!$AN$3:$AN$40)) -> -2.3245686 | AO10: =-1*((RawData!AO9-AVERAGE(RawData!$AO$3:$AO$40))/STDEV(RawData!$AO$3:$AO$40)) -> -1.3355779 | AP10: =-1*((RawData!AP9-AVERAGE(RawData!$AP$3:$AP$40))/STDEV(RawData!$AP$3:$AP$40)) -> 1.5588062 | AQ10: =-1*((RawData!AQ9-AVERAGE(RawData!$AQ$3:$AQ$40))/STDEV(RawData!$AQ$3:$AQ$40)) -> 1.5732719
A11: =RawData!A10 -> Costa Rica | B11: =-1*((RawData!B10-AVERAGE(RawData!$B$3:$B$40))/STDEV(RawData!$B$3:$B$40)) -> -1.0631397 | C11: =((RawData!C10-AVERAGE(RawData!$C$3:$C$40))/STDEV(RawData!$C$3:$C$40)) -> -0.24662998 | D11: =((RawData!D10-AVERAGE(RawData!$D$3:$D$40))/STDEV(RawData!$D$3:$D$40)) -> -1.1101589 | E11: =((RawData!E10-AVERAGE(RawData!$E$3:$E$40))/STDEV(RawData!$E$3:$E$40)) -> -0.42248502 | F11: =((RawData!F10-AVERAGE(RawData!$F$3:$F$40))/STDEV(RawData!$F$3:$F$40)) -> -1.1366879 | G11: =((RawData!G10-AVERAGE(RawData!$G$3:$G$40))/STDEV(RawData!$G$3:$G$40)) -> -0.16428036 | H11: =((RawData!H10-AVERAGE(RawData!$H$3:$H$40))/STDEV(RawData!$H$3:$H$40)) -> -0.2662561 | I11: =((RawData!I10-AVERAGE(RawData!$I$3:$I$40))/STDEV(RawData!$I$3:$I$40)) -> -0.38409362 | J11: =-1*((RawData!J10-AVERAGE(RawData!$J$3:$J$40))/STDEV(RawData!$J$3:$J$40)) -> 0.9361174 | K11: =-1*((RawData!K10-AVERAGE(RawData!$K$3:$K$40))/STDEV(RawData!$K$3:$K$40)) -> 1.574608 | L11: =-1*((RawData!L10-AVERAGE(RawData!$L$3:$L$40))/STDEV(RawData!$L$3:$L$40)) -> 0.6703676 | M11: =-1*((RawData!M10-AVERAGE(RawData!$M$3:$M$40))/STDEV(RawData!$M$3:$M$40)) -> -2.2395907 | N11: =-1*((RawData!N10-AVERAGE(RawData!$N$3:$N$40))/STDEV(RawData!$N$3:$N$40)) -> 0.33845396 | O11: =-1*((AbsValues!B10-AVERAGE(AbsValues!$B$3:$B$40))/STDEV(AbsValues!$B$3:$B$40)) -> -1.7970792 | P11: =-1*((RawData!P10-AVERAGE(RawData!$P$3:$P$40))/STDEV(RawData!$P$3:$P$40)) -> 1.34831 | Q11: =-1*((RawData!Q10-AVERAGE(RawData!$Q$3:$Q$40))/STDEV(RawData!$Q$3:$Q$40)) -> 0.023567445 | R11: =-1*((RawData!R10-AVERAGE(RawData!$R$3:$R$40))/STDEV(RawData!$R$3:$R$40)) -> 0.66356595 | S11: =-1*((RawData!S10-AVERAGE(RawData!$S$3:$S$40))/STDEV(RawData!$S$3:$S$40)) -> 0.33845396 | T11: =-1*((AbsValues!C10-AVERAGE(AbsValues!$C$3:$C$40))/STDEV(AbsValues!$C$3:$C$40)) -> -3.860518 | U11: =-1*((RawData!U10-AVERAGE(RawData!$U$3:$U$40))/STDEV(RawData!$U$3:$U$40)) -> 0.37657581 | V11: =-1*((RawData!V10-AVERAGE(RawData!$V$3:$V$40))/STDEV(RawData!$V$3:$V$40)) -> 0.85082825 | W11: =-1*((RawData!W10-AVERAGE(RawData!$W$3:$W$40))/STDEV(RawData!$W$3:$W$40)) -> 1.2222741 | X11: =-1*((RawData!X10-AVERAGE(RawData!$X$3:$X$40))/STDEV(RawData!$X$3:$X$40)) -> 1.1513215 | Y11: =((RawData!Y10-AVERAGE(RawData!$Y$3:$Y$40))/STDEV(RawData!$Y$3:$Y$40)) -> -0.43150517 | Z11: =((RawData!Z10-AVERAGE(RawData!$Z$3:$Z$40))/STDEV(RawData!$Z$3:$Z$40)) -> 0.18465614 | AA11: =-1*((RawData!AA10-AVERAGE(RawData!$AA$3:$AA$40))/STDEV(RawData!$AA$3:$AA$40)) -> 0.72368386 | AB11: =-1*((RawData!AB10-AVERAGE(RawData!$AB$3:$AB$40))/STDEV(RawData!$AB$3:$AB$40)) -> 0.44275606 | AC11: =-1*((RawData!AC10-AVERAGE(RawData!$AC$3:$AC$40))/STDEV(RawData!$AC$3:$AC$40)) -> 1.4524631 | AD11: =-1*((RawData!AD10-AVERAGE(RawData!$AD$3:$AD$40))/STDEV(RawData!$AD$3:$AD$40)) -> -0.42727718 | AE11: =-1*((RawData!AE10-AVERAGE(RawData!$AE$3:$AE$40))/STDEV(RawData!$AE$3:$AE$40)) -> -0.9361174 | AF11: =-1*((RawData!AF10-AVERAGE(RawData!$AF$3:$AF$40))/STDEV(RawData!$AF$3:$AF$40)) -> 0.58969853 | AG11: =-1*((RawData!AG10-AVERAGE(RawData!$AG$3:$AG$40))/STDEV(RawData!$AG$3:$AG$40)) -> -1.2218766 | AH11: =((RawData!AH10-AVERAGE(RawData!$AH$3:$AH$40))/STDEV(RawData!$AH$3:$AH$40)) -> 0.32819245 | AI11: =((RawData!AI10-AVERAGE(RawData!$AI$3:$AI$40))/STDEV(RawData!$AI$3:$AI$40)) -> 0.55436816 | AJ11: =-1*((RawData!AJ10-AVERAGE(RawData!$AJ$3:$AJ$40))/STDEV(RawData!$AJ$3:$AJ$40)) -> 0.98675438 | AK11: =-1*((RawData!AK10-AVERAGE(RawData!$AK$3:$AK$40))/STDEV(RawData!$AK$3:$AK$40)) -> 0.55036113 | AL11: =-1*((RawData!AL10-AVERAGE(RawData!$AL$3:$AL$40))/STDEV(RawData!$AL$3:$AL$40)) -> -0.015120709 | AM11: =-1*((RawData!AM10-AVERAGE(RawData!$AM$3:$AM$40))/STDEV(RawData!$AM$3:$AM$40)) -> -0.74635186 | AN11: =((RawData!AN10-AVERAGE(RawData!$AN$3:$AN$40))/STDEV(RawData!$AN$3:$AN$40)) -> -2.7001367 | AO11: =-1*((RawData!AO10-AVERAGE(RawData!$AO$3:$AO$40))/STDEV(RawData!$AO$3:$AO$40)) -> 2.5684191 | AP11: =-1*((RawData!AP10-AVERAGE(RawData!$AP$3:$AP$40))/STDEV(RawData!$AP$3:$AP$40)) -> -0.48376743 | AQ11: =-1*((RawData!AQ10-AVERAGE(RawData!$AQ$3:$AQ$40))/STDEV(RawData!$AQ$3:$AQ$40)) -> 1.5732719
A12: =RawData!A11 -> Czech Republic | B12: =-1*((RawData!B11-AVERAGE(RawData!$B$3:$B$40))/STDEV(RawData!$B$3:$B$40)) -> 0.58631398 | C12: =((RawData!C11-AVERAGE(RawData!$C$3:$C$40))/STDEV(RawData!$C$3:$C$40)) -> -0.15800644 | D12: =((RawData!D11-AVERAGE(RawData!$D$3:$D$40))/STDEV(RawData!$D$3:$D$40)) -> -1.0594133 | E12: =((RawData!E11-AVERAGE(RawData!$E$3:$E$40))/STDEV(RawData!$E$3:$E$40)) -> 0.2103632 | F12: =((RawData!F11-AVERAGE(RawData!$F$3:$F$40))/STDEV(RawData!$F$3:$F$40)) -> 0.23002689 | G12: =((RawData!G11-AVERAGE(RawData!$G$3:$G$40))/STDEV(RawData!$G$3:$G$40)) -> 0.42027513 | H12: =((RawData!H11-AVERAGE(RawData!$H$3:$H$40))/STDEV(RawData!$H$3:$H$40)) -> -0.2662561 | I12: =((RawData!I11-AVERAGE(RawData!$I$3:$I$40))/STDEV(RawData!$I$3:$I$40)) -> -0.38409362 | J12: =-1*((RawData!J11-AVERAGE(RawData!$J$3:$J$40))/STDEV(RawData!$J$3:$J$40)) -> 0.9361174 | K12: =-1*((RawData!K11-AVERAGE(RawData!$K$3:$K$40))/STDEV(RawData!$K$3:$K$40)) -> -0.39509184 | L12: =-1*((RawData!L11-AVERAGE(RawData!$L$3:$L$40))/STDEV(RawData!$L$3:$L$40)) -> 0.6703676 | M12: =-1*((RawData!M11-AVERAGE(RawData!$M$3:$M$40))/STDEV(RawData!$M$3:$M$40)) -> 0.62106297 | N12: =-1*((RawData!N11-AVERAGE(RawData!$N$3:$N$40))/STDEV(RawData!$N$3:$N$40)) -> 0.33845396 | O12: =-1*((AbsValues!B11-AVERAGE(AbsValues!$B$3:$B$40))/STDEV(AbsValues!$B$3:$B$40)) -> 0.59391264 | P12: =-1*((RawData!P11-AVERAGE(RawData!$P$3:$P$40))/STDEV(RawData!$P$3:$P$40)) -> 1.2423429 | Q12: =-1*((RawData!Q11-AVERAGE(RawData!$Q$3:$Q$40))/STDEV(RawData!$Q$3:$Q$40)) -> 0.44866878 | R12: =-1*((RawData!R11-AVERAGE(RawData!$R$3:$R$40))/STDEV(RawData!$R$3:$R$40)) -> 0.50134373 | S12: =-1*((RawData!S11-AVERAGE(RawData!$S$3:$S$40))/STDEV(RawData!$S$3:$S$40)) -> 0.33845396 | T12: =-1*((AbsValues!C11-AVERAGE(AbsValues!$C$3:$C$40))/STDEV(AbsValues!$C$3:$C$40)) -> 0.32073762 | U12: =-1*((RawData!U11-AVERAGE(RawData!$U$3:$U$40))/STDEV(RawData!$U$3:$U$40)) -> -0.22846116 | V12: =-1*((RawData!V11-AVERAGE(RawData!$V$3:$V$40))/STDEV(RawData!$V$3:$V$40)) -> 0.15083421 | W12: =-1*((RawData!W11-AVERAGE(RawData!$W$3:$W$40))/STDEV(RawData!$W$3:$W$40)) -> -0.3169609 | X12: =-1*((RawData!X11-AVERAGE(RawData!$X$3:$X$40))/STDEV(RawData!$X$3:$X$40)) -> -2.0206751 | Y12: =((RawData!Y11-AVERAGE(RawData!$Y$3:$Y$40))/STDEV(RawData!$Y$3:$Y$40)) -> 0.36085131 | Z12: =((RawData!Z11-AVERAGE(RawData!$Z$3:$Z$40))/STDEV(RawData!$Z$3:$Z$40)) -> 0.18465614 | AA12: =-1*((RawData!AA11-AVERAGE(RawData!$AA$3:$AA$40))/STDEV(RawData!$AA$3:$AA$40)) -> 0.71688453 | AB12: =-1*((RawData!AB11-AVERAGE(RawData!$AB$3:$AB$40))/STDEV(RawData!$AB$3:$AB$40)) -> 0.44275606 | AC12: =-1*((RawData!AC11-AVERAGE(RawData!$AC$3:$AC$40))/STDEV(RawData!$AC$3:$AC$40)) -> -0.6703676 | AD12: =-1*((RawData!AD11-AVERAGE(RawData!$AD$3:$AD$40))/STDEV(RawData!$AD$3:$AD$40)) -> 2.2788116 | AE12: =-1*((RawData!AE11-AVERAGE(RawData!$AE$3:$AE$40))/STDEV(RawData!$AE$3:$AE$40)) -> 1.0401304 | AF12: =-1*((RawData!AF11-AVERAGE(RawData!$AF$3:$AF$40))/STDEV(RawData!$AF$3:$AF$40)) -> 0.58969853 | AG12: =-1*((RawData!AG11-AVERAGE(RawData!$AG$3:$AG$40))/STDEV(RawData!$AG$3:$AG$40)) -> 0.79687605 | AH12: =((RawData!AH11-AVERAGE(RawData!$AH$3:$AH$40))/STDEV(RawData!$AH$3:$AH$40)) -> 0.32819245 | AI12: =((RawData!AI11-AVERAGE(RawData!$AI$3:$AI$40))/STDEV(RawData!$AI$3:$AI$40)) -> 0.55436816 | AJ12: =-1*((RawData!AJ11-AVERAGE(RawData!$AJ$3:$AJ$40))/STDEV(RawData!$AJ$3:$AJ$40)) -> -0.98675438 | AK12: =-1*((RawData!AK11-AVERAGE(RawData!$AK$3:$AK$40))/STDEV(RawData!$AK$3:$AK$40)) -> 0.55036113 | AL12: =-1*((RawData!AL11-AVERAGE(RawData!$AL$3:$AL$40))/STDEV(RawData!$AL$3:$AL$40)) -> -0.015120709 | AM12: =-1*((RawData!AM11-AVERAGE(RawData!$AM$3:$AM$40))/STDEV(RawData!$AM$3:$AM$40)) -> 0.2620345 | AN12: =((RawData!AN11-AVERAGE(RawData!$AN$3:$AN$40))/STDEV(RawData!$AN$3:$AN$40)) -> 0.83020307 | AO12: =-1*((RawData!AO11-AVERAGE(RawData!$AO$3:$AO$40))/STDEV(RawData!$AO$3:$AO$40)) -> 0.61642058 | AP12: =-1*((RawData!AP11-AVERAGE(RawData!$AP$3:$AP$40))/STDEV(RawData!$AP$3:$AP$40)) -> -0.48376743 | AQ12: =-1*((RawData!AQ11-AVERAGE(RawData!$AQ$3:$AQ$40))/STDEV(RawData!$AQ$3:$AQ$40)) -> -0.68274065
A13: =RawData!A12 -> Germany | B13: =-1*((RawData!B12-AVERAGE(RawData!$B$3:$B$40))/STDEV(RawData!$B$3:$B$40)) -> -1.0738542 | C13: =((RawData!C12-AVERAGE(RawData!$C$3:$C$40))/STDEV(RawData!$C$3:$C$40)) -> -0.15800644 | D13: =((RawData!D12-AVERAGE(RawData!$D$3:$D$40))/STDEV(RawData!$D$3:$D$40)) -> 0.58981677 | E13: =((RawData!E12-AVERAGE(RawData!$E$3:$E$40))/STDEV(RawData!$E$3:$E$40)) -> 0.24279096 | F13: =((RawData!F12-AVERAGE(RawData!$F$3:$F$40))/STDEV(RawData!$F$3:$F$40)) -> -0.55513491 | G13: =((RawData!G12-AVERAGE(RawData!$G$3:$G$40))/STDEV(RawData!$G$3:$G$40)) -> 0.58161067 | H13: =((RawData!H12-AVERAGE(RawData!$H$3:$H$40))/STDEV(RawData!$H$3:$H$40)) -> 1.1791342 | I13: =((RawData!I12-AVERAGE(RawData!$I$3:$I$40))/STDEV(RawData!$I$3:$I$40)) -> -0.38409362 | J13: =-1*((RawData!J12-AVERAGE(RawData!$J$3:$J$40))/STDEV(RawData!$J$3:$J$40)) -> 0.9361174 | K13: =-1*((RawData!K12-AVERAGE(RawData!$K$3:$K$40))/STDEV(RawData!$K$3:$K$40)) -> -0.89845957 | L13: =-1*((RawData!L12-AVERAGE(RawData!$L$3:$L$40))/STDEV(RawData!$L$3:$L$40)) -> 0.6703676 | M13: =-1*((RawData!M12-AVERAGE(RawData!$M$3:$M$40))/STDEV(RawData!$M$3:$M$40)) -> 0.62106297 | N13: =-1*((RawData!N12-AVERAGE(RawData!$N$3:$N$40))/STDEV(RawData!$N$3:$N$40)) -> -2.8768587 | O13: =-1*((AbsValues!B12-AVERAGE(AbsValues!$B$3:$B$40))/STDEV(AbsValues!$B$3:$B$40)) -> 0.59391264 | P13: =-1*((RawData!P12-AVERAGE(RawData!$P$3:$P$40))/STDEV(RawData!$P$3:$P$40)) -> -0.14304859 | Q13: =-1*((RawData!Q12-AVERAGE(RawData!$Q$3:$Q$40))/STDEV(RawData!$Q$3:$Q$40)) -> 0.25936472 | R13: =-1*((RawData!R12-AVERAGE(RawData!$R$3:$R$40))/STDEV(RawData!$R$3:$R$40)) -> 0.6745694 | S13: =-1*((RawData!S12-AVERAGE(RawData!$S$3:$S$40))/STDEV(RawData!$S$3:$S$40)) -> -2.8768587 | T13: =-1*((AbsValues!C12-AVERAGE(AbsValues!$C$3:$C$40))/STDEV(AbsValues!$C$3:$C$40)) -> 0.32073762 | U13: =-1*((RawData!U12-AVERAGE(RawData!$U$3:$U$40))/STDEV(RawData!$U$3:$U$40)) -> -0.48371114 | V13: =-1*((RawData!V12-AVERAGE(RawData!$V$3:$V$40))/STDEV(RawData!$V$3:$V$40)) -> -0.14447578 | W13: =-1*((RawData!W12-AVERAGE(RawData!$W$3:$W$40))/STDEV(RawData!$W$3:$W$40)) -> 0.06784786 | X13: =-1*((RawData!X12-AVERAGE(RawData!$X$3:$X$40))/STDEV(RawData!$X$3:$X$40)) -> 0.43073313 | Y13: =((RawData!Y12-AVERAGE(RawData!$Y$3:$Y$40))/STDEV(RawData!$Y$3:$Y$40)) -> -0.16183976 | Z13: =((RawData!Z12-AVERAGE(RawData!$Z$3:$Z$40))/STDEV(RawData!$Z$3:$Z$40)) -> 0.18465614 | AA13: =-1*((RawData!AA12-AVERAGE(RawData!$AA$3:$AA$40))/STDEV(RawData!$AA$3:$AA$40)) -> 0.30723261 | AB13: =-1*((RawData!AB12-AVERAGE(RawData!$AB$3:$AB$40))/STDEV(RawData!$AB$3:$AB$40)) -> 0.44275606 | AC13: =-1*((RawData!AC12-AVERAGE(RawData!$AC$3:$AC$40))/STDEV(RawData!$AC$3:$AC$40)) -> -0.6703676 | AD13: =-1*((RawData!AD12-AVERAGE(RawData!$AD$3:$AD$40))/STDEV(RawData!$AD$3:$AD$40)) -> -0.42727718 | AE13: =-1*((RawData!AE12-AVERAGE(RawData!$AE$3:$AE$40))/STDEV(RawData!$AE$3:$AE$40)) -> 1.0401304 | AF13: =-1*((RawData!AF12-AVERAGE(RawData!$AF$3:$AF$40))/STDEV(RawData!$AF$3:$AF$40)) -> 0.58969853 | AG13: =-1*((RawData!AG12-AVERAGE(RawData!$AG$3:$AG$40))/STDEV(RawData!$AG$3:$AG$40)) -> 0.79687605 | AH13: =((RawData!AH12-AVERAGE(RawData!$AH$3:$AH$40))/STDEV(RawData!$AH$3:$AH$40)) -> 0.14370557 | AI13: =((RawData!AI12-AVERAGE(RawData!$AI$3:$AI$40))/STDEV(RawData!$AI$3:$AI$40)) -> 0.42738811 | AJ13: =-1*((RawData!AJ12-AVERAGE(RawData!$AJ$3:$AJ$40))/STDEV(RawData!$AJ$3:$AJ$40)) -> 0.98675438 | AK13: =-1*((RawData!AK12-AVERAGE(RawData!$AK$3:$AK$40))/STDEV(RawData!$AK$3:$AK$40)) -> -0.59173829 | AL13: =-1*((RawData!AL12-AVERAGE(RawData!$AL$3:$AL$40))/STDEV(RawData!$AL$3:$AL$40)) -> 1.2947279 | AM13: =-1*((RawData!AM12-AVERAGE(RawData!$AM$3:$AM$40))/STDEV(RawData!$AM$3:$AM$40)) -> 0.17884263 | AN13: =((RawData!AN12-AVERAGE(RawData!$AN$3:$AN$40))/STDEV(RawData!$AN$3:$AN$40)) -> 0.71753265 | AO13: =-1*((RawData!AO12-AVERAGE(RawData!$AO$3:$AO$40))/STDEV(RawData!$AO$3:$AO$40)) -> 0.61642058 | AP13: =-1*((RawData!AP12-AVERAGE(RawData!$AP$3:$AP$40))/STDEV(RawData!$AP$3:$AP$40)) -> -0.48376743 | AQ13: =-1*((RawData!AQ12-AVERAGE(RawData!$AQ$3:$AQ$40))/STDEV(RawData!$AQ$3:$AQ$40)) -> -0.68274065
A14: =RawData!A13 -> Denmark | B14: =-1*((RawData!B13-AVERAGE(RawData!$B$3:$B$40))/STDEV(RawData!$B$3:$B$40)) -> 0.40304135 | C14: =((RawData!C13-AVERAGE(RawData!$C$3:$C$40))/STDEV(RawData!$C$3:$C$40)) -> -0.24662998 | D14: =((RawData!D13-AVERAGE(RawData!$D$3:$D$40))/STDEV(RawData!$D$3:$D$40)) -> 0.33608906 | E14: =((RawData!E13-AVERAGE(RawData!$E$3:$E$40))/STDEV(RawData!$E$3:$E$40)) -> -0.36751786 | F14: =((RawData!F13-AVERAGE(RawData!$F$3:$F$40))/STDEV(RawData!$F$3:$F$40)) -> -0.55513491 | G14: =((RawData!G13-AVERAGE(RawData!$G$3:$G$40))/STDEV(RawData!$G$3:$G$40)) -> 0.26252277 | H14: =((RawData!H13-AVERAGE(RawData!$H$3:$H$40))/STDEV(RawData!$H$3:$H$40)) -> -1.7116464 | I14: =((RawData!I13-AVERAGE(RawData!$I$3:$I$40))/STDEV(RawData!$I$3:$I$40)) -> -0.38409362 | J14: =-1*((RawData!J13-AVERAGE(RawData!$J$3:$J$40))/STDEV(RawData!$J$3:$J$40)) -> 0.9361174 | K14: =-1*((RawData!K13-AVERAGE(RawData!$K$3:$K$40))/STDEV(RawData!$K$3:$K$40)) -> 1.3119813 | L14: =-1*((RawData!L13-AVERAGE(RawData!$L$3:$L$40))/STDEV(RawData!$L$3:$L$40)) -> -1.4524631 | M14: =-1*((RawData!M13-AVERAGE(RawData!$M$3:$M$40))/STDEV(RawData!$M$3:$M$40)) -> 0.62106297 | N14: =-1*((RawData!N13-AVERAGE(RawData!$N$3:$N$40))/STDEV(RawData!$N$3:$N$40)) -> 0.33845396 | O14: =-1*((AbsValues!B13-AVERAGE(AbsValues!$B$3:$B$40))/STDEV(AbsValues!$B$3:$B$40)) -> -0.42594905 | P14: =-1*((RawData!P13-AVERAGE(RawData!$P$3:$P$40))/STDEV(RawData!$P$3:$P$40)) -> -1.0500792 | Q14: =-1*((RawData!Q13-AVERAGE(RawData!$Q$3:$Q$40))/STDEV(RawData!$Q$3:$Q$40)) -> 0.62163709 | R14: =-1*((RawData!R13-AVERAGE(RawData!$R$3:$R$40))/STDEV(RawData!$R$3:$R$40)) -> 0.049027454 | S14: =-1*((RawData!S13-AVERAGE(RawData!$S$3:$S$40))/STDEV(RawData!$S$3:$S$40)) -> 0.33845396 | T14: =-1*((AbsValues!C13-AVERAGE(AbsValues!$C$3:$C$40))/STDEV(AbsValues!$C$3:$C$40)) -> 0.32073762 | U14: =-1*((RawData!U13-AVERAGE(RawData!$U$3:$U$40))/STDEV(RawData!$U$3:$U$40)) -> -1.665424 | V14: =-1*((RawData!V13-AVERAGE(RawData!$V$3:$V$40))/STDEV(RawData!$V$3:$V$40)) -> -1.5116517 | W14: =-1*((RawData!W13-AVERAGE(RawData!$W$3:$W$40))/STDEV(RawData!$W$3:$W$40)) -> -1.0865784 | X14: =-1*((RawData!X13-AVERAGE(RawData!$X$3:$X$40))/STDEV(RawData!$X$3:$X$40)) -> 0.98637605 | Y14: =((RawData!Y13-AVERAGE(RawData!$Y$3:$Y$40))/STDEV(RawData!$Y$3:$Y$40)) -> 0.57772646 | Z14: =((RawData!Z13-AVERAGE(RawData!$Z$3:$Z$40))/STDEV(RawData!$Z$3:$Z$40)) -> 0.18465614 | AA14: =-1*((RawData!AA13-AVERAGE(RawData!$AA$3:$AA$40))/STDEV(RawData!$AA$3:$AA$40)) -> 0.52790204 | AB14: =-1*((RawData!AB13-AVERAGE(RawData!$AB$3:$AB$40))/STDEV(RawData!$AB$3:$AB$40)) -> 0.44275606 | AC14: =-1*((RawData!AC13-AVERAGE(RawData!$AC$3:$AC$40))/STDEV(RawData!$AC$3:$AC$40)) -> -0.6703676 | AD14: =-1*((RawData!AD13-AVERAGE(RawData!$AD$3:$AD$40))/STDEV(RawData!$AD$3:$AD$40)) -> -0.42727718 | AE14: =-1*((RawData!AE13-AVERAGE(RawData!$AE$3:$AE$40))/STDEV(RawData!$AE$3:$AE$40)) -> 1.0401304 | AF14: =-1*((RawData!AF13-AVERAGE(RawData!$AF$3:$AF$40))/STDEV(RawData!$AF$3:$AF$40)) -> 0.58969853 | AG14: =-1*((RawData!AG13-AVERAGE(RawData!$AG$3:$AG$40))/STDEV(RawData!$AG$3:$AG$40)) -> 0.79687605 | AH14: =((RawData!AH13-AVERAGE(RawData!$AH$3:$AH$40))/STDEV(RawData!$AH$3:$AH$40)) -> 0.32819245 | AI14: =((RawData!AI13-AVERAGE(RawData!$AI$3:$AI$40))/STDEV(RawData!$AI$3:$AI$40)) -> 0.55436816 | AJ14: =-1*((RawData!AJ13-AVERAGE(RawData!$AJ$3:$AJ$40))/STDEV(RawData!$AJ$3:$AJ$40)) -> -0.98675438 | AK14: =-1*((RawData!AK13-AVERAGE(RawData!$AK$3:$AK$40))/STDEV(RawData!$AK$3:$AK$40)) -> -0.65449101 | AL14: =-1*((RawData!AL13-AVERAGE(RawData!$AL$3:$AL$40))/STDEV(RawData!$AL$3:$AL$40)) -> -0.62638341 | AM14: =-1*((RawData!AM13-AVERAGE(RawData!$AM$3:$AM$40))/STDEV(RawData!$AM$3:$AM$40)) -> -0.44383595 | AN14: =((RawData!AN13-AVERAGE(RawData!$AN$3:$AN$40))/STDEV(RawData!$AN$3:$AN$40)) -> 0.041510154 | AO14: =-1*((RawData!AO13-AVERAGE(RawData!$AO$3:$AO$40))/STDEV(RawData!$AO$3:$AO$40)) -> -1.3355779 | AP14: =-1*((RawData!AP13-AVERAGE(RawData!$AP$3:$AP$40))/STDEV(RawData!$AP$3:$AP$40)) -> -0.48376743 | AQ14: =-1*((RawData!AQ13-AVERAGE(RawData!$AQ$3:$AQ$40))/STDEV(RawData!$AQ$3:$AQ$40)) -> -0.68274065
A15: =RawData!A14 -> Estonia | B15: =-1*((RawData!B14-AVERAGE(RawData!$B$3:$B$40))/STDEV(RawData!$B$3:$B$40)) -> 0.40304135 | C15: =((RawData!C14-AVERAGE(RawData!$C$3:$C$40))/STDEV(RawData!$C$3:$C$40)) -> 4.1845469 | D15: =((RawData!D14-AVERAGE(RawData!$D$3:$D$40))/STDEV(RawData!$D$3:$D$40)) -> 1.3509999 | E15: =((RawData!E14-AVERAGE(RawData!$E$3:$E$40))/STDEV(RawData!$E$3:$E$40)) -> 1.7625147 | F15: =((RawData!F14-AVERAGE(RawData!$F$3:$F$40))/STDEV(RawData!$F$3:$F$40)) -> 2.5923737 | G15: =((RawData!G14-AVERAGE(RawData!$G$3:$G$40))/STDEV(RawData!$G$3:$G$40)) -> 1.3170924 | H15: =((RawData!H14-AVERAGE(RawData!$H$3:$H$40))/STDEV(RawData!$H$3:$H$40)) -> 1.1791342 | I15: =((RawData!I14-AVERAGE(RawData!$I$3:$I$40))/STDEV(RawData!$I$3:$I$40)) -> 2.5350179 | J15: =-1*((RawData!J14-AVERAGE(RawData!$J$3:$J$40))/STDEV(RawData!$J$3:$J$40)) -> 0.9361174 | K15: =-1*((RawData!K14-AVERAGE(RawData!$K$3:$K$40))/STDEV(RawData!$K$3:$K$40)) -> 1.0493547 | L15: =-1*((RawData!L14-AVERAGE(RawData!$L$3:$L$40))/STDEV(RawData!$L$3:$L$40)) -> 0.6703676 | M15: =-1*((RawData!M14-AVERAGE(RawData!$M$3:$M$40))/STDEV(RawData!$M$3:$M$40)) -> 0.62106297 | N15: =-1*((RawData!N14-AVERAGE(RawData!$N$3:$N$40))/STDEV(RawData!$N$3:$N$40)) -> 0.33845396 | O15: =-1*((AbsValues!B14-AVERAGE(AbsValues!$B$3:$B$40))/STDEV(AbsValues!$B$3:$B$40)) -> 0.59391264 | P15: =-1*((RawData!P14-AVERAGE(RawData!$P$3:$P$40))/STDEV(RawData!$P$3:$P$40)) -> 2.8133499 | Q15: =-1*((RawData!Q14-AVERAGE(RawData!$Q$3:$Q$40))/STDEV(RawData!$Q$3:$Q$40)) -> 0.72018932 | R15: =-1*((RawData!R14-AVERAGE(RawData!$R$3:$R$40))/STDEV(RawData!$R$3:$R$40)) -> -0.04008587 | S15: =-1*((RawData!S14-AVERAGE(RawData!$S$3:$S$40))/STDEV(RawData!$S$3:$S$40)) -> 0.33845396 | T15: =-1*((AbsValues!C14-AVERAGE(AbsValues!$C$3:$C$40))/STDEV(AbsValues!$C$3:$C$40)) -> 0.32073762 | U15: =-1*((RawData!U14-AVERAGE(RawData!$U$3:$U$40))/STDEV(RawData!$U$3:$U$40)) -> -0.15283154 | V15: =-1*((RawData!V14-AVERAGE(RawData!$V$3:$V$40))/STDEV(RawData!$V$3:$V$40)) -> 2.1633171 | W15: =-1*((RawData!W14-AVERAGE(RawData!$W$3:$W$40))/STDEV(RawData!$W$3:$W$40)) -> -0.89417403 | X15: =-1*((RawData!X14-AVERAGE(RawData!$X$3:$X$40))/STDEV(RawData!$X$3:$X$40)) -> -0.25702874 | Y15: =((RawData!Y14-AVERAGE(RawData!$Y$3:$Y$40))/STDEV(RawData!$Y$3:$Y$40)) -> 1.1710558 | Z15: =((RawData!Z14-AVERAGE(RawData!$Z$3:$Z$40))/STDEV(RawData!$Z$3:$Z$40)) -> 2.5236339 | AA15: =-1*((RawData!AA14-AVERAGE(RawData!$AA$3:$AA$40))/STDEV(RawData!$AA$3:$AA$40)) -> 0.52479408 | AB15: =-1*((RawData!AB14-AVERAGE(RawData!$AB$3:$AB$40))/STDEV(RawData!$AB$3:$AB$40)) -> 0.44275606 | AC15: =-1*((RawData!AC14-AVERAGE(RawData!$AC$3:$AC$40))/STDEV(RawData!$AC$3:$AC$40)) -> 1.4524631 | AD15: =-1*((RawData!AD14-AVERAGE(RawData!$AD$3:$AD$40))/STDEV(RawData!$AD$3:$AD$40)) -> 2.2788116 | AE15: =-1*((RawData!AE14-AVERAGE(RawData!$AE$3:$AE$40))/STDEV(RawData!$AE$3:$AE$40)) -> 1.0401304 | AF15: =-1*((RawData!AF14-AVERAGE(RawData!$AF$3:$AF$40))/STDEV(RawData!$AF$3:$AF$40)) -> 0.58969853 | AG15: =-1*((RawData!AG14-AVERAGE(RawData!$AG$3:$AG$40))/STDEV(RawData!$AG$3:$AG$40)) -> 0.79687605 | AH15: =((RawData!AH14-AVERAGE(RawData!$AH$3:$AH$40))/STDEV(RawData!$AH$3:$AH$40)) -> 0.32819245 | AI15: =((RawData!AI14-AVERAGE(RawData!$AI$3:$AI$40))/STDEV(RawData!$AI$3:$AI$40)) -> 0.55436816 | AJ15: =-1*((RawData!AJ14-AVERAGE(RawData!$AJ$3:$AJ$40))/STDEV(RawData!$AJ$3:$AJ$40)) -> -0.98675438 | AK15: =-1*((RawData!AK14-AVERAGE(RawData!$AK$3:$AK$40))/STDEV(RawData!$AK$3:$AK$40)) -> 2.0564263 | AL15: =-1*((RawData!AL14-AVERAGE(RawData!$AL$3:$AL$40))/STDEV(RawData!$AL$3:$AL$40)) -> 1.2947279 | AM15: =-1*((RawData!AM14-AVERAGE(RawData!$AM$3:$AM$40))/STDEV(RawData!$AM$3:$AM$40)) -> 0.76622769 | AN15: =((RawData!AN14-AVERAGE(RawData!$AN$3:$AN$40))/STDEV(RawData!$AN$3:$AN$40)) -> -0.48428512 | AO15: =-1*((RawData!AO14-AVERAGE(RawData!$AO$3:$AO$40))/STDEV(RawData!$AO$3:$AO$40)) -> 0.61642058 | AP15: =-1*((RawData!AP14-AVERAGE(RawData!$AP$3:$AP$40))/STDEV(RawData!$AP$3:$AP$40)) -> -0.48376743 | AQ15: =-1*((RawData!AQ14-AVERAGE(RawData!$AQ$3:$AQ$40))/STDEV(RawData!$AQ$3:$AQ$40)) -> 1.5732719
... A41: =RawData!A40 -> United States | B41: =-1*((RawData!B40-AVERAGE(RawData!$B$3:$B$40))/STDEV(RawData!$B$3:$B$40)) -> -0.25118953 | C41: =((RawData!C40-AVERAGE(RawData!$C$3:$C$40))/STDEV(RawData!$C$3:$C$40)) -> -0.24662998 | D41: =((RawData!D40-AVERAGE(RawData!$D$3:$D$40))/STDEV(RawData!$D$3:$D$40)) -> 0.84354448 | E41: =((RawData!E40-AVERAGE(RawData!$E$3:$E$40))/STDEV(RawData!$E$3:$E$40)) -> 1.7625147 | F41: =((RawData!F40-AVERAGE(RawData!$F$3:$F$40))/STDEV(RawData!$F$3:$F$40)) -> 2.5923737 | G41: =((RawData!G40-AVERAGE(RawData!$G$3:$G$40))/STDEV(RawData!$G$3:$G$40)) -> -0.75848453 | H41: =((RawData!H40-AVERAGE(RawData!$H$3:$H$40))/STDEV(RawData!$H$3:$H$40)) -> 1.1791342 | I41: =((RawData!I40-AVERAGE(RawData!$I$3:$I$40))/STDEV(RawData!$I$3:$I$40)) -> -0.38409362 | J41: =-1*((RawData!J40-AVERAGE(RawData!$J$3:$J$40))/STDEV(RawData!$J$3:$J$40)) -> -1.0401304 | K41: =-1*((RawData!K40-AVERAGE(RawData!$K$3:$K$40))/STDEV(RawData!$K$3:$K$40)) -> 1.1587825 | L41: =-1*((RawData!L40-AVERAGE(RawData!$L$3:$L$40))/STDEV(RawData!$L$3:$L$40)) -> 0.6703676 | M41: =-1*((RawData!M40-AVERAGE(RawData!$M$3:$M$40))/STDEV(RawData!$M$3:$M$40)) -> -0.09410045 | N41: =-1*((RawData!N40-AVERAGE(RawData!$N$3:$N$40))/STDEV(RawData!$N$3:$N$40)) -> 0.33845396 | O41: =-1*((AbsValues!B40-AVERAGE(AbsValues!$B$3:$B$40))/STDEV(AbsValues!$B$3:$B$40)) -> 0.59391264 | P41: =-1*((RawData!P40-AVERAGE(RawData!$P$3:$P$40))/STDEV(RawData!$P$3:$P$40)) -> 0.015666163 | Q41: =-1*((RawData!Q40-AVERAGE(RawData!$Q$3:$Q$40))/STDEV(RawData!$Q$3:$Q$40)) -> -0.18645457 | R41: =-1*((RawData!R40-AVERAGE(RawData!$R$3:$R$40))/STDEV(RawData!$R$3:$R$40)) -> -0.060536877 | S41: =-1*((RawData!S40-AVERAGE(RawData!$S$3:$S$40))/STDEV(RawData!$S$3:$S$40)) -> 0.33845396 | T41: =-1*((AbsValues!C40-AVERAGE(AbsValues!$C$3:$C$40))/STDEV(AbsValues!$C$3:$C$40)) -> 0.32073762 | U41: =-1*((RawData!U40-AVERAGE(RawData!$U$3:$U$40))/STDEV(RawData!$U$3:$U$40)) -> -0.67240704 | V41: =-1*((RawData!V40-AVERAGE(RawData!$V$3:$V$40))/STDEV(RawData!$V$3:$V$40)) -> -0.34499914 | W41: =-1*((RawData!W40-AVERAGE(RawData!$W$3:$W$40))/STDEV(RawData!$W$3:$W$40)) -> 2.2804982 | X41: =-1*((RawData!X40-AVERAGE(RawData!$X$3:$X$40))/STDEV(RawData!$X$3:$X$40)) -> 1.1513215 | Y41: =((RawData!Y40-AVERAGE(RawData!$Y$3:$Y$40))/STDEV(RawData!$Y$3:$Y$40)) -> -1.5819828 | Z41: =((RawData!Z40-AVERAGE(RawData!$Z$3:$Z$40))/STDEV(RawData!$Z$3:$Z$40)) -> 0.18465614 | AA41: =-1*((RawData!AA40-AVERAGE(RawData!$AA$3:$AA$40))/STDEV(RawData!$AA$3:$AA$40)) -> -2.5206137 | AB41: =-1*((RawData!AB40-AVERAGE(RawData!$AB$3:$AB$40))/STDEV(RawData!$AB$3:$AB$40)) -> 0.44275606 | AC41: =-1*((RawData!AC40-AVERAGE(RawData!$AC$3:$AC$40))/STDEV(RawData!$AC$3:$AC$40)) -> -0.6703676 | AD41: =-1*((RawData!AD40-AVERAGE(RawData!$AD$3:$AD$40))/STDEV(RawData!$AD$3:$AD$40)) -> -0.42727718 | AE41: =-1*((RawData!AE40-AVERAGE(RawData!$AE$3:$AE$40))/STDEV(RawData!$AE$3:$AE$40)) -> -0.9361174 | AF41: =-1*((RawData!AF40-AVERAGE(RawData!$AF$3:$AF$40))/STDEV(RawData!$AF$3:$AF$40)) -> 0.58969853 | AG41: =-1*((RawData!AG40-AVERAGE(RawData!$AG$3:$AG$40))/STDEV(RawData!$AG$3:$AG$40)) -> 0.79687605 | AH41: =((RawData!AH40-AVERAGE(RawData!$AH$3:$AH$40))/STDEV(RawData!$AH$3:$AH$40)) -> 0.32819245 | AI41: =((RawData!AI40-AVERAGE(RawData!$AI$3:$AI$40))/STDEV(RawData!$AI$3:$AI$40)) -> -1.9852328 | AJ41: =-1*((RawData!AJ40-AVERAGE(RawData!$AJ$3:$AJ$40))/STDEV(RawData!$AJ$3:$AJ$40)) -> 0.98675438 | AK41: =-1*((RawData!AK40-AVERAGE(RawData!$AK$3:$AK$40))/STDEV(RawData!$AK$3:$AK$40)) -> -0.95570405 | AL41: =-1*((RawData!AL40-AVERAGE(RawData!$AL$3:$AL$40))/STDEV(RawData!$AL$3:$AL$40)) -> -1.3249694 | AM41: =-1*((RawData!AM40-AVERAGE(RawData!$AM$3:$AM$40))/STDEV(RawData!$AM$3:$AM$40)) -> -1.250545 | AN41: =((RawData!AN40-AVERAGE(RawData!$AN$3:$AN$40))/STDEV(RawData!$AN$3:$AN$40)) -> -0.44672832 | AO41: =-1*((RawData!AO40-AVERAGE(RawData!$AO$3:$AO$40))/STDEV(RawData!$AO$3:$AO$40)) -> 0.61642058 | AP41: =-1*((RawData!AP40-AVERAGE(RawData!$AP$3:$AP$40))/STDEV(RawData!$AP$3:$AP$40)) -> -0.48376743 | AQ41: =-1*((RawData!AQ40-AVERAGE(RawData!$AQ$3:$AQ$40))/STDEV(RawData!$AQ$3:$AQ$40)) -> -0.68274065

Sheet Subcategories
A1: Subcategories — RAW (pre-rescale) Equal-Weighted Averages (LIVE)
A2: country | B2: corporate_rate | C2: cost_recovery | D2: incentives | E2: income_tax | F2: income_tax_complexity | G2: capital_gains_and_dividends | H2: consumption_tax_rate | I2: consumption_tax_base | J2: real_property_tax | K2: wealth_taxes | L2: capital_taxes | M2: territorial | N2: withholding_taxes | O2: tax_treaties | P2: international_regulations
A3: =RawData!A3 -> Austria | B3: =(ZScores!B4)/1 -> 0.21976872 | C3: =(ZScores!C4+ZScores!D4+ZScores!E4+ZScores!F4+ZScores!G4+ZScores!H4+ZScores!I4)/7 -> 0.087334194 | D3: =(ZScores!J4+ZScores!K4+ZScores!L4+ZScores!M4+ZScores!N4+ZScores!O4)/6 -> -0.17185145 | E3: =(ZScores!P4+ZScores!Q4+ZScores!R4)/3 -> -0.56449664 | F3: =(ZScores!S4+ZScores!T4)/2 -> 0.32959579 | G3: =(ZScores!U4+ZScores!V4)/2 -> -0.40585345 | H3: =(ZScores!W4)/1 -> -0.12455652 | I3: =(ZScores!X4+ZScores!Y4)/2 -> 0.067896098 | J3: =(ZScores!Z4+ZScores!AA4)/2 -> -0.81376412 | K3: =(ZScores!AB4+ZScores!AC4)/2 -> 0.94760959 | L3: =(ZScores!AD4+ZScores!AE4+ZScores!AF4+ZScores!AG4)/4 -> 0.0057950007 | M3: =(ZScores!AH4+ZScores!AI4+ZScores!AJ4)/3 -> 0.623105 | N3: =(ZScores!AK4+ZScores!AL4+ZScores!AM4)/3 -> 0.11595869 | O3: =(ZScores!AN4)/1 -> 0.49219182 | P3: =(ZScores!AO4+ZScores!AP4+ZScores!AQ4)/3 -> -0.83402866
A4: =RawData!A4 -> Australia | B4: =(ZScores!B5)/1 -> -1.0631397 | C4: =(ZScores!C5+ZScores!D5+ZScores!E5+ZScores!F5+ZScores!G5+ZScores!H5+ZScores!I5)/7 -> -0.13563177 | D4: =(ZScores!J5+ZScores!K5+ZScores!L5+ZScores!M5+ZScores!N5+ZScores!O5)/6 -> 0.29901542 | E4: =(ZScores!P5+ZScores!Q5+ZScores!R5)/3 -> 0.030696435 | F4: =(ZScores!S5+ZScores!T5)/2 -> 0.32959579 | G4: =(ZScores!U5+ZScores!V5)/2 -> -0.11397039 | H4: =(ZScores!W5)/1 -> 1.7994873 | I4: =(ZScores!X5+ZScores!Y5)/2 -> -0.36754749 | J4: =(ZScores!Z5+ZScores!AA5)/2 -> 1.5910564 | K4: =(ZScores!AB5+ZScores!AC5)/2 -> 0.94760959 | L4: =(ZScores!AD5+ZScores!AE5+ZScores!AF5+ZScores!AG5)/4 -> 0.0057950007 | M4: =(ZScores!AH5+ZScores!AI5+ZScores!AJ5)/3 -> 0.623105 | N4: =(ZScores!AK5+ZScores!AL5+ZScores!AM5)/3 -> -0.59491786 | O4: =(ZScores!AN5)/1 -> -1.0476372 | P4: =(ZScores!AO5+ZScores!AP5+ZScores!AQ5)/3 -> -0.1833625
A5: =RawData!A5 -> Belgium | B5: =(ZScores!B6)/1 -> -0.14677654 | C5: =(ZScores!C6+ZScores!D6+ZScores!E6+ZScores!F6+ZScores!G6+ZScores!H6+ZScores!I6)/7 -> 0.30504261 | D5: =(ZScores!J6+ZScores!K6+ZScores!L6+ZScores!M6+ZScores!N6+ZScores!O6)/6 -> 0.079179898 | E5: =(ZScores!P6+ZScores!Q6+ZScores!R6)/3 -> -0.34927694 | F5: =(ZScores!S6+ZScores!T6)/2 -> 0.32959579 | G5: =(ZScores!U6+ZScores!V6)/2 -> 0.52467977 | H5: =(ZScores!W6)/1 -> -0.3169609 | I5: =(ZScores!X6+ZScores!Y6)/2 -> -0.27323913 | J5: =(ZScores!Z6+ZScores!AA6)/2 -> -0.22687415 | K5: =(ZScores!AB6+ZScores!AC6)/2 -> -0.87856623 | L5: =(ZScores!AD6+ZScores!AE6+ZScores!AF6+ZScores!AG6)/4 -> -0.49889317 | M5: =(ZScores!AH6+ZScores!AI6+ZScores!AJ6)/3 -> 0.623105 | N5: =(ZScores!AK6+ZScores!AL6+ZScores!AM6)/3 -> -1.1770728 | O5: =(ZScores!AN6)/1 -> 0.71753265 | P5: =(ZScores!AO6+ZScores!AP6+ZScores!AQ6)/3 -> -0.83402866
A6: =RawData!A6 -> Canada | B6: =(ZScores!B7)/1 -> -0.32659485 | C6: =(ZScores!C7+ZScores!D7+ZScores!E7+ZScores!F7+ZScores!G7+ZScores!H7+ZScores!I7)/7 -> -0.11860992 | D6: =(ZScores!J7+ZScores!K7+ZScores!L7+ZScores!M7+ZScores!N7+ZScores!O7)/6 -> 0.18464829 | E6: =(ZScores!P7+ZScores!Q7+ZScores!R7)/3 -> -0.093892783 | F6: =(ZScores!S7+ZScores!T7)/2 -> 0.32959579 | G6: =(ZScores!U7+ZScores!V7)/2 -> -0.89564211 | H6: =(ZScores!W7)/1 -> 1.3569572 | I6: =(ZScores!X7+ZScores!Y7)/2 -> 0.19089917 | J6: =(ZScores!Z7+ZScores!AA7)/2 -> -0.6273913 | K6: =(ZScores!AB7+ZScores!AC7)/2 -> 0.94760959 | L6: =(ZScores!AD7+ZScores!AE7+ZScores!AF7+ZScores!AG7)/4 -> -0.55441861 | M6: =(ZScores!AH7+ZScores!AI7+ZScores!AJ7)/3 -> -0.45799809 | N6: =(ZScores!AK7+ZScores!AL7+ZScores!AM7)/3 -> -0.69612911 | O6: =(ZScores!AN7)/1 -> 0.75508946 | P6: =(ZScores!AO7+ZScores!AP7+ZScores!AQ7)/3 -> 0.49749536
A7: =RawData!A7 -> Switzerland | B7: =(ZScores!B8)/1 -> 0.84146229 | C7: =(ZScores!C8+ZScores!D8+ZScores!E8+ZScores!F8+ZScores!G8+ZScores!H8+ZScores!I8)/7 -> 0.093009732 | D7: =(ZScores!J8+ZScores!K8+ZScores!L8+ZScores!M8+ZScores!N8+ZScores!O8)/6 -> -0.26276368 | E7: =(ZScores!P8+ZScores!Q8+ZScores!R8)/3 -> 0.17482241 | F7: =(ZScores!S8+ZScores!T8)/2 -> 0.32959579 | G7: =(ZScores!U8+ZScores!V8)/2 -> 0.8678956 | H7: =(ZScores!W8)/1 -> 2.1650556 | I7: =(ZScores!X8+ZScores!Y8)/2 -> 0.030322697 | J7: =(ZScores!Z8+ZScores!AA8)/2 -> 0.36923113 | K7: =(ZScores!AB8+ZScores!AC8)/2 -> -1.6433267 | L7: =(ZScores!AD8+ZScores!AE8+ZScores!AF8+ZScores!AG8)/4 -> -1.0591068 | M7: =(ZScores!AH8+ZScores!AI8+ZScores!AJ8)/3 -> 0.623105 | N7: =(ZScores!AK8+ZScores!AL8+ZScores!AM8)/3 -> -0.48156577 | O7: =(ZScores!AN8)/1 -> 1.2808847 | P7: =(ZScores!AO8+ZScores!AP8+ZScores!AQ8)/3 -> 1.5241636
A8: =RawData!A8 -> Chile | B8: =(ZScores!B9)/1 -> -0.51332181 | C8: =(ZScores!C9+ZScores!D9+ZScores!E9+ZScores!F9+ZScores!G9+ZScores!H9+ZScores!I9)/7 -> -1.0669064 | D8: =(ZScores!J9+ZScores!K9+ZScores!L9+ZScores!M9+ZScores!N9+ZScores!O9)/6 -> 0.44269233 | E8: =(ZScores!P9+ZScores!Q9+ZScores!R9)/3 -> -0.14030183 | F8: =(ZScores!S9+ZScores!T9)/2 -> 0.32959579 | G8: =(ZScores!U9+ZScores!V9)/2 -> -0.72121974 | H8: =(ZScores!W9)/1 -> 0.06784786 | I8: =(ZScores!X9+ZScores!Y9)/2 -> 1.0498952 | J8: =(ZScores!Z9+ZScores!AA9)/2 -> 0.45383419 | K8: =(ZScores!AB9+ZScores!AC9)/2 -> -0.11380577 | L8: =(ZScores!AD9+ZScores!AE9+ZScores!AF9+ZScores!AG9)/4 -> 0.6823172 | M8: =(ZScores!AH9+ZScores!AI9+ZScores!AJ9)/3 -> -2.1111774 | N8: =(ZScores!AK9+ZScores!AL9+ZScores!AM9)/3 -> -1.4899521 | O8: =(ZScores!AN9)/1 -> -1.4607621 | P8: =(ZScores!AO9+ZScores!AP9+ZScores!AQ9)/3 -> 0.92416647
A9: =RawData!A9 -> Colombia | B9: =(ZScores!B10)/1 -> -1.9795029 | C9: =(ZScores!C10+ZScores!D10+ZScores!E10+ZScores!F10+ZScores!G10+ZScores!H10+ZScores!I10)/7 -> -0.52249771 | D9: =(ZScores!J10+ZScores!K10+ZScores!L10+ZScores!M10+ZScores!N10+ZScores!O10)/6 -> 0.033567072 | E9: =(ZScores!P10+ZScores!Q10+ZScores!R10)/3 -> 0.3119505 | F9: =(ZScores!S10+ZScores!T10)/2 -> -0.092469636 | G9: =(ZScores!U10+ZScores!V10)/2 -> 0.39495389 | H9: =(ZScores!W10)/1 -> 0.06784786 | I9: =(ZScores!X10+ZScores!Y10)/2 -> -0.10862858 | J9: =(ZScores!Z10+ZScores!AA10)/2 -> 0.45449519 | K9: =(ZScores!AB10+ZScores!AC10)/2 -> -1.6433267 | L9: =(ZScores!AD10+ZScores!AE10+ZScores!AF10+ZScores!AG10)/4 -> -0.56504481 | M9: =(ZScores!AH10+ZScores!AI10+ZScores!AJ10)/3 -> -1.4533412 | N9: =(ZScores!AK10+ZScores!AL10+ZScores!AM10)/3 -> -0.2151854 | O9: =(ZScores!AN10)/1 -> -2.3245686 | P9: =(ZScores!AO10+ZScores!AP10+ZScores!AQ10)/3 -> 0.59883339
A10: =RawData!A10 -> Costa Rica | B10: =(ZScores!B11)/1 -> -1.0631397 | C10: =(ZScores!C11+ZScores!D11+ZScores!E11+ZScores!F11+ZScores!G11+ZScores!H11+ZScores!I11)/7 -> -0.5329417 | D10: =(ZScores!J11+ZScores!K11+ZScores!L11+ZScores!M11+ZScores!N11+ZScores!O11)/6 -> -0.086187156 | E10: =(ZScores!P11+ZScores!Q11+ZScores!R11)/3 -> 0.67848114 | F10: =(ZScores!S11+ZScores!T11)/2 -> -1.761032 | G10: =(ZScores!U11+ZScores!V11)/2 -> 0.61370203 | H10: =(ZScores!W11)/1 -> 1.2222741 | I10: =(ZScores!X11+ZScores!Y11)/2 -> 0.35990817 | J10: =(ZScores!Z11+ZScores!AA11)/2 -> 0.45417 | K10: =(ZScores!AB11+ZScores!AC11)/2 -> 0.94760959 | L10: =(ZScores!AD11+ZScores!AE11+ZScores!AF11+ZScores!AG11)/4 -> -0.49889317 | M10: =(ZScores!AH11+ZScores!AI11+ZScores!AJ11)/3 -> 0.623105 | N10: =(ZScores!AK11+ZScores!AL11+ZScores!AM11)/3 -> -0.070370478 | O10: =(ZScores!AN11)/1 -> -2.7001367 | P10: =(ZScores!AO11+ZScores!AP11+ZScores!AQ11)/3 -> 1.2193079
A11: =RawData!A11 -> Czech Republic | B11: =(ZScores!B12)/1 -> 0.58631398 | C11: =(ZScores!C12+ZScores!D12+ZScores!E12+ZScores!F12+ZScores!G12+ZScores!H12+ZScores!I12)/7 -> -0.14387204 | D11: =(ZScores!J12+ZScores!K12+ZScores!L12+ZScores!M12+ZScores!N12+ZScores!O12)/6 -> 0.46080379 | E11: =(ZScores!P12+ZScores!Q12+ZScores!R12)/3 -> 0.73078514 | F11: =(ZScores!S12+ZScores!T12)/2 -> 0.32959579 | G11: =(ZScores!U12+ZScores!V12)/2 -> -0.038813479 | H11: =(ZScores!W12)/1 -> -0.3169609 | I11: =(ZScores!X12+ZScores!Y12)/2 -> -0.82991189 | J11: =(ZScores!Z12+ZScores!AA12)/2 -> 0.45077034 | K11: =(ZScores!AB12+ZScores!AC12)/2 -> -0.11380577 | L11: =(ZScores!AD12+ZScores!AE12+ZScores!AF12+ZScores!AG12)/4 -> 1.1763792 | M11: =(ZScores!AH12+ZScores!AI12+ZScores!AJ12)/3 -> -0.034731258 | N11: =(ZScores!AK12+ZScores!AL12+ZScores!AM12)/3 -> 0.26575831 | O11: =(ZScores!AN12)/1 -> 0.83020307 | P11: =(ZScores!AO12+ZScores!AP12+ZScores!AQ12)/3 -> -0.1833625
A12: =RawData!A12 -> Germany | B12: =(ZScores!B13)/1 -> -1.0738542 | C12: =(ZScores!C13+ZScores!D13+ZScores!E13+ZScores!F13+ZScores!G13+ZScores!H13+ZScores!I13)/7 -> 0.21373109 | D12: =(ZScores!J13+ZScores!K13+ZScores!L13+ZScores!M13+ZScores!N13+ZScores!O13)/6 -> -0.15897627 | E12: =(ZScores!P13+ZScores!Q13+ZScores!R13)/3 -> 0.26362851 | F12: =(ZScores!S13+ZScores!T13)/2 -> -1.2780605 | G12: =(ZScores!U13+ZScores!V13)/2 -> -0.31409346 | H12: =(ZScores!W13)/1 -> 0.06784786 | I12: =(ZScores!X13+ZScores!Y13)/2 -> 0.13444669 | J12: =(ZScores!Z13+ZScores!AA13)/2 -> 0.24594437 | K12: =(ZScores!AB13+ZScores!AC13)/2 -> -0.11380577 | L12: =(ZScores!AD13+ZScores!AE13+ZScores!AF13+ZScores!AG13)/4 -> 0.49985696 | M12: =(ZScores!AH13+ZScores!AI13+ZScores!AJ13)/3 -> 0.51928269 | N12: =(ZScores!AK13+ZScores!AL13+ZScores!AM13)/3 -> 0.29394409 | O12: =(ZScores!AN13)/1 -> 0.71753265 | P12: =(ZScores!AO13+ZScores!AP13+ZScores!AQ13)/3 -> -0.1833625
A13: =RawData!A13 -> Denmark | B13: =(ZScores!B14)/1 -> 0.40304135 | C13: =(ZScores!C14+ZScores!D14+ZScores!E14+ZScores!F14+ZScores!G14+ZScores!H14+ZScores!I14)/7 -> -0.38091584 | D13: =(ZScores!J14+ZScores!K14+ZScores!L14+ZScores!M14+ZScores!N14+ZScores!O14)/6 -> 0.22153392 | E13: =(ZScores!P14+ZScores!Q14+ZScores!R14)/3 -> -0.12647155 | F13: =(ZScores!S14+ZScores!T14)/2 -> 0.32959579 | G13: =(ZScores!U14+ZScores!V14)/2 -> -1.5885378 | H13: =(ZScores!W14)/1 -> -1.0865784 | I13: =(ZScores!X14+ZScores!Y14)/2 -> 0.78205126 | J13: =(ZScores!Z14+ZScores!AA14)/2 -> 0.35627909 | K13: =(ZScores!AB14+ZScores!AC14)/2 -> -0.11380577 | L13: =(ZScores!AD14+ZScores!AE14+ZScores!AF14+ZScores!AG14)/4 -> 0.49985696 | M13: =(ZScores!AH14+ZScores!AI14+ZScores!AJ14)/3 -> -0.034731258 | N13: =(ZScores!AK14+ZScores!AL14+ZScores!AM14)/3 -> -0.57490346 | O13: =(ZScores!AN14)/1 -> 0.041510154 | P13: =(ZScores!AO14+ZScores!AP14+ZScores!AQ14)/3 -> -0.83402866
A14: =RawData!A14 -> Estonia | B14: =(ZScores!B15)/1 -> 0.40304135 | C14: =(ZScores!C15+ZScores!D15+ZScores!E15+ZScores!F15+ZScores!G15+ZScores!H15+ZScores!I15)/7 -> 2.1316685 | D14: =(ZScores!J15+ZScores!K15+ZScores!L15+ZScores!M15+ZScores!N15+ZScores!O15)/6 -> 0.70154488 | E14: =(ZScores!P15+ZScores!Q15+ZScores!R15)/3 -> 1.1644845 | F14: =(ZScores!S15+ZScores!T15)/2 -> 0.32959579 | G14: =(ZScores!U15+ZScores!V15)/2 -> 1.0052428 | H14: =(ZScores!W15)/1 -> -0.89417403 | I14: =(ZScores!X15+ZScores!Y15)/2 -> 0.45701354 | J14: =(ZScores!Z15+ZScores!AA15)/2 -> 1.524214 | K14: =(ZScores!AB15+ZScores!AC15)/2 -> 0.94760959 | L14: =(ZScores!AD15+ZScores!AE15+ZScores!AF15+ZScores!AG15)/4 -> 1.1763792 | M14: =(ZScores!AH15+ZScores!AI15+ZScores!AJ15)/3 -> -0.034731258 | N14: =(ZScores!AK15+ZScores!AL15+ZScores!AM15)/3 -> 1.3724606 | O14: =(ZScores!AN15)/1 -> -0.48428512 | P14: =(ZScores!AO15+ZScores!AP15+ZScores!AQ15)/3 -> 0.56864169
... A40: =RawData!A40 -> United States | B40: =(ZScores!B41)/1 -> -0.25118953 | C40: =(ZScores!C41+ZScores!D41+ZScores!E41+ZScores!F41+ZScores!G41+ZScores!H41+ZScores!I41)/7 -> 0.71262271 | D40: =(ZScores!J41+ZScores!K41+ZScores!L41+ZScores!M41+ZScores!N41+ZScores!O41)/6 -> 0.2712143 | E40: =(ZScores!P41+ZScores!Q41+ZScores!R41)/3 -> -0.07710843 | F40: =(ZScores!S41+ZScores!T41)/2 -> 0.32959579 | G40: =(ZScores!U41+ZScores!V41)/2 -> -0.50870309 | H40: =(ZScores!W41)/1 -> 2.2804982 | I40: =(ZScores!X41+ZScores!Y41)/2 -> -0.21533063 | J40: =(ZScores!Z41+ZScores!AA41)/2 -> -1.1679788 | K40: =(ZScores!AB41+ZScores!AC41)/2 -> -0.11380577 | L40: =(ZScores!AD41+ZScores!AE41+ZScores!AF41+ZScores!AG41)/4 -> 0.0057950007 | M40: =(ZScores!AH41+ZScores!AI41+ZScores!AJ41)/3 -> -0.22342866 | N40: =(ZScores!AK41+ZScores!AL41+ZScores!AM41)/3 -> -1.1770728 | O40: =(ZScores!AN41)/1 -> -0.44672832 | P40: =(ZScores!AO41+ZScores!AP41+ZScores!AQ41)/3 -> -0.1833625

Sheet SubcategoriesScored
A1: Subcategories — Rescaled to 0-100 (LIVE)
A2: score2(x): shift so MIN becomes 1 (eliminates negatives), then scale so MAX becomes 100.
A3: country | B3: corporate_rate | C3: cost_recovery | D3: incentives | E3: income_tax | F3: income_tax_complexity | G3: capital_gains_and_dividends | H3: consumption_tax_rate | I3: consumption_tax_base | J3: real_property_tax | K3: wealth_taxes | L3: capital_taxes | M3: territorial | N3: withholding_taxes | O3: tax_treaties | P3: international_regulations
A4: =RawData!A3 -> Austria | B4: =(Subcategories!B3-MIN(Subcategories!$B$3:$B$40)+1)/(MAX(Subcategories!$B$3:$B$40)-MIN(Subcategories!$B$3:$B$40)+1)*100 -> 57.037228 | C4: =(Subcategories!C3-MIN(Subcategories!$C$3:$C$40)+1)/(MAX(Subcategories!$C$3:$C$40)-MIN(Subcategories!$C$3:$C$40)+1)*100 -> 51.308852 | D4: =(Subcategories!D3-MIN(Subcategories!$D$3:$D$40)+1)/(MAX(Subcategories!$D$3:$D$40)-MIN(Subcategories!$D$3:$D$40)+1)*100 -> 69.764142 | E4: =(Subcategories!E3-MIN(Subcategories!$E$3:$E$40)+1)/(MAX(Subcategories!$E$3:$E$40)-MIN(Subcategories!$E$3:$E$40)+1)*100 -> 40.577319 | F4: =(Subcategories!F3-MIN(Subcategories!$F$3:$F$40)+1)/(MAX(Subcategories!$F$3:$F$40)-MIN(Subcategories!$F$3:$F$40)+1)*100 -> 100 | G4: =(Subcategories!G3-MIN(Subcategories!$G$3:$G$40)+1)/(MAX(Subcategories!$G$3:$G$40)-MIN(Subcategories!$G$3:$G$40)+1)*100 -> 52.485978 | H4: =(Subcategories!H3-MIN(Subcategories!$H$3:$H$40)+1)/(MAX(Subcategories!$H$3:$H$40)-MIN(Subcategories!$H$3:$H$40)+1)*100 -> 49.387358 | I4: =(Subcategories!I3-MIN(Subcategories!$I$3:$I$40)+1)/(MAX(Subcategories!$I$3:$I$40)-MIN(Subcategories!$I$3:$I$40)+1)*100 -> 58.548483 | J4: =(Subcategories!J3-MIN(Subcategories!$J$3:$J$40)+1)/(MAX(Subcategories!$J$3:$J$40)-MIN(Subcategories!$J$3:$J$40)+1)*100 -> 45.804792 | K4: =(Subcategories!K3-MIN(Subcategories!$K$3:$K$40)+1)/(MAX(Subcategories!$K$3:$K$40)-MIN(Subcategories!$K$3:$K$40)+1)*100 -> 100 | L4: =(Subcategories!L3-MIN(Subcategories!$L$3:$L$40)+1)/(MAX(Subcategories!$L$3:$L$40)-MIN(Subcategories!$L$3:$L$40)+1)*100 -> 63.820453 | M4: =(Subcategories!M3-MIN(Subcategories!$M$3:$M$40)+1)/(MAX(Subcategories!$M$3:$M$40)-MIN(Subcategories!$M$3:$M$40)+1)*100 -> 100 | N4: =(Subcategories!N3-MIN(Subcategories!$N$3:$N$40)+1)/(MAX(Subcategories!$N$3:$N$40)-MIN(Subcategories!$N$3:$N$40)+1)*100 -> 62.067048 | O4: =(Subcategories!O3-MIN(Subcategories!$O$3:$O$40)+1)/(MAX(Subcategories!$O$3:$O$40)-MIN(Subcategories!$O$3:$O$40)+1)*100 -> 72.191024 | P4: =(Subcategories!P3-MIN(Subcategories!$P$3:$P$40)+1)/(MAX(Subcategories!$P$3:$P$40)-MIN(Subcategories!$P$3:$P$40)+1)*100 -> 26.564757
A5: =RawData!A4 -> Australia | B5: =(Subcategories!B4-MIN(Subcategories!$B$3:$B$40)+1)/(MAX(Subcategories!$B$3:$B$40)-MIN(Subcategories!$B$3:$B$40)+1)*100 -> 35.555843 | C5: =(Subcategories!C4-MIN(Subcategories!$C$3:$C$40)+1)/(MAX(Subcategories!$C$3:$C$40)-MIN(Subcategories!$C$3:$C$40)+1)*100 -> 45.998336 | D5: =(Subcategories!D4-MIN(Subcategories!$D$3:$D$40)+1)/(MAX(Subcategories!$D$3:$D$40)-MIN(Subcategories!$D$3:$D$40)+1)*100 -> 83.310971 | E5: =(Subcategories!E4-MIN(Subcategories!$E$3:$E$40)+1)/(MAX(Subcategories!$E$3:$E$40)-MIN(Subcategories!$E$3:$E$40)+1)*100 -> 61.033279 | F5: =(Subcategories!F4-MIN(Subcategories!$F$3:$F$40)+1)/(MAX(Subcategories!$F$3:$F$40)-MIN(Subcategories!$F$3:$F$40)+1)*100 -> 100 | G5: =(Subcategories!G4-MIN(Subcategories!$G$3:$G$40)+1)/(MAX(Subcategories!$G$3:$G$40)-MIN(Subcategories!$G$3:$G$40)+1)*100 -> 59.337095 | H5: =(Subcategories!H4-MIN(Subcategories!$H$3:$H$40)+1)/(MAX(Subcategories!$H$3:$H$40)-MIN(Subcategories!$H$3:$H$40)+1)*100 -> 89.877472 | I5: =(Subcategories!I4-MIN(Subcategories!$I$3:$I$40)+1)/(MAX(Subcategories!$I$3:$I$40)-MIN(Subcategories!$I$3:$I$40)+1)*100 -> 48.001296 | J5: =(Subcategories!J4-MIN(Subcategories!$J$3:$J$40)+1)/(MAX(Subcategories!$J$3:$J$40)-MIN(Subcategories!$J$3:$J$40)+1)*100 -> 100 | K5: =(Subcategories!K4-MIN(Subcategories!$K$3:$K$40)+1)/(MAX(Subcategories!$K$3:$K$40)-MIN(Subcategories!$K$3:$K$40)+1)*100 -> 100 | L5: =(Subcategories!L4-MIN(Subcategories!$L$3:$L$40)+1)/(MAX(Subcategories!$L$3:$L$40)-MIN(Subcategories!$L$3:$L$40)+1)*100 -> 63.820453 | M5: =(Subcategories!M4-MIN(Subcategories!$M$3:$M$40)+1)/(MAX(Subcategories!$M$3:$M$40)-MIN(Subcategories!$M$3:$M$40)+1)*100 -> 100 | N5: =(Subcategories!N4-MIN(Subcategories!$N$3:$N$40)+1)/(MAX(Subcategories!$N$3:$N$40)-MIN(Subcategories!$N$3:$N$40)+1)*100 -> 45.135537 | O5: =(Subcategories!O4-MIN(Subcategories!$O$3:$O$40)+1)/(MAX(Subcategories!$O$3:$O$40)-MIN(Subcategories!$O$3:$O$40)+1)*100 -> 45.675488 | P5: =(Subcategories!P4-MIN(Subcategories!$P$3:$P$40)+1)/(MAX(Subcategories!$P$3:$P$40)-MIN(Subcategories!$P$3:$P$40)+1)*100 -> 43.849545
A6: =RawData!A5 -> Belgium | B6: =(Subcategories!B5-MIN(Subcategories!$B$3:$B$40)+1)/(MAX(Subcategories!$B$3:$B$40)-MIN(Subcategories!$B$3:$B$40)+1)*100 -> 50.89969 | C6: =(Subcategories!C5-MIN(Subcategories!$C$3:$C$40)+1)/(MAX(Subcategories!$C$3:$C$40)-MIN(Subcategories!$C$3:$C$40)+1)*100 -> 56.494145 | D6: =(Subcategories!D5-MIN(Subcategories!$D$3:$D$40)+1)/(MAX(Subcategories!$D$3:$D$40)-MIN(Subcategories!$D$3:$D$40)+1)*100 -> 76.986308 | E6: =(Subcategories!E5-MIN(Subcategories!$E$3:$E$40)+1)/(MAX(Subcategories!$E$3:$E$40)-MIN(Subcategories!$E$3:$E$40)+1)*100 -> 47.974122 | F6: =(Subcategories!F5-MIN(Subcategories!$F$3:$F$40)+1)/(MAX(Subcategories!$F$3:$F$40)-MIN(Subcategories!$F$3:$F$40)+1)*100 -> 100 | G6: =(Subcategories!G5-MIN(Subcategories!$G$3:$G$40)+1)/(MAX(Subcategories!$G$3:$G$40)-MIN(Subcategories!$G$3:$G$40)+1)*100 -> 74.327575 | H6: =(Subcategories!H5-MIN(Subcategories!$H$3:$H$40)+1)/(MAX(Subcategories!$H$3:$H$40)-MIN(Subcategories!$H$3:$H$40)+1)*100 -> 45.338347 | I6: =(Subcategories!I5-MIN(Subcategories!$I$3:$I$40)+1)/(MAX(Subcategories!$I$3:$I$40)-MIN(Subcategories!$I$3:$I$40)+1)*100 -> 50.285605 | J6: =(Subcategories!J5-MIN(Subcategories!$J$3:$J$40)+1)/(MAX(Subcategories!$J$3:$J$40)-MIN(Subcategories!$J$3:$J$40)+1)*100 -> 59.030987 | K6: =(Subcategories!K5-MIN(Subcategories!$K$3:$K$40)+1)/(MAX(Subcategories!$K$3:$K$40)-MIN(Subcategories!$K$3:$K$40)+1)*100 -> 49.144856 | L6: =(Subcategories!L5-MIN(Subcategories!$L$3:$L$40)+1)/(MAX(Subcategories!$L$3:$L$40)-MIN(Subcategories!$L$3:$L$40)+1)*100 -> 48.221925 | M6: =(Subcategories!M5-MIN(Subcategories!$M$3:$M$40)+1)/(MAX(Subcategories!$M$3:$M$40)-MIN(Subcategories!$M$3:$M$40)+1)*100 -> 100 | N6: =(Subcategories!N5-MIN(Subcategories!$N$3:$N$40)+1)/(MAX(Subcategories!$N$3:$N$40)-MIN(Subcategories!$N$3:$N$40)+1)*100 -> 31.26989 | O6: =(Subcategories!O5-MIN(Subcategories!$O$3:$O$40)+1)/(MAX(Subcategories!$O$3:$O$40)-MIN(Subcategories!$O$3:$O$40)+1)*100 -> 76.071346 | P6: =(Subcategories!P5-MIN(Subcategories!$P$3:$P$40)+1)/(MAX(Subcategories!$P$3:$P$40)-MIN(Subcategories!$P$3:$P$40)+1)*100 -> 26.564757
A7: =RawData!A6 -> Canada | B7: =(Subcategories!B6-MIN(Subcategories!$B$3:$B$40)+1)/(MAX(Subcategories!$B$3:$B$40)-MIN(Subcategories!$B$3:$B$40)+1)*100 -> 47.88876 | C7: =(Subcategories!C6-MIN(Subcategories!$C$3:$C$40)+1)/(MAX(Subcategories!$C$3:$C$40)-MIN(Subcategories!$C$3:$C$40)+1)*100 -> 46.403756 | D7: =(Subcategories!D6-MIN(Subcategories!$D$3:$D$40)+1)/(MAX(Subcategories!$D$3:$D$40)-MIN(Subcategories!$D$3:$D$40)+1)*100 -> 80.020631 | E7: =(Subcategories!E6-MIN(Subcategories!$E$3:$E$40)+1)/(MAX(Subcategories!$E$3:$E$40)-MIN(Subcategories!$E$3:$E$40)+1)*100 -> 56.751321 | F7: =(Subcategories!F6-MIN(Subcategories!$F$3:$F$40)+1)/(MAX(Subcategories!$F$3:$F$40)-MIN(Subcategories!$F$3:$F$40)+1)*100 -> 100 | G7: =(Subcategories!G6-MIN(Subcategories!$G$3:$G$40)+1)/(MAX(Subcategories!$G$3:$G$40)-MIN(Subcategories!$G$3:$G$40)+1)*100 -> 40.989594 | H7: =(Subcategories!H6-MIN(Subcategories!$H$3:$H$40)+1)/(MAX(Subcategories!$H$3:$H$40)-MIN(Subcategories!$H$3:$H$40)+1)*100 -> 80.564746 | I7: =(Subcategories!I6-MIN(Subcategories!$I$3:$I$40)+1)/(MAX(Subcategories!$I$3:$I$40)-MIN(Subcategories!$I$3:$I$40)+1)*100 -> 61.527827 | J7: =(Subcategories!J6-MIN(Subcategories!$J$3:$J$40)+1)/(MAX(Subcategories!$J$3:$J$40)-MIN(Subcategories!$J$3:$J$40)+1)*100 -> 50.004904 | K7: =(Subcategories!K6-MIN(Subcategories!$K$3:$K$40)+1)/(MAX(Subcategories!$K$3:$K$40)-MIN(Subcategories!$K$3:$K$40)+1)*100 -> 100 | L7: =(Subcategories!L6-MIN(Subcategories!$L$3:$L$40)+1)/(MAX(Subcategories!$L$3:$L$40)-MIN(Subcategories!$L$3:$L$40)+1)*100 -> 46.505786 | M7: =(Subcategories!M6-MIN(Subcategories!$M$3:$M$40)+1)/(MAX(Subcategories!$M$3:$M$40)-MIN(Subcategories!$M$3:$M$40)+1)*100 -> 71.049242 | N7: =(Subcategories!N6-MIN(Subcategories!$N$3:$N$40)+1)/(MAX(Subcategories!$N$3:$N$40)-MIN(Subcategories!$N$3:$N$40)+1)*100 -> 42.724908 | O7: =(Subcategories!O6-MIN(Subcategories!$O$3:$O$40)+1)/(MAX(Subcategories!$O$3:$O$40)-MIN(Subcategories!$O$3:$O$40)+1)*100 -> 76.718066 | P7: =(Subcategories!P6-MIN(Subcategories!$P$3:$P$40)+1)/(MAX(Subcategories!$P$3:$P$40)-MIN(Subcategories!$P$3:$P$40)+1)*100 -> 61.936368
A8: =RawData!A7 -> Switzerland | B8: =(Subcategories!B7-MIN(Subcategories!$B$3:$B$40)+1)/(MAX(Subcategories!$B$3:$B$40)-MIN(Subcategories!$B$3:$B$40)+1)*100 -> 67.447044 | C8: =(Subcategories!C7-MIN(Subcategories!$C$3:$C$40)+1)/(MAX(Subcategories!$C$3:$C$40)-MIN(Subcategories!$C$3:$C$40)+1)*100 -> 51.444029 | D8: =(Subcategories!D7-MIN(Subcategories!$D$3:$D$40)+1)/(MAX(Subcategories!$D$3:$D$40)-MIN(Subcategories!$D$3:$D$40)+1)*100 -> 67.148599 | E8: =(Subcategories!E7-MIN(Subcategories!$E$3:$E$40)+1)/(MAX(Subcategories!$E$3:$E$40)-MIN(Subcategories!$E$3:$E$40)+1)*100 -> 65.986689 | F8: =(Subcategories!F7-MIN(Subcategories!$F$3:$F$40)+1)/(MAX(Subcategories!$F$3:$F$40)-MIN(Subcategories!$F$3:$F$40)+1)*100 -> 100 | G8: =(Subcategories!G7-MIN(Subcategories!$G$3:$G$40)+1)/(MAX(Subcategories!$G$3:$G$40)-MIN(Subcategories!$G$3:$G$40)+1)*100 -> 82.383582 | H8: =(Subcategories!H7-MIN(Subcategories!$H$3:$H$40)+1)/(MAX(Subcategories!$H$3:$H$40)-MIN(Subcategories!$H$3:$H$40)+1)*100 -> 97.570593 | I8: =(Subcategories!I7-MIN(Subcategories!$I$3:$I$40)+1)/(MAX(Subcategories!$I$3:$I$40)-MIN(Subcategories!$I$3:$I$40)+1)*100 -> 57.638391 | J8: =(Subcategories!J7-MIN(Subcategories!$J$3:$J$40)+1)/(MAX(Subcategories!$J$3:$J$40)-MIN(Subcategories!$J$3:$J$40)+1)*100 -> 72.464859 | K8: =(Subcategories!K7-MIN(Subcategories!$K$3:$K$40)+1)/(MAX(Subcategories!$K$3:$K$40)-MIN(Subcategories!$K$3:$K$40)+1)*100 -> 27.84789 | L8: =(Subcategories!L7-MIN(Subcategories!$L$3:$L$40)+1)/(MAX(Subcategories!$L$3:$L$40)-MIN(Subcategories!$L$3:$L$40)+1)*100 -> 30.907258 | M8: =(Subcategories!M7-MIN(Subcategories!$M$3:$M$40)+1)/(MAX(Subcategories!$M$3:$M$40)-MIN(Subcategories!$M$3:$M$40)+1)*100 -> 100 | N8: =(Subcategories!N7-MIN(Subcategories!$N$3:$N$40)+1)/(MAX(Subcategories!$N$3:$N$40)-MIN(Subcategories!$N$3:$N$40)+1)*100 -> 47.835334 | O8: =(Subcategories!O7-MIN(Subcategories!$O$3:$O$40)+1)/(MAX(Subcategories!$O$3:$O$40)-MIN(Subcategories!$O$3:$O$40)+1)*100 -> 85.772152 | P8: =(Subcategories!P7-MIN(Subcategories!$P$3:$P$40)+1)/(MAX(Subcategories!$P$3:$P$40)-MIN(Subcategories!$P$3:$P$40)+1)*100 -> 89.209561
A9: =RawData!A8 -> Chile | B9: =(Subcategories!B8-MIN(Subcategories!$B$3:$B$40)+1)/(MAX(Subcategories!$B$3:$B$40)-MIN(Subcategories!$B$3:$B$40)+1)*100 -> 44.762151 | C9: =(Subcategories!C8-MIN(Subcategories!$C$3:$C$40)+1)/(MAX(Subcategories!$C$3:$C$40)-MIN(Subcategories!$C$3:$C$40)+1)*100 -> 23.817605 | D9: =(Subcategories!D8-MIN(Subcategories!$D$3:$D$40)+1)/(MAX(Subcategories!$D$3:$D$40)-MIN(Subcategories!$D$3:$D$40)+1)*100 -> 87.444553 | E9: =(Subcategories!E8-MIN(Subcategories!$E$3:$E$40)+1)/(MAX(Subcategories!$E$3:$E$40)-MIN(Subcategories!$E$3:$E$40)+1)*100 -> 55.156306 | F9: =(Subcategories!F8-MIN(Subcategories!$F$3:$F$40)+1)/(MAX(Subcategories!$F$3:$F$40)-MIN(Subcategories!$F$3:$F$40)+1)*100 -> 100 | G9: =(Subcategories!G8-MIN(Subcategories!$G$3:$G$40)+1)/(MAX(Subcategories!$G$3:$G$40)-MIN(Subcategories!$G$3:$G$40)+1)*100 -> 45.083659 | H9: =(Subcategories!H8-MIN(Subcategories!$H$3:$H$40)+1)/(MAX(Subcategories!$H$3:$H$40)-MIN(Subcategories!$H$3:$H$40)+1)*100 -> 53.436369 | I9: =(Subcategories!I8-MIN(Subcategories!$I$3:$I$40)+1)/(MAX(Subcategories!$I$3:$I$40)-MIN(Subcategories!$I$3:$I$40)+1)*100 -> 82.334178 | J9: =(Subcategories!J8-MIN(Subcategories!$J$3:$J$40)+1)/(MAX(Subcategories!$J$3:$J$40)-MIN(Subcategories!$J$3:$J$40)+1)*100 -> 74.371479 | K9: =(Subcategories!K8-MIN(Subcategories!$K$3:$K$40)+1)/(MAX(Subcategories!$K$3:$K$40)-MIN(Subcategories!$K$3:$K$40)+1)*100 -> 70.441821 | L9: =(Subcategories!L8-MIN(Subcategories!$L$3:$L$40)+1)/(MAX(Subcategories!$L$3:$L$40)-MIN(Subcategories!$L$3:$L$40)+1)*100 -> 84.729899 | M9: =(Subcategories!M8-MIN(Subcategories!$M$3:$M$40)+1)/(MAX(Subcategories!$M$3:$M$40)-MIN(Subcategories!$M$3:$M$40)+1)*100 -> 26.778906 | N9: =(Subcategories!N8-MIN(Subcategories!$N$3:$N$40)+1)/(MAX(Subcategories!$N$3:$N$40)-MIN(Subcategories!$N$3:$N$40)+1)*100 -> 23.817794 | O9: =(Subcategories!O8-MIN(Subcategories!$O$3:$O$40)+1)/(MAX(Subcategories!$O$3:$O$40)-MIN(Subcategories!$O$3:$O$40)+1)*100 -> 38.561564 | P9: =(Subcategories!P8-MIN(Subcategories!$P$3:$P$40)+1)/(MAX(Subcategories!$P$3:$P$40)-MIN(Subcategories!$P$3:$P$40)+1)*100 -> 73.270783
A10: =RawData!A9 -> Colombia | B10: =(Subcategories!B9-MIN(Subcategories!$B$3:$B$40)+1)/(MAX(Subcategories!$B$3:$B$40)-MIN(Subcategories!$B$3:$B$40)+1)*100 -> 20.211996 | C10: =(Subcategories!C9-MIN(Subcategories!$C$3:$C$40)+1)/(MAX(Subcategories!$C$3:$C$40)-MIN(Subcategories!$C$3:$C$40)+1)*100 -> 36.784116 | D10: =(Subcategories!D9-MIN(Subcategories!$D$3:$D$40)+1)/(MAX(Subcategories!$D$3:$D$40)-MIN(Subcategories!$D$3:$D$40)+1)*100 -> 75.674028 | E10: =(Subcategories!E9-MIN(Subcategories!$E$3:$E$40)+1)/(MAX(Subcategories!$E$3:$E$40)-MIN(Subcategories!$E$3:$E$40)+1)*100 -> 70.699591 | F10: =(Subcategories!F9-MIN(Subcategories!$F$3:$F$40)+1)/(MAX(Subcategories!$F$3:$F$40)-MIN(Subcategories!$F$3:$F$40)+1)*100 -> 86.65124 | G10: =(Subcategories!G9-MIN(Subcategories!$G$3:$G$40)+1)/(MAX(Subcategories!$G$3:$G$40)-MIN(Subcategories!$G$3:$G$40)+1)*100 -> 71.282633 | H10: =(Subcategories!H9-MIN(Subcategories!$H$3:$H$40)+1)/(MAX(Subcategories!$H$3:$H$40)-MIN(Subcategories!$H$3:$H$40)+1)*100 -> 53.436369 | I10: =(Subcategories!I9-MIN(Subcategories!$I$3:$I$40)+1)/(MAX(Subcategories!$I$3:$I$40)-MIN(Subcategories!$I$3:$I$40)+1)*100 -> 54.272754 | J10: =(Subcategories!J9-MIN(Subcategories!$J$3:$J$40)+1)/(MAX(Subcategories!$J$3:$J$40)-MIN(Subcategories!$J$3:$J$40)+1)*100 -> 74.386376 | K10: =(Subcategories!K9-MIN(Subcategories!$K$3:$K$40)+1)/(MAX(Subcategories!$K$3:$K$40)-MIN(Subcategories!$K$3:$K$40)+1)*100 -> 27.84789 | L10: =(Subcategories!L9-MIN(Subcategories!$L$3:$L$40)+1)/(MAX(Subcategories!$L$3:$L$40)-MIN(Subcategories!$L$3:$L$40)+1)*100 -> 46.177359 | M10: =(Subcategories!M9-MIN(Subcategories!$M$3:$M$40)+1)/(MAX(Subcategories!$M$3:$M$40)-MIN(Subcategories!$M$3:$M$40)+1)*100 -> 44.395042 | N10: =(Subcategories!N9-MIN(Subcategories!$N$3:$N$40)+1)/(MAX(Subcategories!$N$3:$N$40)-MIN(Subcategories!$N$3:$N$40)+1)*100 -> 54.179926 | O10: =(Subcategories!O9-MIN(Subcategories!$O$3:$O$40)+1)/(MAX(Subcategories!$O$3:$O$40)-MIN(Subcategories!$O$3:$O$40)+1)*100 -> 23.686996 | P10: =(Subcategories!P9-MIN(Subcategories!$P$3:$P$40)+1)/(MAX(Subcategories!$P$3:$P$40)-MIN(Subcategories!$P$3:$P$40)+1)*100 -> 64.628388
A11: =RawData!A10 -> Costa Rica | B11: =(Subcategories!B10-MIN(Subcategories!$B$3:$B$40)+1)/(MAX(Subcategories!$B$3:$B$40)-MIN(Subcategories!$B$3:$B$40)+1)*100 -> 35.555843 | C11: =(Subcategories!C10-MIN(Subcategories!$C$3:$C$40)+1)/(MAX(Subcategories!$C$3:$C$40)-MIN(Subcategories!$C$3:$C$40)+1)*100 -> 36.535365 | D11: =(Subcategories!D10-MIN(Subcategories!$D$3:$D$40)+1)/(MAX(Subcategories!$D$3:$D$40)-MIN(Subcategories!$D$3:$D$40)+1)*100 -> 72.228701 | E11: =(Subcategories!E10-MIN(Subcategories!$E$3:$E$40)+1)/(MAX(Subcategories!$E$3:$E$40)-MIN(Subcategories!$E$3:$E$40)+1)*100 -> 83.29674 | F11: =(Subcategories!F10-MIN(Subcategories!$F$3:$F$40)+1)/(MAX(Subcategories!$F$3:$F$40)-MIN(Subcategories!$F$3:$F$40)+1)*100 -> 33.879233 | G11: =(Subcategories!G10-MIN(Subcategories!$G$3:$G$40)+1)/(MAX(Subcategories!$G$3:$G$40)-MIN(Subcategories!$G$3:$G$40)+1)*100 -> 76.417117 | H11: =(Subcategories!H10-MIN(Subcategories!$H$3:$H$40)+1)/(MAX(Subcategories!$H$3:$H$40)-MIN(Subcategories!$H$3:$H$40)+1)*100 -> 77.730438 | I11: =(Subcategories!I10-MIN(Subcategories!$I$3:$I$40)+1)/(MAX(Subcategories!$I$3:$I$40)-MIN(Subcategories!$I$3:$I$40)+1)*100 -> 65.621514 | J11: =(Subcategories!J10-MIN(Subcategories!$J$3:$J$40)+1)/(MAX(Subcategories!$J$3:$J$40)-MIN(Subcategories!$J$3:$J$40)+1)*100 -> 74.379047 | K11: =(Subcategories!K10-MIN(Subcategories!$K$3:$K$40)+1)/(MAX(Subcategories!$K$3:$K$40)-MIN(Subcategories!$K$3:$K$40)+1)*100 -> 100 | L11: =(Subcategories!L10-MIN(Subcategories!$L$3:$L$40)+1)/(MAX(Subcategories!$L$3:$L$40)-MIN(Subcategories!$L$3:$L$40)+1)*100 -> 48.221925 | M11: =(Subcategories!M10-MIN(Subcategories!$M$3:$M$40)+1)/(MAX(Subcategories!$M$3:$M$40)-MIN(Subcategories!$M$3:$M$40)+1)*100 -> 100 | N11: =(Subcategories!N10-MIN(Subcategories!$N$3:$N$40)+1)/(MAX(Subcategories!$N$3:$N$40)-MIN(Subcategories!$N$3:$N$40)+1)*100 -> 57.629098 | O11: =(Subcategories!O10-MIN(Subcategories!$O$3:$O$40)+1)/(MAX(Subcategories!$O$3:$O$40)-MIN(Subcategories!$O$3:$O$40)+1)*100 -> 17.219792 | P11: =(Subcategories!P10-MIN(Subcategories!$P$3:$P$40)+1)/(MAX(Subcategories!$P$3:$P$40)-MIN(Subcategories!$P$3:$P$40)+1)*100 -> 81.111142
A12: =RawData!A11 -> Czech Republic | B12: =(Subcategories!B11-MIN(Subcategories!$B$3:$B$40)+1)/(MAX(Subcategories!$B$3:$B$40)-MIN(Subcategories!$B$3:$B$40)+1)*100 -> 63.174767 | C12: =(Subcategories!C11-MIN(Subcategories!$C$3:$C$40)+1)/(MAX(Subcategories!$C$3:$C$40)-MIN(Subcategories!$C$3:$C$40)+1)*100 -> 45.802073 | D12: =(Subcategories!D11-MIN(Subcategories!$D$3:$D$40)+1)/(MAX(Subcategories!$D$3:$D$40)-MIN(Subcategories!$D$3:$D$40)+1)*100 -> 87.965619 | E12: =(Subcategories!E11-MIN(Subcategories!$E$3:$E$40)+1)/(MAX(Subcategories!$E$3:$E$40)-MIN(Subcategories!$E$3:$E$40)+1)*100 -> 85.094356 | F12: =(Subcategories!F11-MIN(Subcategories!$F$3:$F$40)+1)/(MAX(Subcategories!$F$3:$F$40)-MIN(Subcategories!$F$3:$F$40)+1)*100 -> 100 | G12: =(Subcategories!G11-MIN(Subcategories!$G$3:$G$40)+1)/(MAX(Subcategories!$G$3:$G$40)-MIN(Subcategories!$G$3:$G$40)+1)*100 -> 61.101188 | H12: =(Subcategories!H11-MIN(Subcategories!$H$3:$H$40)+1)/(MAX(Subcategories!$H$3:$H$40)-MIN(Subcategories!$H$3:$H$40)+1)*100 -> 45.338347 | I12: =(Subcategories!I11-MIN(Subcategories!$I$3:$I$40)+1)/(MAX(Subcategories!$I$3:$I$40)-MIN(Subcategories!$I$3:$I$40)+1)*100 -> 36.80204 | J12: =(Subcategories!J11-MIN(Subcategories!$J$3:$J$40)+1)/(MAX(Subcategories!$J$3:$J$40)-MIN(Subcategories!$J$3:$J$40)+1)*100 -> 74.302432 | K12: =(Subcategories!K11-MIN(Subcategories!$K$3:$K$40)+1)/(MAX(Subcategories!$K$3:$K$40)-MIN(Subcategories!$K$3:$K$40)+1)*100 -> 70.441821 | L12: =(Subcategories!L11-MIN(Subcategories!$L$3:$L$40)+1)/(MAX(Subcategories!$L$3:$L$40)-MIN(Subcategories!$L$3:$L$40)+1)*100 -> 100 | M12: =(Subcategories!M11-MIN(Subcategories!$M$3:$M$40)+1)/(MAX(Subcategories!$M$3:$M$40)-MIN(Subcategories!$M$3:$M$40)+1)*100 -> 82.383864 | N12: =(Subcategories!N11-MIN(Subcategories!$N$3:$N$40)+1)/(MAX(Subcategories!$N$3:$N$40)-MIN(Subcategories!$N$3:$N$40)+1)*100 -> 65.634945 | O12: =(Subcategories!O11-MIN(Subcategories!$O$3:$O$40)+1)/(MAX(Subcategories!$O$3:$O$40)-MIN(Subcategories!$O$3:$O$40)+1)*100 -> 78.011507 | P12: =(Subcategories!P11-MIN(Subcategories!$P$3:$P$40)+1)/(MAX(Subcategories!$P$3:$P$40)-MIN(Subcategories!$P$3:$P$40)+1)*100 -> 43.849545
A13: =RawData!A12 -> Germany | B13: =(Subcategories!B12-MIN(Subcategories!$B$3:$B$40)+1)/(MAX(Subcategories!$B$3:$B$40)-MIN(Subcategories!$B$3:$B$40)+1)*100 -> 35.376436 | C13: =(Subcategories!C12-MIN(Subcategories!$C$3:$C$40)+1)/(MAX(Subcategories!$C$3:$C$40)-MIN(Subcategories!$C$3:$C$40)+1)*100 -> 54.319323 | D13: =(Subcategories!D12-MIN(Subcategories!$D$3:$D$40)+1)/(MAX(Subcategories!$D$3:$D$40)-MIN(Subcategories!$D$3:$D$40)+1)*100 -> 70.13456 | E13: =(Subcategories!E12-MIN(Subcategories!$E$3:$E$40)+1)/(MAX(Subcategories!$E$3:$E$40)-MIN(Subcategories!$E$3:$E$40)+1)*100 -> 69.038831 | F13: =(Subcategories!F12-MIN(Subcategories!$F$3:$F$40)+1)/(MAX(Subcategories!$F$3:$F$40)-MIN(Subcategories!$F$3:$F$40)+1)*100 -> 49.154284 | G13: =(Subcategories!G12-MIN(Subcategories!$G$3:$G$40)+1)/(MAX(Subcategories!$G$3:$G$40)-MIN(Subcategories!$G$3:$G$40)+1)*100 -> 54.63978 | H13: =(Subcategories!H12-MIN(Subcategories!$H$3:$H$40)+1)/(MAX(Subcategories!$H$3:$H$40)-MIN(Subcategories!$H$3:$H$40)+1)*100 -> 53.436369 | I13: =(Subcategories!I12-MIN(Subcategories!$I$3:$I$40)+1)/(MAX(Subcategories!$I$3:$I$40)-MIN(Subcategories!$I$3:$I$40)+1)*100 -> 60.160452 | J13: =(Subcategories!J12-MIN(Subcategories!$J$3:$J$40)+1)/(MAX(Subcategories!$J$3:$J$40)-MIN(Subcategories!$J$3:$J$40)+1)*100 -> 69.68646 | K13: =(Subcategories!K12-MIN(Subcategories!$K$3:$K$40)+1)/(MAX(Subcategories!$K$3:$K$40)-MIN(Subcategories!$K$3:$K$40)+1)*100 -> 70.441821 | L13: =(Subcategories!L12-MIN(Subcategories!$L$3:$L$40)+1)/(MAX(Subcategories!$L$3:$L$40)-MIN(Subcategories!$L$3:$L$40)+1)*100 -> 79.090553 | M13: =(Subcategories!M12-MIN(Subcategories!$M$3:$M$40)+1)/(MAX(Subcategories!$M$3:$M$40)-MIN(Subcategories!$M$3:$M$40)+1)*100 -> 97.219752 | N13: =(Subcategories!N12-MIN(Subcategories!$N$3:$N$40)+1)/(MAX(Subcategories!$N$3:$N$40)-MIN(Subcategories!$N$3:$N$40)+1)*100 -> 66.306268 | O13: =(Subcategories!O12-MIN(Subcategories!$O$3:$O$40)+1)/(MAX(Subcategories!$O$3:$O$40)-MIN(Subcategories!$O$3:$O$40)+1)*100 -> 76.071346 | P13: =(Subcategories!P12-MIN(Subcategories!$P$3:$P$40)+1)/(MAX(Subcategories!$P$3:$P$40)-MIN(Subcategories!$P$3:$P$40)+1)*100 -> 43.849545
A14: =RawData!A13 -> Denmark | B14: =(Subcategories!B13-MIN(Subcategories!$B$3:$B$40)+1)/(MAX(Subcategories!$B$3:$B$40)-MIN(Subcategories!$B$3:$B$40)+1)*100 -> 60.105998 | C14: =(Subcategories!C13-MIN(Subcategories!$C$3:$C$40)+1)/(MAX(Subcategories!$C$3:$C$40)-MIN(Subcategories!$C$3:$C$40)+1)*100 -> 40.156257 | D14: =(Subcategories!D13-MIN(Subcategories!$D$3:$D$40)+1)/(MAX(Subcategories!$D$3:$D$40)-MIN(Subcategories!$D$3:$D$40)+1)*100 -> 81.08183 | E14: =(Subcategories!E13-MIN(Subcategories!$E$3:$E$40)+1)/(MAX(Subcategories!$E$3:$E$40)-MIN(Subcategories!$E$3:$E$40)+1)*100 -> 55.631634 | F14: =(Subcategories!F13-MIN(Subcategories!$F$3:$F$40)+1)/(MAX(Subcategories!$F$3:$F$40)-MIN(Subcategories!$F$3:$F$40)+1)*100 -> 100 | G14: =(Subcategories!G13-MIN(Subcategories!$G$3:$G$40)+1)/(MAX(Subcategories!$G$3:$G$40)-MIN(Subcategories!$G$3:$G$40)+1)*100 -> 24.725856 | H14: =(Subcategories!H13-MIN(Subcategories!$H$3:$H$40)+1)/(MAX(Subcategories!$H$3:$H$40)-MIN(Subcategories!$H$3:$H$40)+1)*100 -> 29.142301 | I14: =(Subcategories!I13-MIN(Subcategories!$I$3:$I$40)+1)/(MAX(Subcategories!$I$3:$I$40)-MIN(Subcategories!$I$3:$I$40)+1)*100 -> 75.846541 | J14: =(Subcategories!J13-MIN(Subcategories!$J$3:$J$40)+1)/(MAX(Subcategories!$J$3:$J$40)-MIN(Subcategories!$J$3:$J$40)+1)*100 -> 72.172971 | K14: =(Subcategories!K13-MIN(Subcategories!$K$3:$K$40)+1)/(MAX(Subcategories!$K$3:$K$40)-MIN(Subcategories!$K$3:$K$40)+1)*100 -> 70.441821 | L14: =(Subcategories!L13-MIN(Subcategories!$L$3:$L$40)+1)/(MAX(Subcategories!$L$3:$L$40)-MIN(Subcategories!$L$3:$L$40)+1)*100 -> 79.090553 | M14: =(Subcategories!M13-MIN(Subcategories!$M$3:$M$40)+1)/(MAX(Subcategories!$M$3:$M$40)-MIN(Subcategories!$M$3:$M$40)+1)*100 -> 82.383864 | N14: =(Subcategories!N13-MIN(Subcategories!$N$3:$N$40)+1)/(MAX(Subcategories!$N$3:$N$40)-MIN(Subcategories!$N$3:$N$40)+1)*100 -> 45.612236 | O14: =(Subcategories!O13-MIN(Subcategories!$O$3:$O$40)+1)/(MAX(Subcategories!$O$3:$O$40)-MIN(Subcategories!$O$3:$O$40)+1)*100 -> 64.430379 | P14: =(Subcategories!P13-MIN(Subcategories!$P$3:$P$40)+1)/(MAX(Subcategories!$P$3:$P$40)-MIN(Subcategories!$P$3:$P$40)+1)*100 -> 26.564757
A15: =RawData!A14 -> Estonia | B15: =(Subcategories!B14-MIN(Subcategories!$B$3:$B$40)+1)/(MAX(Subcategories!$B$3:$B$40)-MIN(Subcategories!$B$3:$B$40)+1)*100 -> 60.105998 | C15: =(Subcategories!C14-MIN(Subcategories!$C$3:$C$40)+1)/(MAX(Subcategories!$C$3:$C$40)-MIN(Subcategories!$C$3:$C$40)+1)*100 -> 100 | D15: =(Subcategories!D14-MIN(Subcategories!$D$3:$D$40)+1)/(MAX(Subcategories!$D$3:$D$40)-MIN(Subcategories!$D$3:$D$40)+1)*100 -> 94.891735 | E15: =(Subcategories!E14-MIN(Subcategories!$E$3:$E$40)+1)/(MAX(Subcategories!$E$3:$E$40)-MIN(Subcategories!$E$3:$E$40)+1)*100 -> 100 | F15: =(Subcategories!F14-MIN(Subcategories!$F$3:$F$40)+1)/(MAX(Subcategories!$F$3:$F$40)-MIN(Subcategories!$F$3:$F$40)+1)*100 -> 100 | G15: =(Subcategories!G14-MIN(Subcategories!$G$3:$G$40)+1)/(MAX(Subcategories!$G$3:$G$40)-MIN(Subcategories!$G$3:$G$40)+1)*100 -> 85.607413 | H15: =(Subcategories!H14-MIN(Subcategories!$H$3:$H$40)+1)/(MAX(Subcategories!$H$3:$H$40)-MIN(Subcategories!$H$3:$H$40)+1)*100 -> 33.191313 | I15: =(Subcategories!I14-MIN(Subcategories!$I$3:$I$40)+1)/(MAX(Subcategories!$I$3:$I$40)-MIN(Subcategories!$I$3:$I$40)+1)*100 -> 67.973572 | J15: =(Subcategories!J14-MIN(Subcategories!$J$3:$J$40)+1)/(MAX(Subcategories!$J$3:$J$40)-MIN(Subcategories!$J$3:$J$40)+1)*100 -> 98.493636 | K15: =(Subcategories!K14-MIN(Subcategories!$K$3:$K$40)+1)/(MAX(Subcategories!$K$3:$K$40)-MIN(Subcategories!$K$3:$K$40)+1)*100 -> 100 | L15: =(Subcategories!L14-MIN(Subcategories!$L$3:$L$40)+1)/(MAX(Subcategories!$L$3:$L$40)-MIN(Subcategories!$L$3:$L$40)+1)*100 -> 100 | M15: =(Subcategories!M14-MIN(Subcategories!$M$3:$M$40)+1)/(MAX(Subcategories!$M$3:$M$40)-MIN(Subcategories!$M$3:$M$40)+1)*100 -> 82.383864 | N15: =(Subcategories!N14-MIN(Subcategories!$N$3:$N$40)+1)/(MAX(Subcategories!$N$3:$N$40)-MIN(Subcategories!$N$3:$N$40)+1)*100 -> 91.994154 | O15: =(Subcategories!O14-MIN(Subcategories!$O$3:$O$40)+1)/(MAX(Subcategories!$O$3:$O$40)-MIN(Subcategories!$O$3:$O$40)+1)*100 -> 55.376294 | P15: =(Subcategories!P14-MIN(Subcategories!$P$3:$P$40)+1)/(MAX(Subcategories!$P$3:$P$40)-MIN(Subcategories!$P$3:$P$40)+1)*100 -> 63.826353
... A41: =RawData!A40 -> United States | B41: =(Subcategories!B40-MIN(Subcategories!$B$3:$B$40)+1)/(MAX(Subcategories!$B$3:$B$40)-MIN(Subcategories!$B$3:$B$40)+1)*100 -> 49.151369 | C41: =(Subcategories!C40-MIN(Subcategories!$C$3:$C$40)+1)/(MAX(Subcategories!$C$3:$C$40)-MIN(Subcategories!$C$3:$C$40)+1)*100 -> 66.201727 | D41: =(Subcategories!D40-MIN(Subcategories!$D$3:$D$40)+1)/(MAX(Subcategories!$D$3:$D$40)-MIN(Subcategories!$D$3:$D$40)+1)*100 -> 82.511134 | E41: =(Subcategories!E40-MIN(Subcategories!$E$3:$E$40)+1)/(MAX(Subcategories!$E$3:$E$40)-MIN(Subcategories!$E$3:$E$40)+1)*100 -> 57.328176 | F41: =(Subcategories!F40-MIN(Subcategories!$F$3:$F$40)+1)/(MAX(Subcategories!$F$3:$F$40)-MIN(Subcategories!$F$3:$F$40)+1)*100 -> 100 | G41: =(Subcategories!G40-MIN(Subcategories!$G$3:$G$40)+1)/(MAX(Subcategories!$G$3:$G$40)-MIN(Subcategories!$G$3:$G$40)+1)*100 -> 50.071878 | H41: =(Subcategories!H40-MIN(Subcategories!$H$3:$H$40)+1)/(MAX(Subcategories!$H$3:$H$40)-MIN(Subcategories!$H$3:$H$40)+1)*100 -> 100 | I41: =(Subcategories!I40-MIN(Subcategories!$I$3:$I$40)+1)/(MAX(Subcategories!$I$3:$I$40)-MIN(Subcategories!$I$3:$I$40)+1)*100 -> 51.688248 | J41: =(Subcategories!J40-MIN(Subcategories!$J$3:$J$40)+1)/(MAX(Subcategories!$J$3:$J$40)-MIN(Subcategories!$J$3:$J$40)+1)*100 -> 37.822185 | K41: =(Subcategories!K40-MIN(Subcategories!$K$3:$K$40)+1)/(MAX(Subcategories!$K$3:$K$40)-MIN(Subcategories!$K$3:$K$40)+1)*100 -> 70.441821 | L41: =(Subcategories!L40-MIN(Subcategories!$L$3:$L$40)+1)/(MAX(Subcategories!$L$3:$L$40)-MIN(Subcategories!$L$3:$L$40)+1)*100 -> 63.820453 | M41: =(Subcategories!M40-MIN(Subcategories!$M$3:$M$40)+1)/(MAX(Subcategories!$M$3:$M$40)-MIN(Subcategories!$M$3:$M$40)+1)*100 -> 77.330754 | N41: =(Subcategories!N40-MIN(Subcategories!$N$3:$N$40)+1)/(MAX(Subcategories!$N$3:$N$40)-MIN(Subcategories!$N$3:$N$40)+1)*100 -> 31.26989 | O41: =(Subcategories!O40-MIN(Subcategories!$O$3:$O$40)+1)/(MAX(Subcategories!$O$3:$O$40)-MIN(Subcategories!$O$3:$O$40)+1)*100 -> 56.023014 | P41: =(Subcategories!P40-MIN(Subcategories!$P$3:$P$40)+1)/(MAX(Subcategories!$P$3:$P$40)-MIN(Subcategories!$P$3:$P$40)+1)*100 -> 43.849545

Sheet Categories
A1: Categories — RAW (pre-rescale) Equal-Weighted Averages (LIVE)
A2: Uses the RAW (pre-score2) Subcategories sheet, not SubcategoriesScored — validated against the Tax Foundation's own categories_score.csv.
A3: country | B3: corporate | C3: consumption | D3: property | E3: income | F3: cross_border
A4: =RawData!A3 -> Austria | B4: =(Subcategories!B3+Subcategories!C3+Subcategories!D3)/3 -> 0.045083822 | C4: =(Subcategories!H3+Subcategories!I3)/2 -> -0.02833021 | D4: =(Subcategories!J3+Subcategories!K3+Subcategories!L3)/3 -> 0.046546823 | E4: =(Subcategories!G3+Subcategories!E3+Subcategories!F3)/3 -> -0.21358477 | F4: =(Subcategories!M3+Subcategories!N3+Subcategories!O3+Subcategories!P3)/4 -> 0.099306712
A5: =RawData!A4 -> Australia | B5: =(Subcategories!B4+Subcategories!C4+Subcategories!D4)/3 -> -0.29991868 | C5: =(Subcategories!H4+Subcategories!I4)/2 -> 0.71596989 | D5: =(Subcategories!J4+Subcategories!K4+Subcategories!L4)/3 -> 0.84815365 | E5: =(Subcategories!G4+Subcategories!E4+Subcategories!F4)/3 -> 0.082107278 | F5: =(Subcategories!M4+Subcategories!N4+Subcategories!O4+Subcategories!P4)/4 -> -0.30070314
A6: =RawData!A5 -> Belgium | B6: =(Subcategories!B5+Subcategories!C5+Subcategories!D5)/3 -> 0.079148653 | C6: =(Subcategories!H5+Subcategories!I5)/2 -> -0.29510002 | D6: =(Subcategories!J5+Subcategories!K5+Subcategories!L5)/3 -> -0.53477785 | E6: =(Subcategories!G5+Subcategories!E5+Subcategories!F5)/3 -> 0.16833288 | F6: =(Subcategories!M5+Subcategories!N5+Subcategories!O5+Subcategories!P5)/4 -> -0.16761596
A7: =RawData!A6 -> Canada | B7: =(Subcategories!B6+Subcategories!C6+Subcategories!D6)/3 -> -0.086852163 | C7: =(Subcategories!H6+Subcategories!I6)/2 -> 0.77392818 | D7: =(Subcategories!J6+Subcategories!K6+Subcategories!L6)/3 -> -0.07806677 | E7: =(Subcategories!G6+Subcategories!E6+Subcategories!F6)/3 -> -0.2199797 | F7: =(Subcategories!M6+Subcategories!N6+Subcategories!O6+Subcategories!P6)/4 -> 0.024614406
A8: =RawData!A7 -> Switzerland | B8: =(Subcategories!B7+Subcategories!C7+Subcategories!D7)/3 -> 0.22390278 | C8: =(Subcategories!H7+Subcategories!I7)/2 -> 1.0976891 | D8: =(Subcategories!J7+Subcategories!K7+Subcategories!L7)/3 -> -0.77773412 | E8: =(Subcategories!G7+Subcategories!E7+Subcategories!F7)/3 -> 0.45743793 | F8: =(Subcategories!M7+Subcategories!N7+Subcategories!O7+Subcategories!P7)/4 -> 0.7366469
A9: =RawData!A8 -> Chile | B9: =(Subcategories!B8+Subcategories!C8+Subcategories!D8)/3 -> -0.37917862 | C9: =(Subcategories!H8+Subcategories!I8)/2 -> 0.55887151 | D9: =(Subcategories!J8+Subcategories!K8+Subcategories!L8)/3 -> 0.34078187 | E9: =(Subcategories!G8+Subcategories!E8+Subcategories!F8)/3 -> -0.17730859 | F9: =(Subcategories!M8+Subcategories!N8+Subcategories!O8+Subcategories!P8)/4 -> -1.0344313
A10: =RawData!A9 -> Colombia | B10: =(Subcategories!B9+Subcategories!C9+Subcategories!D9)/3 -> -0.82281117 | C10: =(Subcategories!H9+Subcategories!I9)/2 -> -0.020390359 | D10: =(Subcategories!J9+Subcategories!K9+Subcategories!L9)/3 -> -0.58462544 | E10: =(Subcategories!G9+Subcategories!E9+Subcategories!F9)/3 -> 0.20481159 | F10: =(Subcategories!M9+Subcategories!N9+Subcategories!O9+Subcategories!P9)/4 -> -0.84856545
A11: =RawData!A10 -> Costa Rica | B11: =(Subcategories!B10+Subcategories!C10+Subcategories!D10)/3 -> -0.56075619 | C11: =(Subcategories!H10+Subcategories!I10)/2 -> 0.79109115 | D11: =(Subcategories!J10+Subcategories!K10+Subcategories!L10)/3 -> 0.30096214 | E11: =(Subcategories!G10+Subcategories!E10+Subcategories!F10)/3 -> -0.15628295 | F11: =(Subcategories!M10+Subcategories!N10+Subcategories!O10+Subcategories!P10)/4 -> -0.23202357
A12: =RawData!A11 -> Czech Republic | B12: =(Subcategories!B11+Subcategories!C11+Subcategories!D11)/3 -> 0.30108191 | C12: =(Subcategories!H11+Subcategories!I11)/2 -> -0.57343639 | D12: =(Subcategories!J11+Subcategories!K11+Subcategories!L11)/3 -> 0.50444791 | E12: =(Subcategories!G11+Subcategories!E11+Subcategories!F11)/3 -> 0.34052248 | F12: =(Subcategories!M11+Subcategories!N11+Subcategories!O11+Subcategories!P11)/4 -> 0.21946691
A13: =RawData!A12 -> Germany | B13: =(Subcategories!B12+Subcategories!C12+Subcategories!D12)/3 -> -0.33969979 | C13: =(Subcategories!H12+Subcategories!I12)/2 -> 0.10114727 | D13: =(Subcategories!J12+Subcategories!K12+Subcategories!L12)/3 -> 0.21066519 | E13: =(Subcategories!G12+Subcategories!E12+Subcategories!F12)/3 -> -0.44284182 | F13: =(Subcategories!M12+Subcategories!N12+Subcategories!O12+Subcategories!P12)/4 -> 0.33684923
A14: =RawData!A13 -> Denmark | B14: =(Subcategories!B13+Subcategories!C13+Subcategories!D13)/3 -> 0.081219807 | C14: =(Subcategories!H13+Subcategories!I13)/2 -> -0.15226358 | D14: =(Subcategories!J13+Subcategories!K13+Subcategories!L13)/3 -> 0.24744343 | E14: =(Subcategories!G13+Subcategories!E13+Subcategories!F13)/3 -> -0.46180452 | F14: =(Subcategories!M13+Subcategories!N13+Subcategories!O13+Subcategories!P13)/4 -> -0.35053831
A15: =RawData!A14 -> Estonia | B15: =(Subcategories!B14+Subcategories!C14+Subcategories!D14)/3 -> 1.0787516 | C15: =(Subcategories!H14+Subcategories!I14)/2 -> -0.21858025 | D15: =(Subcategories!J14+Subcategories!K14+Subcategories!L14)/3 -> 1.2160676 | E15: =(Subcategories!G14+Subcategories!E14+Subcategories!F14)/3 -> 0.83310768 | F15: =(Subcategories!M14+Subcategories!N14+Subcategories!O14+Subcategories!P14)/4 -> 0.35552149
... A41: =RawData!A40 -> United States | B41: =(Subcategories!B40+Subcategories!C40+Subcategories!D40)/3 -> 0.24421582 | C41: =(Subcategories!H40+Subcategories!I40)/2 -> 1.0325838 | D41: =(Subcategories!J40+Subcategories!K40+Subcategories!L40)/3 -> -0.42532985 | E41: =(Subcategories!G40+Subcategories!E40+Subcategories!F40)/3 -> -0.085405243 | F41: =(Subcategories!M40+Subcategories!N40+Subcategories!O40+Subcategories!P40)/4 -> -0.50764807

Sheet CategoriesScored
A1: Categories — Rescaled to 0-100 (LIVE)
A2: country | B2: corporate | C2: consumption | D2: property | E2: income | F2: cross_border
A3: =RawData!A3 -> Austria | B3: =(Categories!B4-MIN(Categories!$B$4:$B$41)+1)/(MAX(Categories!$B$4:$B$41)-MIN(Categories!$B$4:$B$41)+1)*100 -> 65.327665 | C3: =(Categories!C4-MIN(Categories!$C$4:$C$41)+1)/(MAX(Categories!$C$4:$C$41)-MIN(Categories!$C$4:$C$41)+1)*100 -> 58.838918 | D3: =(Categories!D4-MIN(Categories!$D$4:$D$41)+1)/(MAX(Categories!$D$4:$D$41)-MIN(Categories!$D$4:$D$41)+1)*100 -> 62.660507 | E3: =(Categories!E4-MIN(Categories!$E$4:$E$41)+1)/(MAX(Categories!$E$4:$E$41)-MIN(Categories!$E$4:$E$41)+1)*100 -> 58.319017 | F3: =(Categories!F4-MIN(Categories!$F$4:$F$41)+1)/(MAX(Categories!$F$4:$F$41)-MIN(Categories!$F$4:$F$41)+1)*100 -> 77.000281
A4: =RawData!A4 -> Australia | B4: =(Categories!B5-MIN(Categories!$B$4:$B$41)+1)/(MAX(Categories!$B$4:$B$41)-MIN(Categories!$B$4:$B$41)+1)*100 -> 55.482643 | C4: =(Categories!C5-MIN(Categories!$C$4:$C$41)+1)/(MAX(Categories!$C$4:$C$41)-MIN(Categories!$C$4:$C$41)+1)*100 -> 81.758543 | D4: =(Categories!D5-MIN(Categories!$D$4:$D$41)+1)/(MAX(Categories!$D$4:$D$41)-MIN(Categories!$D$4:$D$41)+1)*100 -> 88.253548 | E4: =(Categories!E5-MIN(Categories!$E$4:$E$41)+1)/(MAX(Categories!$E$4:$E$41)-MIN(Categories!$E$4:$E$41)+1)*100 -> 69.935712 | F4: =(Categories!F5-MIN(Categories!$F$4:$F$41)+1)/(MAX(Categories!$F$4:$F$41)-MIN(Categories!$F$4:$F$41)+1)*100 -> 62.565111
A5: =RawData!A5 -> Belgium | B5: =(Categories!B6-MIN(Categories!$B$4:$B$41)+1)/(MAX(Categories!$B$4:$B$41)-MIN(Categories!$B$4:$B$41)+1)*100 -> 66.299742 | C5: =(Categories!C6-MIN(Categories!$C$4:$C$41)+1)/(MAX(Categories!$C$4:$C$41)-MIN(Categories!$C$4:$C$41)+1)*100 -> 50.624135 | D5: =(Categories!D6-MIN(Categories!$D$4:$D$41)+1)/(MAX(Categories!$D$4:$D$41)-MIN(Categories!$D$4:$D$41)+1)*100 -> 44.100453 | E5: =(Categories!E6-MIN(Categories!$E$4:$E$41)+1)/(MAX(Categories!$E$4:$E$41)-MIN(Categories!$E$4:$E$41)+1)*100 -> 73.323211 | F5: =(Categories!F6-MIN(Categories!$F$4:$F$41)+1)/(MAX(Categories!$F$4:$F$41)-MIN(Categories!$F$4:$F$41)+1)*100 -> 67.367833
A6: =RawData!A6 -> Canada | B6: =(Categories!B7-MIN(Categories!$B$4:$B$41)+1)/(MAX(Categories!$B$4:$B$41)-MIN(Categories!$B$4:$B$41)+1)*100 -> 61.562728 | C6: =(Categories!C7-MIN(Categories!$C$4:$C$41)+1)/(MAX(Categories!$C$4:$C$41)-MIN(Categories!$C$4:$C$41)+1)*100 -> 83.543284 | D6: =(Categories!D7-MIN(Categories!$D$4:$D$41)+1)/(MAX(Categories!$D$4:$D$41)-MIN(Categories!$D$4:$D$41)+1)*100 -> 58.681947 | E6: =(Categories!E7-MIN(Categories!$E$4:$E$41)+1)/(MAX(Categories!$E$4:$E$41)-MIN(Categories!$E$4:$E$41)+1)*100 -> 58.067783 | F6: =(Categories!F7-MIN(Categories!$F$4:$F$41)+1)/(MAX(Categories!$F$4:$F$41)-MIN(Categories!$F$4:$F$41)+1)*100 -> 74.304857
A7: =RawData!A7 -> Switzerland | B7: =(Categories!B8-MIN(Categories!$B$4:$B$41)+1)/(MAX(Categories!$B$4:$B$41)-MIN(Categories!$B$4:$B$41)+1)*100 -> 70.430459 | C7: =(Categories!C8-MIN(Categories!$C$4:$C$41)+1)/(MAX(Categories!$C$4:$C$41)-MIN(Categories!$C$4:$C$41)+1)*100 -> 93.513025 | D7: =(Categories!D8-MIN(Categories!$D$4:$D$41)+1)/(MAX(Categories!$D$4:$D$41)-MIN(Categories!$D$4:$D$41)+1)*100 -> 36.343546 | E7: =(Categories!E8-MIN(Categories!$E$4:$E$41)+1)/(MAX(Categories!$E$4:$E$41)-MIN(Categories!$E$4:$E$41)+1)*100 -> 84.681127 | F7: =(Categories!F8-MIN(Categories!$F$4:$F$41)+1)/(MAX(Categories!$F$4:$F$41)-MIN(Categories!$F$4:$F$41)+1)*100 -> 100
A8: =RawData!A8 -> Chile | B8: =(Categories!B9-MIN(Categories!$B$4:$B$41)+1)/(MAX(Categories!$B$4:$B$41)-MIN(Categories!$B$4:$B$41)+1)*100 -> 53.220875 | C8: =(Categories!C9-MIN(Categories!$C$4:$C$41)+1)/(MAX(Categories!$C$4:$C$41)-MIN(Categories!$C$4:$C$41)+1)*100 -> 76.92093 | D8: =(Categories!D9-MIN(Categories!$D$4:$D$41)+1)/(MAX(Categories!$D$4:$D$41)-MIN(Categories!$D$4:$D$41)+1)*100 -> 72.054601 | E8: =(Categories!E9-MIN(Categories!$E$4:$E$41)+1)/(MAX(Categories!$E$4:$E$41)-MIN(Categories!$E$4:$E$41)+1)*100 -> 59.74418 | F8: =(Categories!F9-MIN(Categories!$F$4:$F$41)+1)/(MAX(Categories!$F$4:$F$41)-MIN(Categories!$F$4:$F$41)+1)*100 -> 36.087037
A9: =RawData!A9 -> Colombia | B9: =(Categories!B10-MIN(Categories!$B$4:$B$41)+1)/(MAX(Categories!$B$4:$B$41)-MIN(Categories!$B$4:$B$41)+1)*100 -> 40.561338 | C9: =(Categories!C10-MIN(Categories!$C$4:$C$41)+1)/(MAX(Categories!$C$4:$C$41)-MIN(Categories!$C$4:$C$41)+1)*100 -> 59.083414 | D9: =(Categories!D10-MIN(Categories!$D$4:$D$41)+1)/(MAX(Categories!$D$4:$D$41)-MIN(Categories!$D$4:$D$41)+1)*100 -> 42.508961 | E9: =(Categories!E10-MIN(Categories!$E$4:$E$41)+1)/(MAX(Categories!$E$4:$E$41)-MIN(Categories!$E$4:$E$41)+1)*100 -> 74.756331 | F9: =(Categories!F10-MIN(Categories!$F$4:$F$41)+1)/(MAX(Categories!$F$4:$F$41)-MIN(Categories!$F$4:$F$41)+1)*100 -> 42.794384
A10: =RawData!A10 -> Costa Rica | B10: =(Categories!B11-MIN(Categories!$B$4:$B$41)+1)/(MAX(Categories!$B$4:$B$41)-MIN(Categories!$B$4:$B$41)+1)*100 -> 48.039362 | C10: =(Categories!C11-MIN(Categories!$C$4:$C$41)+1)/(MAX(Categories!$C$4:$C$41)-MIN(Categories!$C$4:$C$41)+1)*100 -> 84.071792 | D10: =(Categories!D11-MIN(Categories!$D$4:$D$41)+1)/(MAX(Categories!$D$4:$D$41)-MIN(Categories!$D$4:$D$41)+1)*100 -> 70.783269 | E10: =(Categories!E11-MIN(Categories!$E$4:$E$41)+1)/(MAX(Categories!$E$4:$E$41)-MIN(Categories!$E$4:$E$41)+1)*100 -> 60.570203 | F10: =(Categories!F11-MIN(Categories!$F$4:$F$41)+1)/(MAX(Categories!$F$4:$F$41)-MIN(Categories!$F$4:$F$41)+1)*100 -> 65.043553
A11: =RawData!A11 -> Czech Republic | B11: =(Categories!B12-MIN(Categories!$B$4:$B$41)+1)/(MAX(Categories!$B$4:$B$41)-MIN(Categories!$B$4:$B$41)+1)*100 -> 72.632849 | C11: =(Categories!C12-MIN(Categories!$C$4:$C$41)+1)/(MAX(Categories!$C$4:$C$41)-MIN(Categories!$C$4:$C$41)+1)*100 -> 42.053176 | D11: =(Categories!D12-MIN(Categories!$D$4:$D$41)+1)/(MAX(Categories!$D$4:$D$41)-MIN(Categories!$D$4:$D$41)+1)*100 -> 77.279995 | E11: =(Categories!E12-MIN(Categories!$E$4:$E$41)+1)/(MAX(Categories!$E$4:$E$41)-MIN(Categories!$E$4:$E$41)+1)*100 -> 80.087932 | F11: =(Categories!F12-MIN(Categories!$F$4:$F$41)+1)/(MAX(Categories!$F$4:$F$41)-MIN(Categories!$F$4:$F$41)+1)*100 -> 81.336507
A12: =RawData!A12 -> Germany | B12: =(Categories!B13-MIN(Categories!$B$4:$B$41)+1)/(MAX(Categories!$B$4:$B$41)-MIN(Categories!$B$4:$B$41)+1)*100 -> 54.347446 | C12: =(Categories!C13-MIN(Categories!$C$4:$C$41)+1)/(MAX(Categories!$C$4:$C$41)-MIN(Categories!$C$4:$C$41)+1)*100 -> 62.825987 | D12: =(Categories!D13-MIN(Categories!$D$4:$D$41)+1)/(MAX(Categories!$D$4:$D$41)-MIN(Categories!$D$4:$D$41)+1)*100 -> 67.900343 | E12: =(Categories!E13-MIN(Categories!$E$4:$E$41)+1)/(MAX(Categories!$E$4:$E$41)-MIN(Categories!$E$4:$E$41)+1)*100 -> 49.312318 | F12: =(Categories!F13-MIN(Categories!$F$4:$F$41)+1)/(MAX(Categories!$F$4:$F$41)-MIN(Categories!$F$4:$F$41)+1)*100 -> 85.572487
A13: =RawData!A13 -> Denmark | B13: =(Categories!B14-MIN(Categories!$B$4:$B$41)+1)/(MAX(Categories!$B$4:$B$41)-MIN(Categories!$B$4:$B$41)+1)*100 -> 66.358845 | C13: =(Categories!C14-MIN(Categories!$C$4:$C$41)+1)/(MAX(Categories!$C$4:$C$41)-MIN(Categories!$C$4:$C$41)+1)*100 -> 55.022573 | D13: =(Categories!D14-MIN(Categories!$D$4:$D$41)+1)/(MAX(Categories!$D$4:$D$41)-MIN(Categories!$D$4:$D$41)+1)*100 -> 69.074568 | E13: =(Categories!E14-MIN(Categories!$E$4:$E$41)+1)/(MAX(Categories!$E$4:$E$41)-MIN(Categories!$E$4:$E$41)+1)*100 -> 48.567341 | F13: =(Categories!F14-MIN(Categories!$F$4:$F$41)+1)/(MAX(Categories!$F$4:$F$41)-MIN(Categories!$F$4:$F$41)+1)*100 -> 60.766708
A14: =RawData!A14 -> Estonia | B14: =(Categories!B15-MIN(Categories!$B$4:$B$41)+1)/(MAX(Categories!$B$4:$B$41)-MIN(Categories!$B$4:$B$41)+1)*100 -> 94.824499 | C14: =(Categories!C15-MIN(Categories!$C$4:$C$41)+1)/(MAX(Categories!$C$4:$C$41)-MIN(Categories!$C$4:$C$41)+1)*100 -> 52.980449 | D14: =(Categories!D15-MIN(Categories!$D$4:$D$41)+1)/(MAX(Categories!$D$4:$D$41)-MIN(Categories!$D$4:$D$41)+1)*100 -> 100 | E14: =(Categories!E15-MIN(Categories!$E$4:$E$41)+1)/(MAX(Categories!$E$4:$E$41)-MIN(Categories!$E$4:$E$41)+1)*100 -> 99.439863 | F14: =(Categories!F15-MIN(Categories!$F$4:$F$41)+1)/(MAX(Categories!$F$4:$F$41)-MIN(Categories!$F$4:$F$41)+1)*100 -> 86.246314
... A40: =RawData!A40 -> United States | B40: =(Categories!B41-MIN(Categories!$B$4:$B$41)+1)/(MAX(Categories!$B$4:$B$41)-MIN(Categories!$B$4:$B$41)+1)*100 -> 71.010113 | C40: =(Categories!C41-MIN(Categories!$C$4:$C$41)+1)/(MAX(Categories!$C$4:$C$41)-MIN(Categories!$C$4:$C$41)+1)*100 -> 91.508202 | D40: =(Categories!D41-MIN(Categories!$D$4:$D$41)+1)/(MAX(Categories!$D$4:$D$41)-MIN(Categories!$D$4:$D$41)+1)*100 -> 47.594818 | E40: =(Categories!E41-MIN(Categories!$E$4:$E$41)+1)/(MAX(Categories!$E$4:$E$41)-MIN(Categories!$E$4:$E$41)+1)*100 -> 63.354738 | F40: =(Categories!F41-MIN(Categories!$F$4:$F$41)+1)/(MAX(Categories!$F$4:$F$41)-MIN(Categories!$F$4:$F$41)+1)*100 -> 55.097082

Sheet Results
A1: Results — Final Score and Ranking (LIVE)
A2: Final = score2(AVERAGE of the 5 RAW (pre-rescale) category scores).
A4: country | B4: corporate score | C4: consumption score | D4: property score | E4: income score | F4: cross_border score | G4: corporate rank | H4: consumption rank | I4: property rank | J4: income rank | K4: cross_border rank | L4: final score | M4: final rank | N4: final_raw (helper)
A5: =RawData!A3 -> Austria | B5: =CategoriesScored!B3 -> 65.327665 | C5: =CategoriesScored!C3 -> 58.838918 | D5: =CategoriesScored!D3 -> 62.660507 | E5: =CategoriesScored!E3 -> 58.319017 | F5: =CategoriesScored!F3 -> 77.000281 | G5: =RANK(B5,$B$5:$B$42,0) -> 19 | H5: =RANK(C5,$C$5:$C$42,0) -> 16 | I5: =RANK(D5,$D$5:$D$42,0) -> 17 | J5: =RANK(E5,$E$5:$E$42,0) -> 26 | K5: =RANK(F5,$F$5:$F$42,0) -> 16 | L5: =(N5-MIN($N$5:$N$42)+1)/(MAX($N$5:$N$42)-MIN($N$5:$N$42)+1)*100 -> 69.645656 | M5: =RANK(L5,$L$5:$L$42,0) -> 19 | N5: =(Categories!B4+Categories!C4+Categories!D4+Categories!E4+Categories!F4)/5 -> -0.010195524
A6: =RawData!A4 -> Australia | B6: =CategoriesScored!B4 -> 55.482643 | C6: =CategoriesScored!C4 -> 81.758543 | D6: =CategoriesScored!D4 -> 88.253548 | E6: =CategoriesScored!E4 -> 69.935712 | F6: =CategoriesScored!F4 -> 62.565111 | G6: =RANK(B6,$B$5:$B$42,0) -> 29 | H6: =RANK(C6,$C$5:$C$42,0) -> 9 | I6: =RANK(D6,$D$5:$D$42,0) -> 2 | J6: =RANK(E6,$E$5:$E$42,0) -> 15 | K6: =RANK(F6,$F$5:$F$42,0) -> 33 | L6: =(N6-MIN($N$5:$N$42)+1)/(MAX($N$5:$N$42)-MIN($N$5:$N$42)+1)*100 -> 79.684171 | M6: =RANK(L6,$L$5:$L$42,0) -> 7 | N6: =(Categories!B5+Categories!C5+Categories!D5+Categories!E5+Categories!F5)/5 -> 0.2091218
A7: =RawData!A5 -> Belgium | B7: =CategoriesScored!B5 -> 66.299742 | C7: =CategoriesScored!C5 -> 50.624135 | D7: =CategoriesScored!D5 -> 44.100453 | E7: =CategoriesScored!E5 -> 73.323211 | F7: =CategoriesScored!F5 -> 67.367833 | G7: =RANK(B7,$B$5:$B$42,0) -> 18 | H7: =RANK(C7,$C$5:$C$42,0) -> 27 | I7: =RANK(D7,$D$5:$D$42,0) -> 32 | J7: =RANK(E7,$E$5:$E$42,0) -> 13 | K7: =RANK(F7,$F$5:$F$42,0) -> 27 | L7: =(N7-MIN($N$5:$N$42)+1)/(MAX($N$5:$N$42)-MIN($N$5:$N$42)+1)*100 -> 63.246462 | M7: =RANK(L7,$L$5:$L$42,0) -> 30 | N7: =(Categories!B6+Categories!C6+Categories!D6+Categories!E6+Categories!F6)/5 -> -0.15000246
A8: =RawData!A6 -> Canada | B8: =CategoriesScored!B6 -> 61.562728 | C8: =CategoriesScored!C6 -> 83.543284 | D8: =CategoriesScored!D6 -> 58.681947 | E8: =CategoriesScored!E6 -> 58.067783 | F8: =CategoriesScored!F6 -> 74.304857 | G8: =RANK(B8,$B$5:$B$42,0) -> 22 | H8: =RANK(C8,$C$5:$C$42,0) -> 7 | I8: =RANK(D8,$D$5:$D$42,0) -> 25 | J8: =RANK(E8,$E$5:$E$42,0) -> 27 | K8: =RANK(F8,$F$5:$F$42,0) -> 18 | L8: =(N8-MIN($N$5:$N$42)+1)/(MAX($N$5:$N$42)-MIN($N$5:$N$42)+1)*100 -> 73.898955 | M8: =RANK(L8,$L$5:$L$42,0) -> 13 | N8: =(Categories!B7+Categories!C7+Categories!D7+Categories!E7+Categories!F7)/5 -> 0.082728791
A9: =RawData!A7 -> Switzerland | B9: =CategoriesScored!B7 -> 70.430459 | C9: =CategoriesScored!C7 -> 93.513025 | D9: =CategoriesScored!D7 -> 36.343546 | E9: =CategoriesScored!E7 -> 84.681127 | F9: =CategoriesScored!F7 -> 100 | G9: =RANK(B9,$B$5:$B$42,0) -> 10 | H9: =RANK(C9,$C$5:$C$42,0) -> 2 | I9: =RANK(D9,$D$5:$D$42,0) -> 36 | J9: =RANK(E9,$E$5:$E$42,0) -> 8 | K9: =RANK(F9,$F$5:$F$42,0) -> 1 | L9: =(N9-MIN($N$5:$N$42)+1)/(MAX($N$5:$N$42)-MIN($N$5:$N$42)+1)*100 -> 86.022021 | M9: =RANK(L9,$L$5:$L$42,0) -> 4 | N9: =(Categories!B8+Categories!C8+Categories!D8+Categories!E8+Categories!F8)/5 -> 0.34758853
A10: =RawData!A8 -> Chile | B10: =CategoriesScored!B8 -> 53.220875 | C10: =CategoriesScored!C8 -> 76.92093 | D10: =CategoriesScored!D8 -> 72.054601 | E10: =CategoriesScored!E8 -> 59.74418 | F10: =CategoriesScored!F8 -> 36.087037 | G10: =RANK(B10,$B$5:$B$42,0) -> 32 | H10: =RANK(C10,$C$5:$C$42,0) -> 10 | I10: =RANK(D10,$D$5:$D$42,0) -> 11 | J10: =RANK(E10,$E$5:$E$42,0) -> 24 | K10: =RANK(F10,$F$5:$F$42,0) -> 38 | L10: =(N10-MIN($N$5:$N$42)+1)/(MAX($N$5:$N$42)-MIN($N$5:$N$42)+1)*100 -> 63.784253 | M10: =RANK(L10,$L$5:$L$42,0) -> 28 | N10: =(Categories!B9+Categories!C9+Categories!D9+Categories!E9+Categories!F9)/5 -> -0.13825302
A11: =RawData!A9 -> Colombia | B11: =CategoriesScored!B9 -> 40.561338 | C11: =CategoriesScored!C9 -> 59.083414 | D11: =CategoriesScored!D9 -> 42.508961 | E11: =CategoriesScored!E9 -> 74.756331 | F11: =CategoriesScored!F9 -> 42.794384 | G11: =RANK(B11,$B$5:$B$42,0) -> 37 | H11: =RANK(C11,$C$5:$C$42,0) -> 15 | I11: =RANK(D11,$D$5:$D$42,0) -> 33 | J11: =RANK(E11,$E$5:$E$42,0) -> 12 | K11: =RANK(F11,$F$5:$F$42,0) -> 37 | L11: =(N11-MIN($N$5:$N$42)+1)/(MAX($N$5:$N$42)-MIN($N$5:$N$42)+1)*100 -> 51.148388 | M11: =RANK(L11,$L$5:$L$42,0) -> 36 | N11: =(Categories!B10+Categories!C10+Categories!D10+Categories!E10+Categories!F10)/5 -> -0.41431617
A12: =RawData!A10 -> Costa Rica | B12: =CategoriesScored!B10 -> 48.039362 | C12: =CategoriesScored!C10 -> 84.071792 | D12: =CategoriesScored!D10 -> 70.783269 | E12: =CategoriesScored!E10 -> 60.570203 | F12: =CategoriesScored!F10 -> 65.043553 | G12: =RANK(B12,$B$5:$B$42,0) -> 34 | H12: =RANK(C12,$C$5:$C$42,0) -> 6 | I12: =RANK(D12,$D$5:$D$42,0) -> 12 | J12: =RANK(E12,$E$5:$E$42,0) -> 23 | K12: =RANK(F12,$F$5:$F$42,0) -> 30 | L12: =(N12-MIN($N$5:$N$42)+1)/(MAX($N$5:$N$42)-MIN($N$5:$N$42)+1)*100 -> 71.421304 | M12: =RANK(L12,$L$5:$L$42,0) -> 17 | N12: =(Categories!B11+Categories!C11+Categories!D11+Categories!E11+Categories!F11)/5 -> 0.028598117
A13: =RawData!A11 -> Czech Republic | B13: =CategoriesScored!B11 -> 72.632849 | C13: =CategoriesScored!C11 -> 42.053176 | D13: =CategoriesScored!D11 -> 77.279995 | E13: =CategoriesScored!E11 -> 80.087932 | F13: =CategoriesScored!F11 -> 81.336507 | G13: =RANK(B13,$B$5:$B$42,0) -> 8 | H13: =RANK(C13,$C$5:$C$42,0) -> 32 | I13: =RANK(D13,$D$5:$D$42,0) -> 6 | J13: =RANK(E13,$E$5:$E$42,0) -> 10 | K13: =RANK(F13,$F$5:$F$42,0) -> 11 | L13: =(N13-MIN($N$5:$N$42)+1)/(MAX($N$5:$N$42)-MIN($N$5:$N$42)+1)*100 -> 77.363309 | M13: =RANK(L13,$L$5:$L$42,0) -> 10 | N13: =(Categories!B12+Categories!C12+Categories!D12+Categories!E12+Categories!F12)/5 -> 0.15841656
A14: =RawData!A12 -> Germany | B14: =CategoriesScored!B12 -> 54.347446 | C14: =CategoriesScored!C12 -> 62.825987 | D14: =CategoriesScored!D12 -> 67.900343 | E14: =CategoriesScored!E12 -> 49.312318 | F14: =CategoriesScored!F12 -> 85.572487 | G14: =RANK(B14,$B$5:$B$42,0) -> 30 | H14: =RANK(C14,$C$5:$C$42,0) -> 13 | I14: =RANK(D14,$D$5:$D$42,0) -> 14 | J14: =RANK(E14,$E$5:$E$42,0) -> 33 | K14: =RANK(F14,$F$5:$F$42,0) -> 9 | L14: =(N14-MIN($N$5:$N$42)+1)/(MAX($N$5:$N$42)-MIN($N$5:$N$42)+1)*100 -> 68.886741 | M14: =RANK(L14,$L$5:$L$42,0) -> 20 | N14: =(Categories!B13+Categories!C13+Categories!D13+Categories!E13+Categories!F13)/5 -> -0.026775984
A15: =RawData!A13 -> Denmark | B15: =CategoriesScored!B13 -> 66.358845 | C15: =CategoriesScored!C13 -> 55.022573 | D15: =CategoriesScored!D13 -> 69.074568 | E15: =CategoriesScored!E13 -> 48.567341 | F15: =CategoriesScored!F13 -> 60.766708 | G15: =RANK(B15,$B$5:$B$42,0) -> 17 | H15: =RANK(C15,$C$5:$C$42,0) -> 19 | I15: =RANK(D15,$D$5:$D$42,0) -> 13 | J15: =RANK(E15,$E$5:$E$42,0) -> 36 | K15: =RANK(F15,$F$5:$F$42,0) -> 34 | L15: =(N15-MIN($N$5:$N$42)+1)/(MAX($N$5:$N$42)-MIN($N$5:$N$42)+1)*100 -> 64.290688 | M15: =RANK(L15,$L$5:$L$42,0) -> 27 | N15: =(Categories!B14+Categories!C14+Categories!D14+Categories!E14+Categories!F14)/5 -> -0.12718863
A16: =RawData!A14 -> Estonia | B16: =CategoriesScored!B14 -> 94.824499 | C16: =CategoriesScored!C14 -> 52.980449 | D16: =CategoriesScored!D14 -> 100 | E16: =CategoriesScored!E14 -> 99.439863 | F16: =CategoriesScored!F14 -> 86.246314 | G16: =RANK(B16,$B$5:$B$42,0) -> 2 | H16: =RANK(C16,$C$5:$C$42,0) -> 22 | I16: =RANK(D16,$D$5:$D$42,0) -> 1 | J16: =RANK(E16,$E$5:$E$42,0) -> 2 | K16: =RANK(F16,$F$5:$F$42,0) -> 7 | L16: =(N16-MIN($N$5:$N$42)+1)/(MAX($N$5:$N$42)-MIN($N$5:$N$42)+1)*100 -> 100 | M16: =RANK(L16,$L$5:$L$42,0) -> 1 | N16: =(Categories!B15+Categories!C15+Categories!D15+Categories!E15+Categories!F15)/5 -> 0.65297362
... A42: =RawData!A40 -> United States | B42: =CategoriesScored!B40 -> 71.010113 | C42: =CategoriesScored!C40 -> 91.508202 | D42: =CategoriesScored!D40 -> 47.594818 | E42: =CategoriesScored!E40 -> 63.354738 | F42: =CategoriesScored!F40 -> 55.097082 | G42: =RANK(B42,$B$5:$B$42,0) -> 9 | H42: =RANK(C42,$C$5:$C$42,0) -> 4 | I42: =RANK(D42,$D$5:$D$42,0) -> 30 | J42: =RANK(E42,$E$5:$E$42,0) -> 17 | K42: =RANK(F42,$F$5:$F$42,0) -> 35 | L42: =(N42-MIN($N$5:$N$42)+1)/(MAX($N$5:$N$42)-MIN($N$5:$N$42)+1)*100 -> 72.477951 | M42: =RANK(L42,$L$5:$L$42,0) -> 15 | N42: =(Categories!B41+Categories!C41+Categories!D41+Categories!E41+Categories!F41)/5 -> 0.051683289
